Workbook

Sheet Store_Kiosk
A1: Classroom Store Kiosk
A4: 1. Scan Student Card
A6: 2. Store Item ID
A7: 3. Quantity
A9: Result | B9: Enter Card ID, Item ID, and Quantity, then press Purchase.
A11: Available Store Items
A12: Item ID | B12: Item Name | D12: Price | E12: Inventory | F12: Category | G12: Description
A13: =IFERROR(__xludf.DUMMYFUNCTION("FILTER( { Imported_Store!A1:A1000, Imported_Store!B1:B1000, IF(ROW(Imported_Store!A1:A1000),"""",), Imported_Store!C1:C1000, Imported_Store!E1:G1000 }, Imported_Store!A1:A1000<>"""", Imported_Store!D1:D1000=""Yes"" )"),7734.0) -> 7734 | B13: =IFERROR(__xludf.DUMMYFUNCTION("""COMPUTED_VALUE"""),"Extra credit 1%") -> Extra credit 1% | D13: =IFERROR(__xludf.DUMMYFUNCTION("""COMPUTED_VALUE"""),100.0) -> 100 | E13: =IFERROR(__xludf.DUMMYFUNCTION("""COMPUTED_VALUE"""),76.0) -> 76 | F13: =IFERROR(__xludf.DUMMYFUNCTION("""COMPUTED_VALUE"""),"Academic") -> Academic | G13: =IFERROR(__xludf.DUMMYFUNCTION("""COMPUTED_VALUE"""),"Get 1% extra credit on an assignment") -> Get 1% extra credit on an assignment

Sheet Student_Profile_Display
A1: Student Profile
A4: Scan Student Card | C4: Scan student card to display profile. | F4: Inventory
F5: Item | G5: Category | H5: Quantity | I5: Total Spent | J5: Last Purchased
A6: Student Name | B6: {=IF($B$4="","",IFNA(XLOOKUP($B$4,Imported_Students!$A:$A,Imported_Students!$B:$B),"Unknown card"))} | C6: Total Deposits | D6: =IF($B$4="","",SUMIFS(Imported_Transactions!$F:$F,Imported_Transactions!$C:$C,$B$4,Imported_Transactions!$E:$E,"DEPOSIT",Imported_Transactions!$L:$L,"Success")) | F6: =IFERROR(__xludf.DUMMYFUNCTION("IF($B$4="""","""",IFNA(QUERY(SORT(FILTER({Imported_Inventory!$D$2:$D70,Imported_Inventory!$E$2:$E70,Imported_Inventory!$F$2:$F70,Imported_Inventory!$G$2:$G70,Imported_Inventory!$H$2:$H70},Imported_Inventory!$A$2:$A70=$B$4,Imported_Inventory!$F$2:$F70>0),5"&",FALSE),""limit 8"",0),""No inventory found""))"),"")
A7: Grade | B7: {=IF($B$4="","",IFNA(XLOOKUP($B$4,Imported_Students!$A:$A,Imported_Students!$C:$C),""))} | C7: Total Withdrawals | D7: =IF($B$4="","",SUMIFS(Imported_Transactions!$F:$F,Imported_Transactions!$C:$C,$B$4,Imported_Transactions!$E:$E,"WITHDRAW",Imported_Transactions!$L:$L,"Success"))
A8: Homeroom | B8: {=IF($B$4="","",IFNA(XLOOKUP($B$4,Imported_Students!$A:$A,Imported_Students!$D:$D),""))} | C8: Total Rewards | D8: =IF($B$4="","",SUMIFS(Imported_Transactions!$F:$F,Imported_Transactions!$C:$C,$B$4,Imported_Transactions!$E:$E,"REWARD",Imported_Transactions!$L:$L,"Success"))
A9: Current Balance | B9: {=IF($B$4="","",IFNA(XLOOKUP($B$4,Imported_Students!$A:$A,Imported_Students!$E:$E),0))} | C9: Total Fines | D9: =IF($B$4="","",SUMIFS(Imported_Transactions!$F:$F,Imported_Transactions!$C:$C,$B$4,Imported_Transactions!$E:$E,"FINE",Imported_Transactions!$L:$L,"Success"))
A10: Job Title | B10: {=IF($B$4="","",IFNA(XLOOKUP($B$4,Imported_Students!$A:$A,Imported_Students!$F:$F),"No job assigned"))} | C10: Store Purchases | D10: =IF($B$4="","",COUNTIFS(Imported_Transactions!$C:$C,$B$4,Imported_Transactions!$E:$E,"STORE_PURCHASE",Imported_Transactions!$L:$L,"Success"))
A11: Attendance Streak (Days) | B11: {=IF($B$4="","",IFNA(XLOOKUP($B$4,Imported_Students!$A:$A,Imported_Students!$G:$G),0))} | C11: Total Spent | D11: =IF($B$4="","",SUMIFS(Imported_Transactions!$F:$F,Imported_Transactions!$C:$C,$B$4,Imported_Transactions!$E:$E,"STORE_PURCHASE",Imported_Transactions!$L:$L,"Success"))
A14: Recent Transactions | G14: Purchase History
A15: Date/Time | B15: Type | C15: Amount | D15: Ending Balance | E15: Note | G15: Date/Time | H15: Type | I15: Amount | J15: Balance After | K15: Note
A16: =IFERROR(__xludf.DUMMYFUNCTION("IF($B$4="""","""", IFNA( QUERY( SORT( FILTER( {Transactions!$A$2:$A70,Transactions!$E$2:$E70,Transactions!$F$2:$F70,Transactions!$H$2:$H70,Transactions!$K$2:$K70}, Transactions!$C$2:$C70=$B$4, Transactions!$L$2:$L70=""Success"", "&" NOT(REGEXMATCH(UPPER(Transactions!$E$2:$E70&"" ""&Transactions!$F$2:$F70&"" ""&Transactions!$H$2:$H70&"" ""&Transactions!$K$2:$K70),""REWARD|FINE"")) ), 1,FALSE ), ""limit 10"", 0 ), ""No transactions found"" ) )"),"") | G16: =IFERROR(__xludf.DUMMYFUNCTION("IF($B$4="""","""",IFNA(QUERY(SORT(FILTER({Transactions!$A$2:$A70,Transactions!$E$2:$E70,Transactions!$F$2:$F70,Transactions!$H$2:$H70,Transactions!$K$2:$K70},Transactions!$C$2:$C70=$B$4,Transactions!$E$2:$E70=""STORE_PURCHASE"",Transactions!$L$2:$L70=""Su"&"ccess""),1,FALSE),""limit 10"",0),""No purchases found""))"),"")
A27: Attendance History | G27: Rewards / Fines
A28: Date/Time | B28: Checkin Time | C28: Status | D28: Note | G28: Date/Time | H28: Type | I28: Amount | J28: Balance After | K28: Note
A29: =IFERROR(__xludf.DUMMYFUNCTION("IF($B$4="""","""",IFNA(QUERY(SORT(FILTER({Imported_Attendance!$A$2:$A70,Imported_Attendance!$I$2:$I70,Imported_Attendance!$H$2:$H70},Imported_Attendance!$C$2:$C70=$B$4),1,FALSE),""limit 10"",0),""No attendance records found""))"),"") | G29: =IFERROR(__xludf.DUMMYFUNCTION("IF($B$4="""","""",IFNA(QUERY(SORT(FILTER({Imported_Transactions!$A$2:$A70,Imported_Transactions!$E$2:$E70,Imported_Transactions!$F$2:$F70,Imported_Transactions!$H$2:$H70,Imported_Transactions!$K$2:$K70},Imported_Transactions!$C$2:$C70=$B$4,REGEXMATCH(Impo"&"rted_Transactions!$E$2:$E70,""REWARD|FINE""),Imported_Transactions!$L$2:$L70=""Success""),1,FALSE),""limit 10"",0),""No rewards or fines found""))"),"")
A39: Stock Portfolio
A40: Ticker | B40: Shares_Owned | C40: Avg_Buy_Price | D40: Total_Cost | E40: Last_Updated
A41: =IFERROR(__xludf.DUMMYFUNCTION("IF($B$4="""","""",IFNA( QUERY( SORT( FILTER( {Imported_Stock_Portfolio!$C$2:$C70,Imported_Stock_Portfolio!$D$2:$D70,Imported_Stock_Portfolio!$E$2:$E70,Imported_Stock_Portfolio!$F$2:$F70,Imported_Stock_Portfolio!$G$2:$G70}, Imported_Stock_Portfolio!$A$2:$A"&"70=$B$4 ), 5,FALSE ), ""limit 10"",0 ), ""No stock holdings found""))"),"")

Sheet Student_Portfolio_Display
A1: Student Stock Portfolio
A3: Scan Student Card | B3: ae072910
A5: Result | B5: Scan a student card, then run Load Stock Portfolio.
A8: Ticker | B8: Shares Owned | C8: Avg Buy Price | D8: Current Price | E8: Market Value | F8: Unrealized Gain/Loss | G8: Last Updated
A9: =IFERROR(__xludf.DUMMYFUNCTION("IF($B$3="""","""",IFNA( QUERY( SORT( FILTER( {Imported_Stock_Portfolio!$C$2:$C73,Imported_Stock_Portfolio!$D$2:$D73,Imported_Stock_Portfolio!$E$2:$E73,Imported_Stock_Portfolio!$G$2:$G73,Imported_Stock_Portfolio!$H$2:$H73,Imported_Stock_Portfolio!$I$2:$I73"&",Imported_Stock_Portfolio!$J$2:$J73}, Imported_Stock_Portfolio!$A$2:$A73=$B$3 ), 5,FALSE ), ""limit 10"",0 ), ""No stock holdings found""))"),"RIDE") -> RIDE | B9: =IFERROR(__xludf.DUMMYFUNCTION("""COMPUTED_VALUE"""),2.0) -> 2 | C9: =IFERROR(__xludf.DUMMYFUNCTION("""COMPUTED_VALUE"""),41.11) -> 41.11 | D9: =IFERROR(__xludf.DUMMYFUNCTION("""COMPUTED_VALUE"""),98.16999999999825) -> 98.17 | E9: =IFERROR(__xludf.DUMMYFUNCTION("""COMPUTED_VALUE"""),196.34) -> 196.34 | F9: =IFERROR(__xludf.DUMMYFUNCTION("""COMPUTED_VALUE"""),114.12) -> 114.12 | G9: =IFERROR(__xludf.DUMMYFUNCTION("""COMPUTED_VALUE"""),46187.706655092596) -> 46187.707
A10: =IFERROR(__xludf.DUMMYFUNCTION("""COMPUTED_VALUE"""),"LOAN") -> LOAN | B10: =IFERROR(__xludf.DUMMYFUNCTION("""COMPUTED_VALUE"""),1.0) -> 1 | C10: =IFERROR(__xludf.DUMMYFUNCTION("""COMPUTED_VALUE"""),58.91) -> 58.91 | D10: =IFERROR(__xludf.DUMMYFUNCTION("""COMPUTED_VALUE"""),76.9900000000016) -> 76.99 | E10: =IFERROR(__xludf.DUMMYFUNCTION("""COMPUTED_VALUE"""),76.99) -> 76.99 | F10: =IFERROR(__xludf.DUMMYFUNCTION("""COMPUTED_VALUE"""),18.08) -> 18.08 | G10: =IFERROR(__xludf.DUMMYFUNCTION("""COMPUTED_VALUE"""),46187.706655092596) -> 46187.707

Sheet Imported_Students
A1: =IFERROR(__xludf.DUMMYFUNCTION("IMPORTRANGE(""https://docs.google.com/spreadsheets/d/1xmGsP2eOXdfhJ9DjzCOVFJKoZ2DuuwRb_dbNg1M77M8/edit?gid=138364344#gid=138364344"",""Students!A:J"")"),"Students / Card Registry") -> Students / Card Registry
A3: =IFERROR(__xludf.DUMMYFUNCTION("""COMPUTED_VALUE"""),"Card_ID") -> Card_ID | B3: =IFERROR(__xludf.DUMMYFUNCTION("""COMPUTED_VALUE"""),"Student_Name") -> Student_Name | C3: =IFERROR(__xludf.DUMMYFUNCTION("""COMPUTED_VALUE"""),"Grade") -> Grade | D3: =IFERROR(__xludf.DUMMYFUNCTION("""COMPUTED_VALUE"""),"Homeroom") -> Homeroom | E3: =IFERROR(__xludf.DUMMYFUNCTION("""COMPUTED_VALUE"""),"Balance") -> Balance | F3: =IFERROR(__xludf.DUMMYFUNCTION("""COMPUTED_VALUE"""),"Job_Title") -> Job_Title | G3: =IFERROR(__xludf.DUMMYFUNCTION("""COMPUTED_VALUE"""),"Active") -> Active | H3: =IFERROR(__xludf.DUMMYFUNCTION("""COMPUTED_VALUE"""),"Last_Updated") -> Last_Updated | I3: =IFERROR(__xludf.DUMMYFUNCTION("""COMPUTED_VALUE"""),"Attendance_Streak") -> Attendance_Streak | J3: =IFERROR(__xludf.DUMMYFUNCTION("""COMPUTED_VALUE"""),"Last_Attendance_Date") -> Last_Attendance_Date
A4: =IFERROR(__xludf.DUMMYFUNCTION("""COMPUTED_VALUE"""),"ba353911") -> ba353911 | B4: =IFERROR(__xludf.DUMMYFUNCTION("""COMPUTED_VALUE"""),"Dayeon Kang") -> Dayeon Kang | C4: =IFERROR(__xludf.DUMMYFUNCTION("""COMPUTED_VALUE"""),10.0) -> 10 | D4: =IFERROR(__xludf.DUMMYFUNCTION("""COMPUTED_VALUE"""),"HS202") -> HS202 | E4: =IFERROR(__xludf.DUMMYFUNCTION("""COMPUTED_VALUE"""),341.98) -> 341.98 | F4: =IFERROR(__xludf.DUMMYFUNCTION("""COMPUTED_VALUE"""),"-") -> - | G4: =IFERROR(__xludf.DUMMYFUNCTION("""COMPUTED_VALUE"""),"Yes") -> Yes | H4: =IFERROR(__xludf.DUMMYFUNCTION("""COMPUTED_VALUE"""),46184.3566087963) -> 46184.357 | I4: =IFERROR(__xludf.DUMMYFUNCTION("""COMPUTED_VALUE"""),4.0) -> 4 | J4: =IFERROR(__xludf.DUMMYFUNCTION("""COMPUTED_VALUE"""),46184.0) -> 46184
A5: =IFERROR(__xludf.DUMMYFUNCTION("""COMPUTED_VALUE"""),"dc04eef4") -> dc04eef4 | B5: =IFERROR(__xludf.DUMMYFUNCTION("""COMPUTED_VALUE"""),"Joshua Jung") -> Joshua Jung | C5: =IFERROR(__xludf.DUMMYFUNCTION("""COMPUTED_VALUE"""),10.0) -> 10 | D5: =IFERROR(__xludf.DUMMYFUNCTION("""COMPUTED_VALUE"""),"HS202") -> HS202 | E5: =IFERROR(__xludf.DUMMYFUNCTION("""COMPUTED_VALUE"""),234.86) -> 234.86 | F5: =IFERROR(__xludf.DUMMYFUNCTION("""COMPUTED_VALUE"""),"-") -> - | G5: =IFERROR(__xludf.DUMMYFUNCTION("""COMPUTED_VALUE"""),"Yes") -> Yes | H5: =IFERROR(__xludf.DUMMYFUNCTION("""COMPUTED_VALUE"""),46185.35445601852) -> 46185.354 | I5: =IFERROR(__xludf.DUMMYFUNCTION("""COMPUTED_VALUE"""),5.0) -> 5 | J5: =IFERROR(__xludf.DUMMYFUNCTION("""COMPUTED_VALUE"""),46185.0) -> 46185
A6: =IFERROR(__xludf.DUMMYFUNCTION("""COMPUTED_VALUE"""),"5a032611") -> 5a032611 | B6: =IFERROR(__xludf.DUMMYFUNCTION("""COMPUTED_VALUE"""),"Harold Dou") -> Harold Dou | C6: =IFERROR(__xludf.DUMMYFUNCTION("""COMPUTED_VALUE"""),10.0) -> 10 | D6: =IFERROR(__xludf.DUMMYFUNCTION("""COMPUTED_VALUE"""),"HS202") -> HS202 | E6: =IFERROR(__xludf.DUMMYFUNCTION("""COMPUTED_VALUE"""),198.0) -> 198 | F6: =IFERROR(__xludf.DUMMYFUNCTION("""COMPUTED_VALUE"""),"-") -> - | G6: =IFERROR(__xludf.DUMMYFUNCTION("""COMPUTED_VALUE"""),"Yes") -> Yes | H6: =IFERROR(__xludf.DUMMYFUNCTION("""COMPUTED_VALUE"""),46184.60606481481) -> 46184.606 | I6: =IFERROR(__xludf.DUMMYFUNCTION("""COMPUTED_VALUE"""),1.0) -> 1 | J6: =IFERROR(__xludf.DUMMYFUNCTION("""COMPUTED_VALUE"""),46184.0) -> 46184
A7: =IFERROR(__xludf.DUMMYFUNCTION("""COMPUTED_VALUE"""),"7c4e261e") -> 7c4e261e | B7: =IFERROR(__xludf.DUMMYFUNCTION("""COMPUTED_VALUE"""),"Suha Lee") -> Suha Lee | C7: =IFERROR(__xludf.DUMMYFUNCTION("""COMPUTED_VALUE"""),10.0) -> 10 | D7: =IFERROR(__xludf.DUMMYFUNCTION("""COMPUTED_VALUE"""),"HS202") -> HS202 | E7: =IFERROR(__xludf.DUMMYFUNCTION("""COMPUTED_VALUE"""),49.83) -> 49.83 | F7: =IFERROR(__xludf.DUMMYFUNCTION("""COMPUTED_VALUE"""),"-") -> - | G7: =IFERROR(__xludf.DUMMYFUNCTION("""COMPUTED_VALUE"""),"Yes") -> Yes | H7: =IFERROR(__xludf.DUMMYFUNCTION("""COMPUTED_VALUE"""),46185.35123842592) -> 46185.351 | I7: =IFERROR(__xludf.DUMMYFUNCTION("""COMPUTED_VALUE"""),4.0) -> 4 | J7: =IFERROR(__xludf.DUMMYFUNCTION("""COMPUTED_VALUE"""),46185.0) -> 46185
A8: =IFERROR(__xludf.DUMMYFUNCTION("""COMPUTED_VALUE"""),"ba0fc5c4") -> ba0fc5c4 | B8: =IFERROR(__xludf.DUMMYFUNCTION("""COMPUTED_VALUE"""),"Junwoo Kang") -> Junwoo Kang | C8: =IFERROR(__xludf.DUMMYFUNCTION("""COMPUTED_VALUE"""),10.0) -> 10 | D8: =IFERROR(__xludf.DUMMYFUNCTION("""COMPUTED_VALUE"""),"HS202") -> HS202 | E8: =IFERROR(__xludf.DUMMYFUNCTION("""COMPUTED_VALUE"""),4.19) -> 4.19 | F8: =IFERROR(__xludf.DUMMYFUNCTION("""COMPUTED_VALUE"""),"-") -> - | G8: =IFERROR(__xludf.DUMMYFUNCTION("""COMPUTED_VALUE"""),"Yes") -> Yes | H8: =IFERROR(__xludf.DUMMYFUNCTION("""COMPUTED_VALUE"""),46184.50125) -> 46184.501 | I8: =IFERROR(__xludf.DUMMYFUNCTION("""COMPUTED_VALUE"""),0.0) -> 0 | J8: =IFERROR(__xludf.DUMMYFUNCTION("""COMPUTED_VALUE"""),46181.0) -> 46181
A9: =IFERROR(__xludf.DUMMYFUNCTION("""COMPUTED_VALUE"""),"ba912211") -> ba912211 | B9: =IFERROR(__xludf.DUMMYFUNCTION("""COMPUTED_VALUE"""),"Daisy Doh") -> Daisy Doh | C9: =IFERROR(__xludf.DUMMYFUNCTION("""COMPUTED_VALUE"""),10.0) -> 10 | D9: =IFERROR(__xludf.DUMMYFUNCTION("""COMPUTED_VALUE"""),"HS202") -> HS202 | E9: =IFERROR(__xludf.DUMMYFUNCTION("""COMPUTED_VALUE"""),483.88) -> 483.88 | F9: =IFERROR(__xludf.DUMMYFUNCTION("""COMPUTED_VALUE"""),"-") -> - | G9: =IFERROR(__xludf.DUMMYFUNCTION("""COMPUTED_VALUE"""),"Yes") -> Yes | H9: =IFERROR(__xludf.DUMMYFUNCTION("""COMPUTED_VALUE"""),46185.34641203703) -> 46185.346 | I9: =IFERROR(__xludf.DUMMYFUNCTION("""COMPUTED_VALUE"""),5.0) -> 5 | J9: =IFERROR(__xludf.DUMMYFUNCTION("""COMPUTED_VALUE"""),46185.0) -> 46185
A10: =IFERROR(__xludf.DUMMYFUNCTION("""COMPUTED_VALUE"""),"5c07fef4") -> 5c07fef4 | B10: =IFERROR(__xludf.DUMMYFUNCTION("""COMPUTED_VALUE"""),"Tiffany Kim") -> Tiffany Kim | C10: =IFERROR(__xludf.DUMMYFUNCTION("""COMPUTED_VALUE"""),10.0) -> 10 | D10: =IFERROR(__xludf.DUMMYFUNCTION("""COMPUTED_VALUE"""),"HS202") -> HS202 | E10: =IFERROR(__xludf.DUMMYFUNCTION("""COMPUTED_VALUE"""),430.0) -> 430 | F10: =IFERROR(__xludf.DUMMYFUNCTION("""COMPUTED_VALUE"""),"-") -> - | G10: =IFERROR(__xludf.DUMMYFUNCTION("""COMPUTED_VALUE"""),"Yes") -> Yes | H10: =IFERROR(__xludf.DUMMYFUNCTION("""COMPUTED_VALUE"""),46185.346180555556) -> 46185.346 | I10: =IFERROR(__xludf.DUMMYFUNCTION("""COMPUTED_VALUE"""),5.0) -> 5 | J10: =IFERROR(__xludf.DUMMYFUNCTION("""COMPUTED_VALUE"""),46185.0) -> 46185
A11: =IFERROR(__xludf.DUMMYFUNCTION("""COMPUTED_VALUE"""),"babde4c4") -> babde4c4 | B11: =IFERROR(__xludf.DUMMYFUNCTION("""COMPUTED_VALUE"""),"Ashley Guk") -> Ashley Guk | C11: =IFERROR(__xludf.DUMMYFUNCTION("""COMPUTED_VALUE"""),10.0) -> 10 | D11: =IFERROR(__xludf.DUMMYFUNCTION("""COMPUTED_VALUE"""),"HS202") -> HS202 | E11: =IFERROR(__xludf.DUMMYFUNCTION("""COMPUTED_VALUE"""),616.0) -> 616 | F11: =IFERROR(__xludf.DUMMYFUNCTION("""COMPUTED_VALUE"""),"-") -> - | G11: =IFERROR(__xludf.DUMMYFUNCTION("""COMPUTED_VALUE"""),"Yes") -> Yes | H11: =IFERROR(__xludf.DUMMYFUNCTION("""COMPUTED_VALUE"""),46184.35596064815) -> 46184.356 | I11: =IFERROR(__xludf.DUMMYFUNCTION("""COMPUTED_VALUE"""),1.0) -> 1 | J11: =IFERROR(__xludf.DUMMYFUNCTION("""COMPUTED_VALUE"""),46184.0) -> 46184
A12: =IFERROR(__xludf.DUMMYFUNCTION("""COMPUTED_VALUE"""),"ae072910") -> ae072910 | B12: =IFERROR(__xludf.DUMMYFUNCTION("""COMPUTED_VALUE"""),"Selena Jung") -> Selena Jung | C12: =IFERROR(__xludf.DUMMYFUNCTION("""COMPUTED_VALUE"""),10.0) -> 10 | D12: =IFERROR(__xludf.DUMMYFUNCTION("""COMPUTED_VALUE"""),"HS202") -> HS202 | E12: =IFERROR(__xludf.DUMMYFUNCTION("""COMPUTED_VALUE"""),353.79) -> 353.79 | F12: =IFERROR(__xludf.DUMMYFUNCTION("""COMPUTED_VALUE"""),"-") -> - | G12: =IFERROR(__xludf.DUMMYFUNCTION("""COMPUTED_VALUE"""),"Yes") -> Yes | H12: =IFERROR(__xludf.DUMMYFUNCTION("""COMPUTED_VALUE"""),46184.351122685184) -> 46184.351 | I12: =IFERROR(__xludf.DUMMYFUNCTION("""COMPUTED_VALUE"""),4.0) -> 4 | J12: =IFERROR(__xludf.DUMMYFUNCTION("""COMPUTED_VALUE"""),46184.0) -> 46184
A13: =IFERROR(__xludf.DUMMYFUNCTION("""COMPUTED_VALUE"""),"1e3e1410") -> 1e3e1410 | B13: =IFERROR(__xludf.DUMMYFUNCTION("""COMPUTED_VALUE"""),"Junjae Park") -> Junjae Park | C13: =IFERROR(__xludf.DUMMYFUNCTION("""COMPUTED_VALUE"""),10.0) -> 10 | D13: =IFERROR(__xludf.DUMMYFUNCTION("""COMPUTED_VALUE"""),"HS202") -> HS202 | E13: =IFERROR(__xludf.DUMMYFUNCTION("""COMPUTED_VALUE"""),27.98) -> 27.98 | F13: =IFERROR(__xludf.DUMMYFUNCTION("""COMPUTED_VALUE"""),"-") -> - | G13: =IFERROR(__xludf.DUMMYFUNCTION("""COMPUTED_VALUE"""),"Yes") -> Yes | H13: =IFERROR(__xludf.DUMMYFUNCTION("""COMPUTED_VALUE"""),46185.64902777778) -> 46185.649 | I13: =IFERROR(__xludf.DUMMYFUNCTION("""COMPUTED_VALUE"""),5.0) -> 5 | J13: =IFERROR(__xludf.DUMMYFUNCTION("""COMPUTED_VALUE"""),46185.0) -> 46185
A14: =IFERROR(__xludf.DUMMYFUNCTION("""COMPUTED_VALUE"""),"9a5f2811") -> 9a5f2811 | B14: =IFERROR(__xludf.DUMMYFUNCTION("""COMPUTED_VALUE"""),"Junyoung Yoo") -> Junyoung Yoo | C14: =IFERROR(__xludf.DUMMYFUNCTION("""COMPUTED_VALUE"""),10.0) -> 10 | D14: =IFERROR(__xludf.DUMMYFUNCTION("""COMPUTED_VALUE"""),"HS202") -> HS202 | E14: =IFERROR(__xludf.DUMMYFUNCTION("""COMPUTED_VALUE"""),46.86) -> 46.86 | F14: =IFERROR(__xludf.DUMMYFUNCTION("""COMPUTED_VALUE"""),"-") -> - | G14: =IFERROR(__xludf.DUMMYFUNCTION("""COMPUTED_VALUE"""),"Yes") -> Yes | H14: =IFERROR(__xludf.DUMMYFUNCTION("""COMPUTED_VALUE"""),46184.467881944445) -> 46184.468 | I14: =IFERROR(__xludf.DUMMYFUNCTION("""COMPUTED_VALUE"""),0.0) -> 0 | J14: =IFERROR(__xludf.DUMMYFUNCTION("""COMPUTED_VALUE"""),46183.0) -> 46183
A15: =IFERROR(__xludf.DUMMYFUNCTION("""COMPUTED_VALUE"""),1321.0) -> 1321 | B15: =IFERROR(__xludf.DUMMYFUNCTION("""COMPUTED_VALUE"""),"Ahin") -> Ahin | C15: =IFERROR(__xludf.DUMMYFUNCTION("""COMPUTED_VALUE"""),7.0) -> 7 | D15: =IFERROR(__xludf.DUMMYFUNCTION("""COMPUTED_VALUE"""),"HS202") -> HS202 | E15: =IFERROR(__xludf.DUMMYFUNCTION("""COMPUTED_VALUE"""),743.61) -> 743.61 | F15: =IFERROR(__xludf.DUMMYFUNCTION("""COMPUTED_VALUE"""),"-") -> - | G15: =IFERROR(__xludf.DUMMYFUNCTION("""COMPUTED_VALUE"""),"Yes") -> Yes | H15: =IFERROR(__xludf.DUMMYFUNCTION("""COMPUTED_VALUE"""),46186.43682870371) -> 46186.437
A16: =IFERROR(__xludf.DUMMYFUNCTION("""COMPUTED_VALUE"""),4673.0) -> 4673 | B16: =IFERROR(__xludf.DUMMYFUNCTION("""COMPUTED_VALUE"""),"Ellie") -> Ellie | C16: =IFERROR(__xludf.DUMMYFUNCTION("""COMPUTED_VALUE"""),7.0) -> 7 | D16: =IFERROR(__xludf.DUMMYFUNCTION("""COMPUTED_VALUE"""),"HS203") -> HS203 | E16: =IFERROR(__xludf.DUMMYFUNCTION("""COMPUTED_VALUE"""),8764.1) -> 8764.1 | F16: =IFERROR(__xludf.DUMMYFUNCTION("""COMPUTED_VALUE"""),"-") -> - | G16: =IFERROR(__xludf.DUMMYFUNCTION("""COMPUTED_VALUE"""),"Yes") -> Yes | H16: =IFERROR(__xludf.DUMMYFUNCTION("""COMPUTED_VALUE"""),46185.53475694444) -> 46185.535
A17: =IFERROR(__xludf.DUMMYFUNCTION("""COMPUTED_VALUE"""),2217.0) -> 2217 | B17: =IFERROR(__xludf.DUMMYFUNCTION("""COMPUTED_VALUE"""),"DK") -> DK | C17: =IFERROR(__xludf.DUMMYFUNCTION("""COMPUTED_VALUE"""),7.0) -> 7 | D17: =IFERROR(__xludf.DUMMYFUNCTION("""COMPUTED_VALUE"""),"HS204") -> HS204 | E17: =IFERROR(__xludf.DUMMYFUNCTION("""COMPUTED_VALUE"""),8404.61) -> 8404.61 | F17: =IFERROR(__xludf.DUMMYFUNCTION("""COMPUTED_VALUE"""),"-") -> - | G17: =IFERROR(__xludf.DUMMYFUNCTION("""COMPUTED_VALUE"""),"Yes") -> Yes | H17: =IFERROR(__xludf.DUMMYFUNCTION("""COMPUTED_VALUE"""),46185.67994212963) -> 46185.68
A18: =IFERROR(__xludf.DUMMYFUNCTION("""COMPUTED_VALUE"""),1978.0) -> 1978 | B18: =IFERROR(__xludf.DUMMYFUNCTION("""COMPUTED_VALUE"""),"Hannah") -> Hannah | C18: =IFERROR(__xludf.DUMMYFUNCTION("""COMPUTED_VALUE"""),7.0) -> 7 | D18: =IFERROR(__xludf.DUMMYFUNCTION("""COMPUTED_VALUE"""),"HS205") -> HS205 | E18: =IFERROR(__xludf.DUMMYFUNCTION("""COMPUTED_VALUE"""),10028.2) -> 10028.2 | F18: =IFERROR(__xludf.DUMMYFUNCTION("""COMPUTED_VALUE"""),"-") -> - | G18: =IFERROR(__xludf.DUMMYFUNCTION("""COMPUTED_VALUE"""),"Yes") -> Yes | H18: =IFERROR(__xludf.DUMMYFUNCTION("""COMPUTED_VALUE"""),46178.54225694444) -> 46178.542
A19: =IFERROR(__xludf.DUMMYFUNCTION("""COMPUTED_VALUE"""),1876.0) -> 1876 | B19: =IFERROR(__xludf.DUMMYFUNCTION("""COMPUTED_VALUE"""),"Lena") -> Lena | C19: =IFERROR(__xludf.DUMMYFUNCTION("""COMPUTED_VALUE"""),7.0) -> 7 | D19: =IFERROR(__xludf.DUMMYFUNCTION("""COMPUTED_VALUE"""),"HS206") -> HS206 | E19: =IFERROR(__xludf.DUMMYFUNCTION("""COMPUTED_VALUE"""),311.09) -> 311.09 | F19: =IFERROR(__xludf.DUMMYFUNCTION("""COMPUTED_VALUE"""),"-") -> - | G19: =IFERROR(__xludf.DUMMYFUNCTION("""COMPUTED_VALUE"""),"Yes") -> Yes | H19: =IFERROR(__xludf.DUMMYFUNCTION("""COMPUTED_VALUE"""),46185.57885416667) -> 46185.579
A20: =IFERROR(__xludf.DUMMYFUNCTION("""COMPUTED_VALUE"""),8765.0) -> 8765 | B20: =IFERROR(__xludf.DUMMYFUNCTION("""COMPUTED_VALUE"""),"Minjun") -> Minjun | C20: =IFERROR(__xludf.DUMMYFUNCTION("""COMPUTED_VALUE"""),7.0) -> 7 | D20: =IFERROR(__xludf.DUMMYFUNCTION("""COMPUTED_VALUE"""),"HS207") -> HS207 | E20: =IFERROR(__xludf.DUMMYFUNCTION("""COMPUTED_VALUE"""),1135.58) -> 1135.58 | F20: =IFERROR(__xludf.DUMMYFUNCTION("""COMPUTED_VALUE"""),"-") -> - | G20: =IFERROR(__xludf.DUMMYFUNCTION("""COMPUTED_VALUE"""),"Yes") -> Yes | H20: =IFERROR(__xludf.DUMMYFUNCTION("""COMPUTED_VALUE"""),46187.40190972222) -> 46187.402
A21: =IFERROR(__xludf.DUMMYFUNCTION("""COMPUTED_VALUE"""),9887.0) -> 9887 | B21: =IFERROR(__xludf.DUMMYFUNCTION("""COMPUTED_VALUE"""),"Ruby") -> Ruby | C21: =IFERROR(__xludf.DUMMYFUNCTION("""COMPUTED_VALUE"""),7.0) -> 7 | D21: =IFERROR(__xludf.DUMMYFUNCTION("""COMPUTED_VALUE"""),"HS208") -> HS208 | E21: =IFERROR(__xludf.DUMMYFUNCTION("""COMPUTED_VALUE"""),1827.26) -> 1827.26 | F21: =IFERROR(__xludf.DUMMYFUNCTION("""COMPUTED_VALUE"""),"-") -> - | G21: =IFERROR(__xludf.DUMMYFUNCTION("""COMPUTED_VALUE"""),"Yes") -> Yes | H21: =IFERROR(__xludf.DUMMYFUNCTION("""COMPUTED_VALUE"""),46185.523518518516) -> 46185.524
A22: =IFERROR(__xludf.DUMMYFUNCTION("""COMPUTED_VALUE"""),7765.0) -> 7765 | B22: =IFERROR(__xludf.DUMMYFUNCTION("""COMPUTED_VALUE"""),"Yeonju") -> Yeonju | C22: =IFERROR(__xludf.DUMMYFUNCTION("""COMPUTED_VALUE"""),7.0) -> 7 | D22: =IFERROR(__xludf.DUMMYFUNCTION("""COMPUTED_VALUE"""),"HS209") -> HS209 | E22: =IFERROR(__xludf.DUMMYFUNCTION("""COMPUTED_VALUE"""),5263.92) -> 5263.92 | F22: =IFERROR(__xludf.DUMMYFUNCTION("""COMPUTED_VALUE"""),"-") -> - | G22: =IFERROR(__xludf.DUMMYFUNCTION("""COMPUTED_VALUE"""),"Yes") -> Yes | H22: =IFERROR(__xludf.DUMMYFUNCTION("""COMPUTED_VALUE"""),46185.44773148148) -> 46185.448
A23: =IFERROR(__xludf.DUMMYFUNCTION("""COMPUTED_VALUE"""),6665.0) -> 6665 | B23: =IFERROR(__xludf.DUMMYFUNCTION("""COMPUTED_VALUE"""),"Jinwoo") -> Jinwoo | C23: =IFERROR(__xludf.DUMMYFUNCTION("""COMPUTED_VALUE"""),7.0) -> 7 | D23: =IFERROR(__xludf.DUMMYFUNCTION("""COMPUTED_VALUE"""),"HS210") -> HS210 | E23: =IFERROR(__xludf.DUMMYFUNCTION("""COMPUTED_VALUE"""),1553.49) -> 1553.49 | F23: =IFERROR(__xludf.DUMMYFUNCTION("""COMPUTED_VALUE"""),"-") -> - | G23: =IFERROR(__xludf.DUMMYFUNCTION("""COMPUTED_VALUE"""),"Yes") -> Yes | H23: =IFERROR(__xludf.DUMMYFUNCTION("""COMPUTED_VALUE"""),46185.53681712963) -> 46185.537
A24: =IFERROR(__xludf.DUMMYFUNCTION("""COMPUTED_VALUE"""),8989.0) -> 8989 | B24: =IFERROR(__xludf.DUMMYFUNCTION("""COMPUTED_VALUE"""),"Oakley") -> Oakley | C24: =IFERROR(__xludf.DUMMYFUNCTION("""COMPUTED_VALUE"""),7.0) -> 7 | D24: =IFERROR(__xludf.DUMMYFUNCTION("""COMPUTED_VALUE"""),"HS211") -> HS211 | E24: =IFERROR(__xludf.DUMMYFUNCTION("""COMPUTED_VALUE"""),7002.67) -> 7002.67 | F24: =IFERROR(__xludf.DUMMYFUNCTION("""COMPUTED_VALUE"""),"-") -> - | G24: =IFERROR(__xludf.DUMMYFUNCTION("""COMPUTED_VALUE"""),"Yes") -> Yes | H24: =IFERROR(__xludf.DUMMYFUNCTION("""COMPUTED_VALUE"""),46185.5353125) -> 46185.535
A25: =IFERROR(__xludf.DUMMYFUNCTION("""COMPUTED_VALUE"""),1234.0) -> 1234 | B25: =IFERROR(__xludf.DUMMYFUNCTION("""COMPUTED_VALUE"""),"Test") -> Test | C25: =IFERROR(__xludf.DUMMYFUNCTION("""COMPUTED_VALUE"""),11.0) -> 11 | E25: =IFERROR(__xludf.DUMMYFUNCTION("""COMPUTED_VALUE"""),95.34) -> 95.34 | F25: =IFERROR(__xludf.DUMMYFUNCTION("""COMPUTED_VALUE"""),"-") -> - | G25: =IFERROR(__xludf.DUMMYFUNCTION("""COMPUTED_VALUE"""),"Yes") -> Yes | H25: =IFERROR(__xludf.DUMMYFUNCTION("""COMPUTED_VALUE"""),46186.699421296296) -> 46186.699
A26: =IFERROR(__xludf.DUMMYFUNCTION("""COMPUTED_VALUE"""),8244.0) -> 8244 | B26: =IFERROR(__xludf.DUMMYFUNCTION("""COMPUTED_VALUE"""),"Alexis Parisee") -> Alexis Parisee | C26: =IFERROR(__xludf.DUMMYFUNCTION("""COMPUTED_VALUE"""),11.0) -> 11 | D26: =IFERROR(__xludf.DUMMYFUNCTION("""COMPUTED_VALUE"""),"HS203") -> HS203 | E26: =IFERROR(__xludf.DUMMYFUNCTION("""COMPUTED_VALUE"""),1000.0) -> 1000 | F26: =IFERROR(__xludf.DUMMYFUNCTION("""COMPUTED_VALUE"""),"-") -> - | G26: =IFERROR(__xludf.DUMMYFUNCTION("""COMPUTED_VALUE"""),"Yes") -> Yes
A27: =IFERROR(__xludf.DUMMYFUNCTION("""COMPUTED_VALUE"""),3846.0) -> 3846 | B27: =IFERROR(__xludf.DUMMYFUNCTION("""COMPUTED_VALUE"""),"Jace Kim") -> Jace Kim | C27: =IFERROR(__xludf.DUMMYFUNCTION("""COMPUTED_VALUE"""),11.0) -> 11 | D27: =IFERROR(__xludf.DUMMYFUNCTION("""COMPUTED_VALUE"""),"HS204") -> HS204 | E27: =IFERROR(__xludf.DUMMYFUNCTION("""COMPUTED_VALUE"""),1893.12) -> 1893.12 | F27: =IFERROR(__xludf.DUMMYFUNCTION("""COMPUTED_VALUE"""),"-") -> - | G27: =IFERROR(__xludf.DUMMYFUNCTION("""COMPUTED_VALUE"""),"Yes") -> Yes | H27: =IFERROR(__xludf.DUMMYFUNCTION("""COMPUTED_VALUE"""),46184.38476851852) -> 46184.385
A28: =IFERROR(__xludf.DUMMYFUNCTION("""COMPUTED_VALUE"""),2659.0) -> 2659 | B28: =IFERROR(__xludf.DUMMYFUNCTION("""COMPUTED_VALUE"""),"Jin Park") -> Jin Park | C28: =IFERROR(__xludf.DUMMYFUNCTION("""COMPUTED_VALUE"""),11.0) -> 11 | D28: =IFERROR(__xludf.DUMMYFUNCTION("""COMPUTED_VALUE"""),"HS205") -> HS205 | E28: =IFERROR(__xludf.DUMMYFUNCTION("""COMPUTED_VALUE"""),3.56) -> 3.56 | F28: =IFERROR(__xludf.DUMMYFUNCTION("""COMPUTED_VALUE"""),"-") -> - | G28: =IFERROR(__xludf.DUMMYFUNCTION("""COMPUTED_VALUE"""),"Yes") -> Yes | H28: =IFERROR(__xludf.DUMMYFUNCTION("""COMPUTED_VALUE"""),46183.57168981482) -> 46183.572
A29: =IFERROR(__xludf.DUMMYFUNCTION("""COMPUTED_VALUE"""),7302.0) -> 7302 | B29: =IFERROR(__xludf.DUMMYFUNCTION("""COMPUTED_VALUE"""),"Claire Yang") -> Claire Yang | C29: =IFERROR(__xludf.DUMMYFUNCTION("""COMPUTED_VALUE"""),11.0) -> 11 | D29: =IFERROR(__xludf.DUMMYFUNCTION("""COMPUTED_VALUE"""),"HS206") -> HS206 | E29: =IFERROR(__xludf.DUMMYFUNCTION("""COMPUTED_VALUE"""),43.05) -> 43.05 | F29: =IFERROR(__xludf.DUMMYFUNCTION("""COMPUTED_VALUE"""),"-") -> - | G29: =IFERROR(__xludf.DUMMYFUNCTION("""COMPUTED_VALUE"""),"Yes") -> Yes | H29: =IFERROR(__xludf.DUMMYFUNCTION("""COMPUTED_VALUE"""),46183.57829861111) -> 46183.578
A30: =IFERROR(__xludf.DUMMYFUNCTION("""COMPUTED_VALUE"""),5420.0) -> 5420 | B30: =IFERROR(__xludf.DUMMYFUNCTION("""COMPUTED_VALUE"""),"Daniel Park") -> Daniel Park | C30: =IFERROR(__xludf.DUMMYFUNCTION("""COMPUTED_VALUE"""),11.0) -> 11 | D30: =IFERROR(__xludf.DUMMYFUNCTION("""COMPUTED_VALUE"""),"HS207") -> HS207 | E30: =IFERROR(__xludf.DUMMYFUNCTION("""COMPUTED_VALUE"""),5.81) -> 5.81 | F30: =IFERROR(__xludf.DUMMYFUNCTION("""COMPUTED_VALUE"""),"-") -> - | G30: =IFERROR(__xludf.DUMMYFUNCTION("""COMPUTED_VALUE"""),"Yes") -> Yes | H30: =IFERROR(__xludf.DUMMYFUNCTION("""COMPUTED_VALUE"""),46185.623460648145) -> 46185.623
A31: =IFERROR(__xludf.DUMMYFUNCTION("""COMPUTED_VALUE"""),4098.0) -> 4098 | B31: =IFERROR(__xludf.DUMMYFUNCTION("""COMPUTED_VALUE"""),"Anthony Ahn") -> Anthony Ahn | C31: =IFERROR(__xludf.DUMMYFUNCTION("""COMPUTED_VALUE"""),11.0) -> 11 | D31: =IFERROR(__xludf.DUMMYFUNCTION("""COMPUTED_VALUE"""),"HS208") -> HS208 | E31: =IFERROR(__xludf.DUMMYFUNCTION("""COMPUTED_VALUE"""),1000.0) -> 1000 | F31: =IFERROR(__xludf.DUMMYFUNCTION("""COMPUTED_VALUE"""),"-") -> - | G31: =IFERROR(__xludf.DUMMYFUNCTION("""COMPUTED_VALUE"""),"Yes") -> Yes
A32: =IFERROR(__xludf.DUMMYFUNCTION("""COMPUTED_VALUE"""),9908.0) -> 9908 | B32: =IFERROR(__xludf.DUMMYFUNCTION("""COMPUTED_VALUE"""),"Alex Kang") -> Alex Kang | C32: =IFERROR(__xludf.DUMMYFUNCTION("""COMPUTED_VALUE"""),11.0) -> 11 | D32: =IFERROR(__xludf.DUMMYFUNCTION("""COMPUTED_VALUE"""),"HS209") -> HS209 | E32: =IFERROR(__xludf.DUMMYFUNCTION("""COMPUTED_VALUE"""),1000.0) -> 1000 | F32: =IFERROR(__xludf.DUMMYFUNCTION("""COMPUTED_VALUE"""),"-") -> - | G32: =IFERROR(__xludf.DUMMYFUNCTION("""COMPUTED_VALUE"""),"Yes") -> Yes
A33: =IFERROR(__xludf.DUMMYFUNCTION("""COMPUTED_VALUE"""),8601.0) -> 8601 | B33: =IFERROR(__xludf.DUMMYFUNCTION("""COMPUTED_VALUE"""),"Mathew Kim") -> Mathew Kim | C33: =IFERROR(__xludf.DUMMYFUNCTION("""COMPUTED_VALUE"""),11.0) -> 11 | D33: =IFERROR(__xludf.DUMMYFUNCTION("""COMPUTED_VALUE"""),"HS210") -> HS210 | E33: =IFERROR(__xludf.DUMMYFUNCTION("""COMPUTED_VALUE"""),1000.0) -> 1000 | F33: =IFERROR(__xludf.DUMMYFUNCTION("""COMPUTED_VALUE"""),"-") -> - | G33: =IFERROR(__xludf.DUMMYFUNCTION("""COMPUTED_VALUE"""),"Yes") -> Yes
A34: =IFERROR(__xludf.DUMMYFUNCTION("""COMPUTED_VALUE"""),3466.0) -> 3466 | B34: =IFERROR(__xludf.DUMMYFUNCTION("""COMPUTED_VALUE"""),"Jay Kim") -> Jay Kim | C34: =IFERROR(__xludf.DUMMYFUNCTION("""COMPUTED_VALUE"""),11.0) -> 11 | D34: =IFERROR(__xludf.DUMMYFUNCTION("""COMPUTED_VALUE"""),"HS211") -> HS211 | E34: =IFERROR(__xludf.DUMMYFUNCTION("""COMPUTED_VALUE"""),130.35) -> 130.35 | F34: =IFERROR(__xludf.DUMMYFUNCTION("""COMPUTED_VALUE"""),"-") -> - | G34: =IFERROR(__xludf.DUMMYFUNCTION("""COMPUTED_VALUE"""),"Yes") -> Yes | H34: =IFERROR(__xludf.DUMMYFUNCTION("""COMPUTED_VALUE"""),46183.64832175926) -> 46183.648
A35: =IFERROR(__xludf.DUMMYFUNCTION("""COMPUTED_VALUE"""),8300.0) -> 8300 | B35: =IFERROR(__xludf.DUMMYFUNCTION("""COMPUTED_VALUE"""),"Andy Lee") -> Andy Lee | C35: =IFERROR(__xludf.DUMMYFUNCTION("""COMPUTED_VALUE"""),11.0) -> 11 | D35: =IFERROR(__xludf.DUMMYFUNCTION("""COMPUTED_VALUE"""),"HS212") -> HS212 | E35: =IFERROR(__xludf.DUMMYFUNCTION("""COMPUTED_VALUE"""),27.22) -> 27.22 | F35: =IFERROR(__xludf.DUMMYFUNCTION("""COMPUTED_VALUE"""),"-") -> - | G35: =IFERROR(__xludf.DUMMYFUNCTION("""COMPUTED_VALUE"""),"Yes") -> Yes | H35: =IFERROR(__xludf.DUMMYFUNCTION("""COMPUTED_VALUE"""),46183.572858796295) -> 46183.573
A36: =IFERROR(__xludf.DUMMYFUNCTION("""COMPUTED_VALUE"""),1688.0) -> 1688 | B36: =IFERROR(__xludf.DUMMYFUNCTION("""COMPUTED_VALUE"""),"Junwoo Yoon") -> Junwoo Yoon | C36: =IFERROR(__xludf.DUMMYFUNCTION("""COMPUTED_VALUE"""),11.0) -> 11 | D36: =IFERROR(__xludf.DUMMYFUNCTION("""COMPUTED_VALUE"""),"HS213") -> HS213 | E36: =IFERROR(__xludf.DUMMYFUNCTION("""COMPUTED_VALUE"""),168.92) -> 168.92 | F36: =IFERROR(__xludf.DUMMYFUNCTION("""COMPUTED_VALUE"""),"-") -> - | G36: =IFERROR(__xludf.DUMMYFUNCTION("""COMPUTED_VALUE"""),"Yes") -> Yes | H36: =IFERROR(__xludf.DUMMYFUNCTION("""COMPUTED_VALUE"""),46183.68376157407) -> 46183.684
A37: =IFERROR(__xludf.DUMMYFUNCTION("""COMPUTED_VALUE"""),8045.0) -> 8045 | B37: =IFERROR(__xludf.DUMMYFUNCTION("""COMPUTED_VALUE"""),"Hyunmo Gu ") -> Hyunmo Gu | C37: =IFERROR(__xludf.DUMMYFUNCTION("""COMPUTED_VALUE"""),11.0) -> 11 | D37: =IFERROR(__xludf.DUMMYFUNCTION("""COMPUTED_VALUE"""),"HS214") -> HS214 | E37: =IFERROR(__xludf.DUMMYFUNCTION("""COMPUTED_VALUE"""),1000.0) -> 1000 | F37: =IFERROR(__xludf.DUMMYFUNCTION("""COMPUTED_VALUE"""),"-") -> - | G37: =IFERROR(__xludf.DUMMYFUNCTION("""COMPUTED_VALUE"""),"Yes") -> Yes
A38: =IFERROR(__xludf.DUMMYFUNCTION("""COMPUTED_VALUE"""),1926.0) -> 1926 | B38: =IFERROR(__xludf.DUMMYFUNCTION("""COMPUTED_VALUE"""),"Sooin Kang") -> Sooin Kang | C38: =IFERROR(__xludf.DUMMYFUNCTION("""COMPUTED_VALUE"""),11.0) -> 11 | D38: =IFERROR(__xludf.DUMMYFUNCTION("""COMPUTED_VALUE"""),"HS215") -> HS215 | E38: =IFERROR(__xludf.DUMMYFUNCTION("""COMPUTED_VALUE"""),1000.0) -> 1000 | F38: =IFERROR(__xludf.DUMMYFUNCTION("""COMPUTED_VALUE"""),"-") -> - | G38: =IFERROR(__xludf.DUMMYFUNCTION("""COMPUTED_VALUE"""),"Yes") -> Yes
A39: =IFERROR(__xludf.DUMMYFUNCTION("""COMPUTED_VALUE"""),1035.0) -> 1035 | B39: =IFERROR(__xludf.DUMMYFUNCTION("""COMPUTED_VALUE"""),"Jiwon Kang") -> Jiwon Kang | C39: =IFERROR(__xludf.DUMMYFUNCTION("""COMPUTED_VALUE"""),11.0) -> 11 | D39: =IFERROR(__xludf.DUMMYFUNCTION("""COMPUTED_VALUE"""),"HS216") -> HS216 | E39: =IFERROR(__xludf.DUMMYFUNCTION("""COMPUTED_VALUE"""),1000.0) -> 1000 | F39: =IFERROR(__xludf.DUMMYFUNCTION("""COMPUTED_VALUE"""),"-") -> - | G39: =IFERROR(__xludf.DUMMYFUNCTION("""COMPUTED_VALUE"""),"Yes") -> Yes
A40: =IFERROR(__xludf.DUMMYFUNCTION("""COMPUTED_VALUE"""),3706.0) -> 3706 | B40: =IFERROR(__xludf.DUMMYFUNCTION("""COMPUTED_VALUE"""),"Kevin Jeon") -> Kevin Jeon | C40: =IFERROR(__xludf.DUMMYFUNCTION("""COMPUTED_VALUE"""),11.0) -> 11 | D40: =IFERROR(__xludf.DUMMYFUNCTION("""COMPUTED_VALUE"""),"HS217") -> HS217 | E40: =IFERROR(__xludf.DUMMYFUNCTION("""COMPUTED_VALUE"""),107.95) -> 107.95 | F40: =IFERROR(__xludf.DUMMYFUNCTION("""COMPUTED_VALUE"""),"-") -> - | G40: =IFERROR(__xludf.DUMMYFUNCTION("""COMPUTED_VALUE"""),"Yes") -> Yes | H40: =IFERROR(__xludf.DUMMYFUNCTION("""COMPUTED_VALUE"""),46183.59241898148) -> 46183.592
A41: =IFERROR(__xludf.DUMMYFUNCTION("""COMPUTED_VALUE"""),1117.0) -> 1117 | B41: =IFERROR(__xludf.DUMMYFUNCTION("""COMPUTED_VALUE"""),"Hyeonjun Kim") -> Hyeonjun Kim | C41: =IFERROR(__xludf.DUMMYFUNCTION("""COMPUTED_VALUE"""),8.0) -> 8 | E41: =IFERROR(__xludf.DUMMYFUNCTION("""COMPUTED_VALUE"""),48.17) -> 48.17 | F41: =IFERROR(__xludf.DUMMYFUNCTION("""COMPUTED_VALUE"""),"-") -> - | G41: =IFERROR(__xludf.DUMMYFUNCTION("""COMPUTED_VALUE"""),"Yes") -> Yes | H41: =IFERROR(__xludf.DUMMYFUNCTION("""COMPUTED_VALUE"""),46185.65935185185) -> 46185.659
A42: =IFERROR(__xludf.DUMMYFUNCTION("""COMPUTED_VALUE"""),9658.0) -> 9658 | B42: =IFERROR(__xludf.DUMMYFUNCTION("""COMPUTED_VALUE"""),"Austin Han") -> Austin Han | C42: =IFERROR(__xludf.DUMMYFUNCTION("""COMPUTED_VALUE"""),8.0) -> 8 | E42: =IFERROR(__xludf.DUMMYFUNCTION("""COMPUTED_VALUE"""),40.51) -> 40.51 | F42: =IFERROR(__xludf.DUMMYFUNCTION("""COMPUTED_VALUE"""),"-") -> - | G42: =IFERROR(__xludf.DUMMYFUNCTION("""COMPUTED_VALUE"""),"Yes") -> Yes | H42: =IFERROR(__xludf.DUMMYFUNCTION("""COMPUTED_VALUE"""),46187.343136574076) -> 46187.343
A43: =IFERROR(__xludf.DUMMYFUNCTION("""COMPUTED_VALUE"""),4647.0) -> 4647 | B43: =IFERROR(__xludf.DUMMYFUNCTION("""COMPUTED_VALUE"""),"Jake Kim") -> Jake Kim | C43: =IFERROR(__xludf.DUMMYFUNCTION("""COMPUTED_VALUE"""),8.0) -> 8 | E43: =IFERROR(__xludf.DUMMYFUNCTION("""COMPUTED_VALUE"""),42.61) -> 42.61 | F43: =IFERROR(__xludf.DUMMYFUNCTION("""COMPUTED_VALUE"""),"-") -> - | G43: =IFERROR(__xludf.DUMMYFUNCTION("""COMPUTED_VALUE"""),"Yes") -> Yes | H43: =IFERROR(__xludf.DUMMYFUNCTION("""COMPUTED_VALUE"""),46187.57518518518) -> 46187.575
A44: =IFERROR(__xludf.DUMMYFUNCTION("""COMPUTED_VALUE"""),4346.0) -> 4346 | B44: =IFERROR(__xludf.DUMMYFUNCTION("""COMPUTED_VALUE"""),"Shay Baek") -> Shay Baek | C44: =IFERROR(__xludf.DUMMYFUNCTION("""COMPUTED_VALUE"""),8.0) -> 8 | E44: =IFERROR(__xludf.DUMMYFUNCTION("""COMPUTED_VALUE"""),1964.86) -> 1964.86 | F44: =IFERROR(__xludf.DUMMYFUNCTION("""COMPUTED_VALUE"""),"-") -> - | G44: =IFERROR(__xludf.DUMMYFUNCTION("""COMPUTED_VALUE"""),"Yes") -> Yes | H44: =IFERROR(__xludf.DUMMYFUNCTION("""COMPUTED_VALUE"""),46185.686527777776) -> 46185.687
A45: =IFERROR(__xludf.DUMMYFUNCTION("""COMPUTED_VALUE"""),8332.0) -> 8332 | B45: =IFERROR(__xludf.DUMMYFUNCTION("""COMPUTED_VALUE"""),"Lily Kim") -> Lily Kim | C45: =IFERROR(__xludf.DUMMYFUNCTION("""COMPUTED_VALUE"""),8.0) -> 8 | E45: =IFERROR(__xludf.DUMMYFUNCTION("""COMPUTED_VALUE"""),921.89) -> 921.89 | F45: =IFERROR(__xludf.DUMMYFUNCTION("""COMPUTED_VALUE"""),"-") -> - | G45: =IFERROR(__xludf.DUMMYFUNCTION("""COMPUTED_VALUE"""),"Yes") -> Yes | H45: =IFERROR(__xludf.DUMMYFUNCTION("""COMPUTED_VALUE"""),46184.59222222222) -> 46184.592
A46: =IFERROR(__xludf.DUMMYFUNCTION("""COMPUTED_VALUE"""),6050.0) -> 6050 | B46: =IFERROR(__xludf.DUMMYFUNCTION("""COMPUTED_VALUE"""),"Claire Jeong") -> Claire Jeong | C46: =IFERROR(__xludf.DUMMYFUNCTION("""COMPUTED_VALUE"""),8.0) -> 8 | E46: =IFERROR(__xludf.DUMMYFUNCTION("""COMPUTED_VALUE"""),38.28) -> 38.28 | F46: =IFERROR(__xludf.DUMMYFUNCTION("""COMPUTED_VALUE"""),"-") -> - | G46: =IFERROR(__xludf.DUMMYFUNCTION("""COMPUTED_VALUE"""),"Yes") -> Yes | H46: =IFERROR(__xludf.DUMMYFUNCTION("""COMPUTED_VALUE"""),46183.595821759256) -> 46183.596
A47: =IFERROR(__xludf.DUMMYFUNCTION("""COMPUTED_VALUE"""),9842.0) -> 9842 | B47: =IFERROR(__xludf.DUMMYFUNCTION("""COMPUTED_VALUE"""),"Sylvia Seo") -> Sylvia Seo | C47: =IFERROR(__xludf.DUMMYFUNCTION("""COMPUTED_VALUE"""),8.0) -> 8 | E47: =IFERROR(__xludf.DUMMYFUNCTION("""COMPUTED_VALUE"""),257.9) -> 257.9 | F47: =IFERROR(__xludf.DUMMYFUNCTION("""COMPUTED_VALUE"""),"-") -> - | G47: =IFERROR(__xludf.DUMMYFUNCTION("""COMPUTED_VALUE"""),"Yes") -> Yes | H47: =IFERROR(__xludf.DUMMYFUNCTION("""COMPUTED_VALUE"""),46184.40719907408) -> 46184.407
A48: =IFERROR(__xludf.DUMMYFUNCTION("""COMPUTED_VALUE"""),2399.0) -> 2399 | B48: =IFERROR(__xludf.DUMMYFUNCTION("""COMPUTED_VALUE"""),"Seoyi Hong") -> Seoyi Hong | C48: =IFERROR(__xludf.DUMMYFUNCTION("""COMPUTED_VALUE"""),8.0) -> 8 | E48: =IFERROR(__xludf.DUMMYFUNCTION("""COMPUTED_VALUE"""),290.59) -> 290.59 | F48: =IFERROR(__xludf.DUMMYFUNCTION("""COMPUTED_VALUE"""),"-") -> - | G48: =IFERROR(__xludf.DUMMYFUNCTION("""COMPUTED_VALUE"""),"Yes") -> Yes | H48: =IFERROR(__xludf.DUMMYFUNCTION("""COMPUTED_VALUE"""),46184.40646990741) -> 46184.406
A49: =IFERROR(__xludf.DUMMYFUNCTION("""COMPUTED_VALUE"""),8365.0) -> 8365 | B49: =IFERROR(__xludf.DUMMYFUNCTION("""COMPUTED_VALUE"""),"Casey Yang") -> Casey Yang | C49: =IFERROR(__xludf.DUMMYFUNCTION("""COMPUTED_VALUE"""),8.0) -> 8 | E49: =IFERROR(__xludf.DUMMYFUNCTION("""COMPUTED_VALUE"""),774.4) -> 774.4 | F49: =IFERROR(__xludf.DUMMYFUNCTION("""COMPUTED_VALUE"""),"-") -> - | G49: =IFERROR(__xludf.DUMMYFUNCTION("""COMPUTED_VALUE"""),"Yes") -> Yes | H49: =IFERROR(__xludf.DUMMYFUNCTION("""COMPUTED_VALUE"""),46185.59349537037) -> 46185.594
A50: =IFERROR(__xludf.DUMMYFUNCTION("""COMPUTED_VALUE"""),6742.0) -> 6742 | B50: =IFERROR(__xludf.DUMMYFUNCTION("""COMPUTED_VALUE"""),"Raoul Kim") -> Raoul Kim | C50: =IFERROR(__xludf.DUMMYFUNCTION("""COMPUTED_VALUE"""),8.0) -> 8 | E50: =IFERROR(__xludf.DUMMYFUNCTION("""COMPUTED_VALUE"""),649.56) -> 649.56 | F50: =IFERROR(__xludf.DUMMYFUNCTION("""COMPUTED_VALUE"""),"-") -> - | G50: =IFERROR(__xludf.DUMMYFUNCTION("""COMPUTED_VALUE"""),"Yes") -> Yes | H50: =IFERROR(__xludf.DUMMYFUNCTION("""COMPUTED_VALUE"""),46187.675462962965) -> 46187.675
A51: =IFERROR(__xludf.DUMMYFUNCTION("""COMPUTED_VALUE"""),8043.0) -> 8043 | B51: =IFERROR(__xludf.DUMMYFUNCTION("""COMPUTED_VALUE"""),"Jayden Hong") -> Jayden Hong | C51: =IFERROR(__xludf.DUMMYFUNCTION("""COMPUTED_VALUE"""),8.0) -> 8 | E51: =IFERROR(__xludf.DUMMYFUNCTION("""COMPUTED_VALUE"""),153.98) -> 153.98 | F51: =IFERROR(__xludf.DUMMYFUNCTION("""COMPUTED_VALUE"""),"-") -> - | G51: =IFERROR(__xludf.DUMMYFUNCTION("""COMPUTED_VALUE"""),"Yes") -> Yes | H51: =IFERROR(__xludf.DUMMYFUNCTION("""COMPUTED_VALUE"""),46186.675358796296) -> 46186.675
A52: =IFERROR(__xludf.DUMMYFUNCTION("""COMPUTED_VALUE"""),1749.0) -> 1749 | B52: =IFERROR(__xludf.DUMMYFUNCTION("""COMPUTED_VALUE"""),"Edward Song") -> Edward Song | C52: =IFERROR(__xludf.DUMMYFUNCTION("""COMPUTED_VALUE"""),8.0) -> 8 | E52: =IFERROR(__xludf.DUMMYFUNCTION("""COMPUTED_VALUE"""),497.54) -> 497.54 | F52: =IFERROR(__xludf.DUMMYFUNCTION("""COMPUTED_VALUE"""),"-") -> - | G52: =IFERROR(__xludf.DUMMYFUNCTION("""COMPUTED_VALUE"""),"Yes") -> Yes | H52: =IFERROR(__xludf.DUMMYFUNCTION("""COMPUTED_VALUE"""),46187.652766203704) -> 46187.653
A53: =IFERROR(__xludf.DUMMYFUNCTION("""COMPUTED_VALUE"""),6119.0) -> 6119 | B53: =IFERROR(__xludf.DUMMYFUNCTION("""COMPUTED_VALUE"""),"Hannah Lee") -> Hannah Lee | C53: =IFERROR(__xludf.DUMMYFUNCTION("""COMPUTED_VALUE"""),8.0) -> 8 | E53: =IFERROR(__xludf.DUMMYFUNCTION("""COMPUTED_VALUE"""),458.06) -> 458.06 | F53: =IFERROR(__xludf.DUMMYFUNCTION("""COMPUTED_VALUE"""),"-") -> - | G53: =IFERROR(__xludf.DUMMYFUNCTION("""COMPUTED_VALUE"""),"Yes") -> Yes | H53: =IFERROR(__xludf.DUMMYFUNCTION("""COMPUTED_VALUE"""),46185.597650462965) -> 46185.598
A54: =IFERROR(__xludf.DUMMYFUNCTION("""COMPUTED_VALUE"""),5121.0) -> 5121 | B54: =IFERROR(__xludf.DUMMYFUNCTION("""COMPUTED_VALUE"""),"Ryan Kang") -> Ryan Kang | C54: =IFERROR(__xludf.DUMMYFUNCTION("""COMPUTED_VALUE"""),8.0) -> 8 | E54: =IFERROR(__xludf.DUMMYFUNCTION("""COMPUTED_VALUE"""),86.92) -> 86.92 | F54: =IFERROR(__xludf.DUMMYFUNCTION("""COMPUTED_VALUE"""),"-") -> - | G54: =IFERROR(__xludf.DUMMYFUNCTION("""COMPUTED_VALUE"""),"Yes") -> Yes | H54: =IFERROR(__xludf.DUMMYFUNCTION("""COMPUTED_VALUE"""),46185.65726851852) -> 46185.657
A55: =IFERROR(__xludf.DUMMYFUNCTION("""COMPUTED_VALUE"""),676768.0) -> 676768 | B55: =IFERROR(__xludf.DUMMYFUNCTION("""COMPUTED_VALUE"""),"Jayden Yun") -> Jayden Yun | C55: =IFERROR(__xludf.DUMMYFUNCTION("""COMPUTED_VALUE"""),8.0) -> 8 | E55: =IFERROR(__xludf.DUMMYFUNCTION("""COMPUTED_VALUE"""),45.45) -> 45.45 | F55: =IFERROR(__xludf.DUMMYFUNCTION("""COMPUTED_VALUE"""),"-") -> - | G55: =IFERROR(__xludf.DUMMYFUNCTION("""COMPUTED_VALUE"""),"Yes") -> Yes | H55: =IFERROR(__xludf.DUMMYFUNCTION("""COMPUTED_VALUE"""),46187.56932870371) -> 46187.569
A56: =IFERROR(__xludf.DUMMYFUNCTION("""COMPUTED_VALUE"""),8375.0) -> 8375 | B56: =IFERROR(__xludf.DUMMYFUNCTION("""COMPUTED_VALUE"""),"Annie Lee") -> Annie Lee | C56: =IFERROR(__xludf.DUMMYFUNCTION("""COMPUTED_VALUE"""),8.0) -> 8 | E56: =IFERROR(__xludf.DUMMYFUNCTION("""COMPUTED_VALUE"""),419.36) -> 419.36 | F56: =IFERROR(__xludf.DUMMYFUNCTION("""COMPUTED_VALUE"""),"-") -> - | G56: =IFERROR(__xludf.DUMMYFUNCTION("""COMPUTED_VALUE"""),"Yes") -> Yes | H56: =IFERROR(__xludf.DUMMYFUNCTION("""COMPUTED_VALUE"""),46183.59747685185) -> 46183.597
A57: =IFERROR(__xludf.DUMMYFUNCTION("""COMPUTED_VALUE"""),7920.0) -> 7920 | B57: =IFERROR(__xludf.DUMMYFUNCTION("""COMPUTED_VALUE"""),"Alyssa Shin") -> Alyssa Shin | C57: =IFERROR(__xludf.DUMMYFUNCTION("""COMPUTED_VALUE"""),8.0) -> 8 | E57: =IFERROR(__xludf.DUMMYFUNCTION("""COMPUTED_VALUE"""),870.12) -> 870.12 | F57: =IFERROR(__xludf.DUMMYFUNCTION("""COMPUTED_VALUE"""),"-") -> - | G57: =IFERROR(__xludf.DUMMYFUNCTION("""COMPUTED_VALUE"""),"Yes") -> Yes | H57: =IFERROR(__xludf.DUMMYFUNCTION("""COMPUTED_VALUE"""),46185.60037037037) -> 46185.6
A58: =IFERROR(__xludf.DUMMYFUNCTION("""COMPUTED_VALUE"""),8673.0) -> 8673 | B58: =IFERROR(__xludf.DUMMYFUNCTION("""COMPUTED_VALUE"""),"Minjung Lee") -> Minjung Lee | C58: =IFERROR(__xludf.DUMMYFUNCTION("""COMPUTED_VALUE"""),8.0) -> 8 | E58: =IFERROR(__xludf.DUMMYFUNCTION("""COMPUTED_VALUE"""),130.1) -> 130.1 | F58: =IFERROR(__xludf.DUMMYFUNCTION("""COMPUTED_VALUE"""),"-") -> - | G58: =IFERROR(__xludf.DUMMYFUNCTION("""COMPUTED_VALUE"""),"Yes") -> Yes | H58: =IFERROR(__xludf.DUMMYFUNCTION("""COMPUTED_VALUE"""),46185.59657407407) -> 46185.597
A60: =IFERROR(__xludf.DUMMYFUNCTION("""COMPUTED_VALUE"""),2233.0) -> 2233 | B60: =IFERROR(__xludf.DUMMYFUNCTION("""COMPUTED_VALUE"""),"John") -> John | C60: =IFERROR(__xludf.DUMMYFUNCTION("""COMPUTED_VALUE"""),"Teacher") -> Teacher | E60: =IFERROR(__xludf.DUMMYFUNCTION("""COMPUTED_VALUE"""),51.9) -> 51.9 | G60: =IFERROR(__xludf.DUMMYFUNCTION("""COMPUTED_VALUE"""),"Yes") -> Yes | H60: =IFERROR(__xludf.DUMMYFUNCTION("""COMPUTED_VALUE"""),46183.65100694444) -> 46183.651
A61: =IFERROR(__xludf.DUMMYFUNCTION("""COMPUTED_VALUE"""),4316.0) -> 4316 | B61: =IFERROR(__xludf.DUMMYFUNCTION("""COMPUTED_VALUE"""),"Chloe An") -> Chloe An | E61: =IFERROR(__xludf.DUMMYFUNCTION("""COMPUTED_VALUE"""),486.43) -> 486.43 | G61: =IFERROR(__xludf.DUMMYFUNCTION("""COMPUTED_VALUE"""),"Yes") -> Yes | H61: =IFERROR(__xludf.DUMMYFUNCTION("""COMPUTED_VALUE"""),46185.40840277778) -> 46185.408
A62: =IFERROR(__xludf.DUMMYFUNCTION("""COMPUTED_VALUE"""),3553.0) -> 3553 | B62: =IFERROR(__xludf.DUMMYFUNCTION("""COMPUTED_VALUE"""),"Ryan Kim") -> Ryan Kim | E62: =IFERROR(__xludf.DUMMYFUNCTION("""COMPUTED_VALUE"""),150.84) -> 150.84 | G62: =IFERROR(__xludf.DUMMYFUNCTION("""COMPUTED_VALUE"""),"Yes") -> Yes | H62: =IFERROR(__xludf.DUMMYFUNCTION("""COMPUTED_VALUE"""),46185.64158564815) -> 46185.642
A63: =IFERROR(__xludf.DUMMYFUNCTION("""COMPUTED_VALUE"""),7415.0) -> 7415 | B63: =IFERROR(__xludf.DUMMYFUNCTION("""COMPUTED_VALUE"""),"Sarah Park") -> Sarah Park | E63: =IFERROR(__xludf.DUMMYFUNCTION("""COMPUTED_VALUE"""),528.56) -> 528.56 | G63: =IFERROR(__xludf.DUMMYFUNCTION("""COMPUTED_VALUE"""),"Yes") -> Yes | H63: =IFERROR(__xludf.DUMMYFUNCTION("""COMPUTED_VALUE"""),46185.55556712963) -> 46185.556
A64: =IFERROR(__xludf.DUMMYFUNCTION("""COMPUTED_VALUE"""),2240.0) -> 2240 | B64: =IFERROR(__xludf.DUMMYFUNCTION("""COMPUTED_VALUE"""),"Shiwoo Kim") -> Shiwoo Kim | E64: =IFERROR(__xludf.DUMMYFUNCTION("""COMPUTED_VALUE"""),1000.0) -> 1000 | G64: =IFERROR(__xludf.DUMMYFUNCTION("""COMPUTED_VALUE"""),"Yes") -> Yes
A65: =IFERROR(__xludf.DUMMYFUNCTION("""COMPUTED_VALUE"""),1535.0) -> 1535 | B65: =IFERROR(__xludf.DUMMYFUNCTION("""COMPUTED_VALUE"""),"Dano Kim") -> Dano Kim | E65: =IFERROR(__xludf.DUMMYFUNCTION("""COMPUTED_VALUE"""),1.89) -> 1.89 | G65: =IFERROR(__xludf.DUMMYFUNCTION("""COMPUTED_VALUE"""),"Yes") -> Yes | H65: =IFERROR(__xludf.DUMMYFUNCTION("""COMPUTED_VALUE"""),46185.584652777776) -> 46185.585
A66: =IFERROR(__xludf.DUMMYFUNCTION("""COMPUTED_VALUE"""),7260.0) -> 7260 | B66: =IFERROR(__xludf.DUMMYFUNCTION("""COMPUTED_VALUE"""),"Soyeon Park") -> Soyeon Park | E66: =IFERROR(__xludf.DUMMYFUNCTION("""COMPUTED_VALUE"""),1056.96) -> 1056.96 | G66: =IFERROR(__xludf.DUMMYFUNCTION("""COMPUTED_VALUE"""),"Yes") -> Yes | H66: =IFERROR(__xludf.DUMMYFUNCTION("""COMPUTED_VALUE"""),46185.63997685185) -> 46185.64
A67: =IFERROR(__xludf.DUMMYFUNCTION("""COMPUTED_VALUE"""),7773.0) -> 7773 | B67: =IFERROR(__xludf.DUMMYFUNCTION("""COMPUTED_VALUE"""),"Gahyeon Yoon") -> Gahyeon Yoon | E67: =IFERROR(__xludf.DUMMYFUNCTION("""COMPUTED_VALUE"""),599.12) -> 599.12 | G67: =IFERROR(__xludf.DUMMYFUNCTION("""COMPUTED_VALUE"""),"Yes") -> Yes | H67: =IFERROR(__xludf.DUMMYFUNCTION("""COMPUTED_VALUE"""),46185.61056712963) -> 46185.611
A68: =IFERROR(__xludf.DUMMYFUNCTION("""COMPUTED_VALUE"""),1064.0) -> 1064 | B68: =IFERROR(__xludf.DUMMYFUNCTION("""COMPUTED_VALUE"""),"Christine Kim") -> Christine Kim | E68: =IFERROR(__xludf.DUMMYFUNCTION("""COMPUTED_VALUE"""),187.23) -> 187.23 | G68: =IFERROR(__xludf.DUMMYFUNCTION("""COMPUTED_VALUE"""),"Yes") -> Yes | H68: =IFERROR(__xludf.DUMMYFUNCTION("""COMPUTED_VALUE"""),46185.555625) -> 46185.556
A69: =IFERROR(__xludf.DUMMYFUNCTION("""COMPUTED_VALUE"""),2698.0) -> 2698 | B69: =IFERROR(__xludf.DUMMYFUNCTION("""COMPUTED_VALUE"""),"David Ki") -> David Ki | E69: =IFERROR(__xludf.DUMMYFUNCTION("""COMPUTED_VALUE"""),1000.0) -> 1000 | G69: =IFERROR(__xludf.DUMMYFUNCTION("""COMPUTED_VALUE"""),"Yes") -> Yes
A70: =IFERROR(__xludf.DUMMYFUNCTION("""COMPUTED_VALUE"""),8054.0) -> 8054 | B70: =IFERROR(__xludf.DUMMYFUNCTION("""COMPUTED_VALUE"""),"Sophie Lee") -> Sophie Lee | E70: =IFERROR(__xludf.DUMMYFUNCTION("""COMPUTED_VALUE"""),1443.46) -> 1443.46 | G70: =IFERROR(__xludf.DUMMYFUNCTION("""COMPUTED_VALUE"""),"Yes") -> Yes | H70: =IFERROR(__xludf.DUMMYFUNCTION("""COMPUTED_VALUE"""),46185.59792824074) -> 46185.598
A71: =IFERROR(__xludf.DUMMYFUNCTION("""COMPUTED_VALUE"""),5938.0) -> 5938 | B71: =IFERROR(__xludf.DUMMYFUNCTION("""COMPUTED_VALUE"""),"Emily Kang") -> Emily Kang | E71: =IFERROR(__xludf.DUMMYFUNCTION("""COMPUTED_VALUE"""),284.14) -> 284.14 | G71: =IFERROR(__xludf.DUMMYFUNCTION("""COMPUTED_VALUE"""),"Yes") -> Yes | H71: =IFERROR(__xludf.DUMMYFUNCTION("""COMPUTED_VALUE"""),46185.629375) -> 46185.629
A72: =IFERROR(__xludf.DUMMYFUNCTION("""COMPUTED_VALUE"""),6755.0) -> 6755 | B72: =IFERROR(__xludf.DUMMYFUNCTION("""COMPUTED_VALUE"""),"Matthew Yang") -> Matthew Yang | E72: =IFERROR(__xludf.DUMMYFUNCTION("""COMPUTED_VALUE"""),1000.0) -> 1000 | G72: =IFERROR(__xludf.DUMMYFUNCTION("""COMPUTED_VALUE"""),"Yes") -> Yes
A73: =IFERROR(__xludf.DUMMYFUNCTION("""COMPUTED_VALUE"""),2640.0) -> 2640 | B73: =IFERROR(__xludf.DUMMYFUNCTION("""COMPUTED_VALUE"""),"Sean Park") -> Sean Park | E73: =IFERROR(__xludf.DUMMYFUNCTION("""COMPUTED_VALUE"""),427.96) -> 427.96 | G73: =IFERROR(__xludf.DUMMYFUNCTION("""COMPUTED_VALUE"""),"Yes") -> Yes | H73: =IFERROR(__xludf.DUMMYFUNCTION("""COMPUTED_VALUE"""),46187.599444444444) -> 46187.599
A74: =IFERROR(__xludf.DUMMYFUNCTION("""COMPUTED_VALUE"""),7465.0) -> 7465 | B74: =IFERROR(__xludf.DUMMYFUNCTION("""COMPUTED_VALUE"""),"Dorothy Park") -> Dorothy Park | E74: =IFERROR(__xludf.DUMMYFUNCTION("""COMPUTED_VALUE"""),1703.18) -> 1703.18 | G74: =IFERROR(__xludf.DUMMYFUNCTION("""COMPUTED_VALUE"""),"Yes") -> Yes | H74: =IFERROR(__xludf.DUMMYFUNCTION("""COMPUTED_VALUE"""),46185.63921296296) -> 46185.639
A75: =IFERROR(__xludf.DUMMYFUNCTION("""COMPUTED_VALUE"""),6407.0) -> 6407 | B75: =IFERROR(__xludf.DUMMYFUNCTION("""COMPUTED_VALUE"""),"Jun Lee") -> Jun Lee | E75: =IFERROR(__xludf.DUMMYFUNCTION("""COMPUTED_VALUE"""),1911.48) -> 1911.48 | G75: =IFERROR(__xludf.DUMMYFUNCTION("""COMPUTED_VALUE"""),"Yes") -> Yes | H75: =IFERROR(__xludf.DUMMYFUNCTION("""COMPUTED_VALUE"""),46184.5325) -> 46184.533
A76: =IFERROR(__xludf.DUMMYFUNCTION("""COMPUTED_VALUE"""),1921.0) -> 1921 | B76: =IFERROR(__xludf.DUMMYFUNCTION("""COMPUTED_VALUE"""),"Danbee Kim") -> Danbee Kim | E76: =IFERROR(__xludf.DUMMYFUNCTION("""COMPUTED_VALUE"""),1141.18) -> 1141.18 | G76: =IFERROR(__xludf.DUMMYFUNCTION("""COMPUTED_VALUE"""),"Yes") -> Yes | H76: =IFERROR(__xludf.DUMMYFUNCTION("""COMPUTED_VALUE"""),46185.406006944446) -> 46185.406
A77: =IFERROR(__xludf.DUMMYFUNCTION("""COMPUTED_VALUE"""),8657.0) -> 8657 | B77: =IFERROR(__xludf.DUMMYFUNCTION("""COMPUTED_VALUE"""),"Briar Cho") -> Briar Cho | E77: =IFERROR(__xludf.DUMMYFUNCTION("""COMPUTED_VALUE"""),1740.57) -> 1740.57 | G77: =IFERROR(__xludf.DUMMYFUNCTION("""COMPUTED_VALUE"""),"Yes") -> Yes | H77: =IFERROR(__xludf.DUMMYFUNCTION("""COMPUTED_VALUE"""),46184.44306712963) -> 46184.443
A78: =IFERROR(__xludf.DUMMYFUNCTION("""COMPUTED_VALUE"""),8312.0) -> 8312 | B78: =IFERROR(__xludf.DUMMYFUNCTION("""COMPUTED_VALUE"""),"Ellie Kim") -> Ellie Kim | E78: =IFERROR(__xludf.DUMMYFUNCTION("""COMPUTED_VALUE"""),1000.0) -> 1000 | G78: =IFERROR(__xludf.DUMMYFUNCTION("""COMPUTED_VALUE"""),"Yes") -> Yes
A79: =IFERROR(__xludf.DUMMYFUNCTION("""COMPUTED_VALUE"""),6657.0) -> 6657 | B79: =IFERROR(__xludf.DUMMYFUNCTION("""COMPUTED_VALUE"""),"Chaewon Jeon") -> Chaewon Jeon | E79: =IFERROR(__xludf.DUMMYFUNCTION("""COMPUTED_VALUE"""),1390.51) -> 1390.51 | G79: =IFERROR(__xludf.DUMMYFUNCTION("""COMPUTED_VALUE"""),"Yes") -> Yes | H79: =IFERROR(__xludf.DUMMYFUNCTION("""COMPUTED_VALUE"""),46185.51641203704) -> 46185.516
A80: =IFERROR(__xludf.DUMMYFUNCTION("""COMPUTED_VALUE"""),9500.0) -> 9500 | B80: =IFERROR(__xludf.DUMMYFUNCTION("""COMPUTED_VALUE"""),"Irene Choi") -> Irene Choi | E80: =IFERROR(__xludf.DUMMYFUNCTION("""COMPUTED_VALUE"""),1389.61) -> 1389.61 | G80: =IFERROR(__xludf.DUMMYFUNCTION("""COMPUTED_VALUE"""),"Yes") -> Yes | H80: =IFERROR(__xludf.DUMMYFUNCTION("""COMPUTED_VALUE"""),46184.42736111111) -> 46184.427

Sheet Imported_Transactions
A1: =IFERROR(__xludf.DUMMYFUNCTION("IMPORTRANGE(""https://docs.google.com/spreadsheets/d/1xmGsP2eOXdfhJ9DjzCOVFJKoZ2DuuwRb_dbNg1M77M8/edit?gid=138364344#gid=138364344"",""Transactions!A:L"")"),"Money / Store Transaction Log") -> Money / Store Transaction Log
A3: =IFERROR(__xludf.DUMMYFUNCTION("""COMPUTED_VALUE"""),"Timestamp") -> Timestamp | B3: =IFERROR(__xludf.DUMMYFUNCTION("""COMPUTED_VALUE"""),"Date") -> Date | C3: =IFERROR(__xludf.DUMMYFUNCTION("""COMPUTED_VALUE"""),"Card_ID") -> Card_ID | D3: =IFERROR(__xludf.DUMMYFUNCTION("""COMPUTED_VALUE"""),"Student_Name") -> Student_Name | E3: =IFERROR(__xludf.DUMMYFUNCTION("""COMPUTED_VALUE"""),"Mode") -> Mode | F3: =IFERROR(__xludf.DUMMYFUNCTION("""COMPUTED_VALUE"""),"Amount") -> Amount | G3: =IFERROR(__xludf.DUMMYFUNCTION("""COMPUTED_VALUE"""),"Starting_Balance") -> Starting_Balance | H3: =IFERROR(__xludf.DUMMYFUNCTION("""COMPUTED_VALUE"""),"Ending_Balance") -> Ending_Balance | I3: =IFERROR(__xludf.DUMMYFUNCTION("""COMPUTED_VALUE"""),"Item_ID") -> Item_ID | J3: =IFERROR(__xludf.DUMMYFUNCTION("""COMPUTED_VALUE"""),"Item_Name") -> Item_Name | K3: =IFERROR(__xludf.DUMMYFUNCTION("""COMPUTED_VALUE"""),"Note") -> Note | L3: =IFERROR(__xludf.DUMMYFUNCTION("""COMPUTED_VALUE"""),"Status") -> Status
A4: =IFERROR(__xludf.DUMMYFUNCTION("""COMPUTED_VALUE"""),46163.34710648148) -> 46163.347 | B4: =IFERROR(__xludf.DUMMYFUNCTION("""COMPUTED_VALUE"""),46163.0) -> 46163 | C4: =IFERROR(__xludf.DUMMYFUNCTION("""COMPUTED_VALUE"""),"5c07fef4") -> 5c07fef4 | D4: =IFERROR(__xludf.DUMMYFUNCTION("""COMPUTED_VALUE"""),"Tiffany Kim") -> Tiffany Kim | E4: =IFERROR(__xludf.DUMMYFUNCTION("""COMPUTED_VALUE"""),"REWARD") -> REWARD | F4: =IFERROR(__xludf.DUMMYFUNCTION("""COMPUTED_VALUE"""),10.0) -> 10 | G4: =IFERROR(__xludf.DUMMYFUNCTION("""COMPUTED_VALUE"""),0.0) -> 0 | H4: =IFERROR(__xludf.DUMMYFUNCTION("""COMPUTED_VALUE"""),10.0) -> 10 | K4: =IFERROR(__xludf.DUMMYFUNCTION("""COMPUTED_VALUE"""),"On-time attendance reward") -> On-time attendance reward | L4: =IFERROR(__xludf.DUMMYFUNCTION("""COMPUTED_VALUE"""),"Success") -> Success
A5: =IFERROR(__xludf.DUMMYFUNCTION("""COMPUTED_VALUE"""),46163.34847222222) -> 46163.348 | B5: =IFERROR(__xludf.DUMMYFUNCTION("""COMPUTED_VALUE"""),46163.0) -> 46163 | C5: =IFERROR(__xludf.DUMMYFUNCTION("""COMPUTED_VALUE"""),"babde4c4") -> babde4c4 | D5: =IFERROR(__xludf.DUMMYFUNCTION("""COMPUTED_VALUE"""),"Ashley Guk") -> Ashley Guk | E5: =IFERROR(__xludf.DUMMYFUNCTION("""COMPUTED_VALUE"""),"REWARD") -> REWARD | F5: =IFERROR(__xludf.DUMMYFUNCTION("""COMPUTED_VALUE"""),10.0) -> 10 | G5: =IFERROR(__xludf.DUMMYFUNCTION("""COMPUTED_VALUE"""),0.0) -> 0 | H5: =IFERROR(__xludf.DUMMYFUNCTION("""COMPUTED_VALUE"""),10.0) -> 10 | K5: =IFERROR(__xludf.DUMMYFUNCTION("""COMPUTED_VALUE"""),"On-time attendance reward") -> On-time attendance reward | L5: =IFERROR(__xludf.DUMMYFUNCTION("""COMPUTED_VALUE"""),"Success") -> Success
A6: =IFERROR(__xludf.DUMMYFUNCTION("""COMPUTED_VALUE"""),46164.34847222222) -> 46164.348 | B6: =IFERROR(__xludf.DUMMYFUNCTION("""COMPUTED_VALUE"""),46164.0) -> 46164 | C6: =IFERROR(__xludf.DUMMYFUNCTION("""COMPUTED_VALUE"""),"ba912211") -> ba912211 | D6: =IFERROR(__xludf.DUMMYFUNCTION("""COMPUTED_VALUE"""),"Daisy Dou") -> Daisy Dou | E6: =IFERROR(__xludf.DUMMYFUNCTION("""COMPUTED_VALUE"""),"REWARD") -> REWARD | F6: =IFERROR(__xludf.DUMMYFUNCTION("""COMPUTED_VALUE"""),10.0) -> 10 | G6: =IFERROR(__xludf.DUMMYFUNCTION("""COMPUTED_VALUE"""),0.0) -> 0 | H6: =IFERROR(__xludf.DUMMYFUNCTION("""COMPUTED_VALUE"""),10.0) -> 10 | K6: =IFERROR(__xludf.DUMMYFUNCTION("""COMPUTED_VALUE"""),"On-time attendance reward") -> On-time attendance reward | L6: =IFERROR(__xludf.DUMMYFUNCTION("""COMPUTED_VALUE"""),"Success") -> Success
A7: =IFERROR(__xludf.DUMMYFUNCTION("""COMPUTED_VALUE"""),46163.34946759259) -> 46163.349 | B7: =IFERROR(__xludf.DUMMYFUNCTION("""COMPUTED_VALUE"""),46163.0) -> 46163 | C7: =IFERROR(__xludf.DUMMYFUNCTION("""COMPUTED_VALUE"""),"dc04eef4") -> dc04eef4 | D7: =IFERROR(__xludf.DUMMYFUNCTION("""COMPUTED_VALUE"""),"Joshua Jung") -> Joshua Jung | E7: =IFERROR(__xludf.DUMMYFUNCTION("""COMPUTED_VALUE"""),"REWARD") -> REWARD | F7: =IFERROR(__xludf.DUMMYFUNCTION("""COMPUTED_VALUE"""),10.0) -> 10 | G7: =IFERROR(__xludf.DUMMYFUNCTION("""COMPUTED_VALUE"""),0.0) -> 0 | H7: =IFERROR(__xludf.DUMMYFUNCTION("""COMPUTED_VALUE"""),10.0) -> 10 | K7: =IFERROR(__xludf.DUMMYFUNCTION("""COMPUTED_VALUE"""),"On-time attendance reward") -> On-time attendance reward | L7: =IFERROR(__xludf.DUMMYFUNCTION("""COMPUTED_VALUE"""),"Success") -> Success
A8: =IFERROR(__xludf.DUMMYFUNCTION("""COMPUTED_VALUE"""),46163.35591435185) -> 46163.356 | B8: =IFERROR(__xludf.DUMMYFUNCTION("""COMPUTED_VALUE"""),46163.0) -> 46163 | C8: =IFERROR(__xludf.DUMMYFUNCTION("""COMPUTED_VALUE"""),"5a032611") -> 5a032611 | D8: =IFERROR(__xludf.DUMMYFUNCTION("""COMPUTED_VALUE"""),"Harold Dou") -> Harold Dou | E8: =IFERROR(__xludf.DUMMYFUNCTION("""COMPUTED_VALUE"""),"REWARD") -> REWARD | F8: =IFERROR(__xludf.DUMMYFUNCTION("""COMPUTED_VALUE"""),10.0) -> 10 | G8: =IFERROR(__xludf.DUMMYFUNCTION("""COMPUTED_VALUE"""),0.0) -> 0 | H8: =IFERROR(__xludf.DUMMYFUNCTION("""COMPUTED_VALUE"""),10.0) -> 10 | K8: =IFERROR(__xludf.DUMMYFUNCTION("""COMPUTED_VALUE"""),"On-time attendance reward") -> On-time attendance reward | L8: =IFERROR(__xludf.DUMMYFUNCTION("""COMPUTED_VALUE"""),"Success") -> Success
A9: =IFERROR(__xludf.DUMMYFUNCTION("""COMPUTED_VALUE"""),46163.356261574074) -> 46163.356 | B9: =IFERROR(__xludf.DUMMYFUNCTION("""COMPUTED_VALUE"""),46163.0) -> 46163 | C9: =IFERROR(__xludf.DUMMYFUNCTION("""COMPUTED_VALUE"""),"ba353911") -> ba353911 | D9: =IFERROR(__xludf.DUMMYFUNCTION("""COMPUTED_VALUE"""),"Dayeon Kang") -> Dayeon Kang | E9: =IFERROR(__xludf.DUMMYFUNCTION("""COMPUTED_VALUE"""),"REWARD") -> REWARD | F9: =IFERROR(__xludf.DUMMYFUNCTION("""COMPUTED_VALUE"""),10.0) -> 10 | G9: =IFERROR(__xludf.DUMMYFUNCTION("""COMPUTED_VALUE"""),0.0) -> 0 | H9: =IFERROR(__xludf.DUMMYFUNCTION("""COMPUTED_VALUE"""),10.0) -> 10 | K9: =IFERROR(__xludf.DUMMYFUNCTION("""COMPUTED_VALUE"""),"On-time attendance reward") -> On-time attendance reward | L9: =IFERROR(__xludf.DUMMYFUNCTION("""COMPUTED_VALUE"""),"Success") -> Success
A10: =IFERROR(__xludf.DUMMYFUNCTION("""COMPUTED_VALUE"""),46164.356261574074) -> 46164.356 | B10: =IFERROR(__xludf.DUMMYFUNCTION("""COMPUTED_VALUE"""),46164.0) -> 46164 | C10: =IFERROR(__xludf.DUMMYFUNCTION("""COMPUTED_VALUE"""),"7c4e261e") -> 7c4e261e | D10: =IFERROR(__xludf.DUMMYFUNCTION("""COMPUTED_VALUE"""),"Suha Lee") -> Suha Lee | E10: =IFERROR(__xludf.DUMMYFUNCTION("""COMPUTED_VALUE"""),"REWARD") -> REWARD | F10: =IFERROR(__xludf.DUMMYFUNCTION("""COMPUTED_VALUE"""),10.0) -> 10 | G10: =IFERROR(__xludf.DUMMYFUNCTION("""COMPUTED_VALUE"""),0.0) -> 0 | H10: =IFERROR(__xludf.DUMMYFUNCTION("""COMPUTED_VALUE"""),10.0) -> 10 | K10: =IFERROR(__xludf.DUMMYFUNCTION("""COMPUTED_VALUE"""),"On-time attendance reward") -> On-time attendance reward | L10: =IFERROR(__xludf.DUMMYFUNCTION("""COMPUTED_VALUE"""),"Success") -> Success
A11: =IFERROR(__xludf.DUMMYFUNCTION("""COMPUTED_VALUE"""),46163.36684027778) -> 46163.367 | B11: =IFERROR(__xludf.DUMMYFUNCTION("""COMPUTED_VALUE"""),46163.0) -> 46163 | C11: =IFERROR(__xludf.DUMMYFUNCTION("""COMPUTED_VALUE"""),"9a5f2811") -> 9a5f2811 | D11: =IFERROR(__xludf.DUMMYFUNCTION("""COMPUTED_VALUE"""),"Junyoung Yoo") -> Junyoung Yoo | E11: =IFERROR(__xludf.DUMMYFUNCTION("""COMPUTED_VALUE"""),"FINE") -> FINE | F11: =IFERROR(__xludf.DUMMYFUNCTION("""COMPUTED_VALUE"""),10.0) -> 10 | G11: =IFERROR(__xludf.DUMMYFUNCTION("""COMPUTED_VALUE"""),0.0) -> 0 | H11: =IFERROR(__xludf.DUMMYFUNCTION("""COMPUTED_VALUE"""),0.0) -> 0 | K11: =IFERROR(__xludf.DUMMYFUNCTION("""COMPUTED_VALUE"""),"Late attendance penalty") -> Late attendance penalty | L11: =IFERROR(__xludf.DUMMYFUNCTION("""COMPUTED_VALUE"""),"Denied - insufficient balance") -> Denied - insufficient balance
A12: =IFERROR(__xludf.DUMMYFUNCTION("""COMPUTED_VALUE"""),46164.36684027778) -> 46164.367 | B12: =IFERROR(__xludf.DUMMYFUNCTION("""COMPUTED_VALUE"""),46164.0) -> 46164 | C12: =IFERROR(__xludf.DUMMYFUNCTION("""COMPUTED_VALUE"""),"1e3e1410") -> 1e3e1410 | D12: =IFERROR(__xludf.DUMMYFUNCTION("""COMPUTED_VALUE"""),"Junjae Park") -> Junjae Park | E12: =IFERROR(__xludf.DUMMYFUNCTION("""COMPUTED_VALUE"""),"FINE") -> FINE | F12: =IFERROR(__xludf.DUMMYFUNCTION("""COMPUTED_VALUE"""),10.0) -> 10 | G12: =IFERROR(__xludf.DUMMYFUNCTION("""COMPUTED_VALUE"""),0.0) -> 0 | H12: =IFERROR(__xludf.DUMMYFUNCTION("""COMPUTED_VALUE"""),0.0) -> 0 | K12: =IFERROR(__xludf.DUMMYFUNCTION("""COMPUTED_VALUE"""),"Late attendance penalty") -> Late attendance penalty | L12: =IFERROR(__xludf.DUMMYFUNCTION("""COMPUTED_VALUE"""),"Denied - insufficient balance") -> Denied - insufficient balance
A13: =IFERROR(__xludf.DUMMYFUNCTION("""COMPUTED_VALUE"""),46163.465162037035) -> 46163.465 | B13: =IFERROR(__xludf.DUMMYFUNCTION("""COMPUTED_VALUE"""),46163.0) -> 46163 | C13: =IFERROR(__xludf.DUMMYFUNCTION("""COMPUTED_VALUE"""),"9a5f2811") -> 9a5f2811 | D13: =IFERROR(__xludf.DUMMYFUNCTION("""COMPUTED_VALUE"""),"Junyoung Yoo") -> Junyoung Yoo | E13: =IFERROR(__xludf.DUMMYFUNCTION("""COMPUTED_VALUE"""),"DEPOSIT") -> DEPOSIT | F13: =IFERROR(__xludf.DUMMYFUNCTION("""COMPUTED_VALUE"""),20.0) -> 20 | G13: =IFERROR(__xludf.DUMMYFUNCTION("""COMPUTED_VALUE"""),0.0) -> 0 | H13: =IFERROR(__xludf.DUMMYFUNCTION("""COMPUTED_VALUE"""),20.0) -> 20 | L13: =IFERROR(__xludf.DUMMYFUNCTION("""COMPUTED_VALUE"""),"Success") -> Success
A14: =IFERROR(__xludf.DUMMYFUNCTION("""COMPUTED_VALUE"""),46163.46760416667) -> 46163.468 | B14: =IFERROR(__xludf.DUMMYFUNCTION("""COMPUTED_VALUE"""),46163.0) -> 46163 | C14: =IFERROR(__xludf.DUMMYFUNCTION("""COMPUTED_VALUE"""),"7c4e261e") -> 7c4e261e | D14: =IFERROR(__xludf.DUMMYFUNCTION("""COMPUTED_VALUE"""),"Suha Lee") -> Suha Lee | E14: =IFERROR(__xludf.DUMMYFUNCTION("""COMPUTED_VALUE"""),"DEPOSIT") -> DEPOSIT | F14: =IFERROR(__xludf.DUMMYFUNCTION("""COMPUTED_VALUE"""),20.0) -> 20 | G14: =IFERROR(__xludf.DUMMYFUNCTION("""COMPUTED_VALUE"""),10.0) -> 10 | H14: =IFERROR(__xludf.DUMMYFUNCTION("""COMPUTED_VALUE"""),30.0) -> 30 | L14: =IFERROR(__xludf.DUMMYFUNCTION("""COMPUTED_VALUE"""),"Success") -> Success
A15: =IFERROR(__xludf.DUMMYFUNCTION("""COMPUTED_VALUE"""),46163.469618055555) -> 46163.47 | B15: =IFERROR(__xludf.DUMMYFUNCTION("""COMPUTED_VALUE"""),46163.0) -> 46163 | C15: =IFERROR(__xludf.DUMMYFUNCTION("""COMPUTED_VALUE"""),"5a032611") -> 5a032611 | D15: =IFERROR(__xludf.DUMMYFUNCTION("""COMPUTED_VALUE"""),"Harold Dou") -> Harold Dou | E15: =IFERROR(__xludf.DUMMYFUNCTION("""COMPUTED_VALUE"""),"DEPOSIT") -> DEPOSIT | F15: =IFERROR(__xludf.DUMMYFUNCTION("""COMPUTED_VALUE"""),20.0) -> 20 | G15: =IFERROR(__xludf.DUMMYFUNCTION("""COMPUTED_VALUE"""),10.0) -> 10 | H15: =IFERROR(__xludf.DUMMYFUNCTION("""COMPUTED_VALUE"""),30.0) -> 30 | L15: =IFERROR(__xludf.DUMMYFUNCTION("""COMPUTED_VALUE"""),"Success") -> Success
A16: =IFERROR(__xludf.DUMMYFUNCTION("""COMPUTED_VALUE"""),46163.472037037034) -> 46163.472 | B16: =IFERROR(__xludf.DUMMYFUNCTION("""COMPUTED_VALUE"""),46163.0) -> 46163 | C16: =IFERROR(__xludf.DUMMYFUNCTION("""COMPUTED_VALUE"""),"babde4c4") -> babde4c4 | D16: =IFERROR(__xludf.DUMMYFUNCTION("""COMPUTED_VALUE"""),"Ashley Guk") -> Ashley Guk | E16: =IFERROR(__xludf.DUMMYFUNCTION("""COMPUTED_VALUE"""),"DEPOSIT") -> DEPOSIT | F16: =IFERROR(__xludf.DUMMYFUNCTION("""COMPUTED_VALUE"""),20.0) -> 20 | G16: =IFERROR(__xludf.DUMMYFUNCTION("""COMPUTED_VALUE"""),10.0) -> 10 | H16: =IFERROR(__xludf.DUMMYFUNCTION("""COMPUTED_VALUE"""),30.0) -> 30 | L16: =IFERROR(__xludf.DUMMYFUNCTION("""COMPUTED_VALUE"""),"Success") -> Success
A17: =IFERROR(__xludf.DUMMYFUNCTION("""COMPUTED_VALUE"""),46163.474490740744) -> 46163.474 | B17: =IFERROR(__xludf.DUMMYFUNCTION("""COMPUTED_VALUE"""),46163.0) -> 46163 | C17: =IFERROR(__xludf.DUMMYFUNCTION("""COMPUTED_VALUE"""),"dc04eef4") -> dc04eef4 | D17: =IFERROR(__xludf.DUMMYFUNCTION("""COMPUTED_VALUE"""),"Joshua Jung") -> Joshua Jung | E17: =IFERROR(__xludf.DUMMYFUNCTION("""COMPUTED_VALUE"""),"DEPOSIT") -> DEPOSIT | F17: =IFERROR(__xludf.DUMMYFUNCTION("""COMPUTED_VALUE"""),20.0) -> 20 | G17: =IFERROR(__xludf.DUMMYFUNCTION("""COMPUTED_VALUE"""),10.0) -> 10 | H17: =IFERROR(__xludf.DUMMYFUNCTION("""COMPUTED_VALUE"""),30.0) -> 30 | L17: =IFERROR(__xludf.DUMMYFUNCTION("""COMPUTED_VALUE"""),"Success") -> Success
A18: =IFERROR(__xludf.DUMMYFUNCTION("""COMPUTED_VALUE"""),46163.47461805555) -> 46163.475 | B18: =IFERROR(__xludf.DUMMYFUNCTION("""COMPUTED_VALUE"""),46163.0) -> 46163 | C18: =IFERROR(__xludf.DUMMYFUNCTION("""COMPUTED_VALUE"""),"1e3e1410") -> 1e3e1410 | D18: =IFERROR(__xludf.DUMMYFUNCTION("""COMPUTED_VALUE"""),"Junjae Park") -> Junjae Park | E18: =IFERROR(__xludf.DUMMYFUNCTION("""COMPUTED_VALUE"""),"DEPOSIT") -> DEPOSIT | F18: =IFERROR(__xludf.DUMMYFUNCTION("""COMPUTED_VALUE"""),20.0) -> 20 | G18: =IFERROR(__xludf.DUMMYFUNCTION("""COMPUTED_VALUE"""),0.0) -> 0 | H18: =IFERROR(__xludf.DUMMYFUNCTION("""COMPUTED_VALUE"""),20.0) -> 20 | L18: =IFERROR(__xludf.DUMMYFUNCTION("""COMPUTED_VALUE"""),"Success") -> Success
A19: =IFERROR(__xludf.DUMMYFUNCTION("""COMPUTED_VALUE"""),46164.34457175926) -> 46164.345 | B19: =IFERROR(__xludf.DUMMYFUNCTION("""COMPUTED_VALUE"""),46164.0) -> 46164 | C19: =IFERROR(__xludf.DUMMYFUNCTION("""COMPUTED_VALUE"""),"5c07fef4") -> 5c07fef4 | D19: =IFERROR(__xludf.DUMMYFUNCTION("""COMPUTED_VALUE"""),"Tiffany Kim") -> Tiffany Kim | E19: =IFERROR(__xludf.DUMMYFUNCTION("""COMPUTED_VALUE"""),"REWARD") -> REWARD | F19: =IFERROR(__xludf.DUMMYFUNCTION("""COMPUTED_VALUE"""),10.0) -> 10 | G19: =IFERROR(__xludf.DUMMYFUNCTION("""COMPUTED_VALUE"""),10.0) -> 10 | H19: =IFERROR(__xludf.DUMMYFUNCTION("""COMPUTED_VALUE"""),20.0) -> 20 | K19: =IFERROR(__xludf.DUMMYFUNCTION("""COMPUTED_VALUE"""),"On-time attendance reward") -> On-time attendance reward | L19: =IFERROR(__xludf.DUMMYFUNCTION("""COMPUTED_VALUE"""),"Success") -> Success
A20: =IFERROR(__xludf.DUMMYFUNCTION("""COMPUTED_VALUE"""),46164.353368055556) -> 46164.353 | B20: =IFERROR(__xludf.DUMMYFUNCTION("""COMPUTED_VALUE"""),46164.0) -> 46164 | C20: =IFERROR(__xludf.DUMMYFUNCTION("""COMPUTED_VALUE"""),"dc04eef4") -> dc04eef4 | D20: =IFERROR(__xludf.DUMMYFUNCTION("""COMPUTED_VALUE"""),"Joshua Jung") -> Joshua Jung | E20: =IFERROR(__xludf.DUMMYFUNCTION("""COMPUTED_VALUE"""),"REWARD") -> REWARD | F20: =IFERROR(__xludf.DUMMYFUNCTION("""COMPUTED_VALUE"""),10.0) -> 10 | G20: =IFERROR(__xludf.DUMMYFUNCTION("""COMPUTED_VALUE"""),30.0) -> 30 | H20: =IFERROR(__xludf.DUMMYFUNCTION("""COMPUTED_VALUE"""),40.0) -> 40 | K20: =IFERROR(__xludf.DUMMYFUNCTION("""COMPUTED_VALUE"""),"On-time attendance reward") -> On-time attendance reward | L20: =IFERROR(__xludf.DUMMYFUNCTION("""COMPUTED_VALUE"""),"Success") -> Success
A21: =IFERROR(__xludf.DUMMYFUNCTION("""COMPUTED_VALUE"""),46164.35349537037) -> 46164.353 | B21: =IFERROR(__xludf.DUMMYFUNCTION("""COMPUTED_VALUE"""),46164.0) -> 46164 | C21: =IFERROR(__xludf.DUMMYFUNCTION("""COMPUTED_VALUE"""),"ba912211") -> ba912211 | D21: =IFERROR(__xludf.DUMMYFUNCTION("""COMPUTED_VALUE"""),"Daisy Dou") -> Daisy Dou | E21: =IFERROR(__xludf.DUMMYFUNCTION("""COMPUTED_VALUE"""),"REWARD") -> REWARD | F21: =IFERROR(__xludf.DUMMYFUNCTION("""COMPUTED_VALUE"""),10.0) -> 10 | G21: =IFERROR(__xludf.DUMMYFUNCTION("""COMPUTED_VALUE"""),10.0) -> 10 | H21: =IFERROR(__xludf.DUMMYFUNCTION("""COMPUTED_VALUE"""),20.0) -> 20 | K21: =IFERROR(__xludf.DUMMYFUNCTION("""COMPUTED_VALUE"""),"On-time attendance reward") -> On-time attendance reward | L21: =IFERROR(__xludf.DUMMYFUNCTION("""COMPUTED_VALUE"""),"Success") -> Success
A22: =IFERROR(__xludf.DUMMYFUNCTION("""COMPUTED_VALUE"""),46164.353634259256) -> 46164.354 | B22: =IFERROR(__xludf.DUMMYFUNCTION("""COMPUTED_VALUE"""),46164.0) -> 46164 | C22: =IFERROR(__xludf.DUMMYFUNCTION("""COMPUTED_VALUE"""),"babde4c4") -> babde4c4 | D22: =IFERROR(__xludf.DUMMYFUNCTION("""COMPUTED_VALUE"""),"Ashley Guk") -> Ashley Guk | E22: =IFERROR(__xludf.DUMMYFUNCTION("""COMPUTED_VALUE"""),"REWARD") -> REWARD | F22: =IFERROR(__xludf.DUMMYFUNCTION("""COMPUTED_VALUE"""),10.0) -> 10 | G22: =IFERROR(__xludf.DUMMYFUNCTION("""COMPUTED_VALUE"""),30.0) -> 30 | H22: =IFERROR(__xludf.DUMMYFUNCTION("""COMPUTED_VALUE"""),40.0) -> 40 | K22: =IFERROR(__xludf.DUMMYFUNCTION("""COMPUTED_VALUE"""),"On-time attendance reward") -> On-time attendance reward | L22: =IFERROR(__xludf.DUMMYFUNCTION("""COMPUTED_VALUE"""),"Success") -> Success
A23: =IFERROR(__xludf.DUMMYFUNCTION("""COMPUTED_VALUE"""),46164.354409722226) -> 46164.354 | B23: =IFERROR(__xludf.DUMMYFUNCTION("""COMPUTED_VALUE"""),46164.0) -> 46164 | C23: =IFERROR(__xludf.DUMMYFUNCTION("""COMPUTED_VALUE"""),"7c4e261e") -> 7c4e261e | D23: =IFERROR(__xludf.DUMMYFUNCTION("""COMPUTED_VALUE"""),"Suha Lee") -> Suha Lee | E23: =IFERROR(__xludf.DUMMYFUNCTION("""COMPUTED_VALUE"""),"REWARD") -> REWARD | F23: =IFERROR(__xludf.DUMMYFUNCTION("""COMPUTED_VALUE"""),10.0) -> 10 | G23: =IFERROR(__xludf.DUMMYFUNCTION("""COMPUTED_VALUE"""),30.0) -> 30 | H23: =IFERROR(__xludf.DUMMYFUNCTION("""COMPUTED_VALUE"""),40.0) -> 40 | K23: =IFERROR(__xludf.DUMMYFUNCTION("""COMPUTED_VALUE"""),"On-time attendance reward") -> On-time attendance reward | L23: =IFERROR(__xludf.DUMMYFUNCTION("""COMPUTED_VALUE"""),"Success") -> Success
A24: =IFERROR(__xludf.DUMMYFUNCTION("""COMPUTED_VALUE"""),46164.35689814815) -> 46164.357 | B24: =IFERROR(__xludf.DUMMYFUNCTION("""COMPUTED_VALUE"""),46164.0) -> 46164 | C24: =IFERROR(__xludf.DUMMYFUNCTION("""COMPUTED_VALUE"""),"ba353911") -> ba353911 | D24: =IFERROR(__xludf.DUMMYFUNCTION("""COMPUTED_VALUE"""),"Dayeon Kang") -> Dayeon Kang | E24: =IFERROR(__xludf.DUMMYFUNCTION("""COMPUTED_VALUE"""),"REWARD") -> REWARD | F24: =IFERROR(__xludf.DUMMYFUNCTION("""COMPUTED_VALUE"""),10.0) -> 10 | G24: =IFERROR(__xludf.DUMMYFUNCTION("""COMPUTED_VALUE"""),10.0) -> 10 | H24: =IFERROR(__xludf.DUMMYFUNCTION("""COMPUTED_VALUE"""),20.0) -> 20 | K24: =IFERROR(__xludf.DUMMYFUNCTION("""COMPUTED_VALUE"""),"On-time attendance reward") -> On-time attendance reward | L24: =IFERROR(__xludf.DUMMYFUNCTION("""COMPUTED_VALUE"""),"Success") -> Success
A25: =IFERROR(__xludf.DUMMYFUNCTION("""COMPUTED_VALUE"""),46164.357037037036) -> 46164.357 | B25: =IFERROR(__xludf.DUMMYFUNCTION("""COMPUTED_VALUE"""),46164.0) -> 46164 | C25: =IFERROR(__xludf.DUMMYFUNCTION("""COMPUTED_VALUE"""),"5a032611") -> 5a032611 | D25: =IFERROR(__xludf.DUMMYFUNCTION("""COMPUTED_VALUE"""),"Harold Dou") -> Harold Dou | E25: =IFERROR(__xludf.DUMMYFUNCTION("""COMPUTED_VALUE"""),"REWARD") -> REWARD | F25: =IFERROR(__xludf.DUMMYFUNCTION("""COMPUTED_VALUE"""),10.0) -> 10 | G25: =IFERROR(__xludf.DUMMYFUNCTION("""COMPUTED_VALUE"""),30.0) -> 30 | H25: =IFERROR(__xludf.DUMMYFUNCTION("""COMPUTED_VALUE"""),40.0) -> 40 | K25: =IFERROR(__xludf.DUMMYFUNCTION("""COMPUTED_VALUE"""),"On-time attendance reward") -> On-time attendance reward | L25: =IFERROR(__xludf.DUMMYFUNCTION("""COMPUTED_VALUE"""),"Success") -> Success
A26: =IFERROR(__xludf.DUMMYFUNCTION("""COMPUTED_VALUE"""),46164.35717592593) -> 46164.357 | B26: =IFERROR(__xludf.DUMMYFUNCTION("""COMPUTED_VALUE"""),46164.0) -> 46164 | C26: =IFERROR(__xludf.DUMMYFUNCTION("""COMPUTED_VALUE"""),"9a5f2811") -> 9a5f2811 | D26: =IFERROR(__xludf.DUMMYFUNCTION("""COMPUTED_VALUE"""),"Junyoung Yoo") -> Junyoung Yoo | E26: =IFERROR(__xludf.DUMMYFUNCTION("""COMPUTED_VALUE"""),"REWARD") -> REWARD | F26: =IFERROR(__xludf.DUMMYFUNCTION("""COMPUTED_VALUE"""),10.0) -> 10 | G26: =IFERROR(__xludf.DUMMYFUNCTION("""COMPUTED_VALUE"""),20.0) -> 20 | H26: =IFERROR(__xludf.DUMMYFUNCTION("""COMPUTED_VALUE"""),30.0) -> 30 | K26: =IFERROR(__xludf.DUMMYFUNCTION("""COMPUTED_VALUE"""),"On-time attendance reward") -> On-time attendance reward | L26: =IFERROR(__xludf.DUMMYFUNCTION("""COMPUTED_VALUE"""),"Success") -> Success
A27: =IFERROR(__xludf.DUMMYFUNCTION("""COMPUTED_VALUE"""),46164.35865740741) -> 46164.359 | B27: =IFERROR(__xludf.DUMMYFUNCTION("""COMPUTED_VALUE"""),46164.0) -> 46164 | C27: =IFERROR(__xludf.DUMMYFUNCTION("""COMPUTED_VALUE"""),"ba912211") -> ba912211 | D27: =IFERROR(__xludf.DUMMYFUNCTION("""COMPUTED_VALUE"""),"Daisy Dou") -> Daisy Dou | E27: =IFERROR(__xludf.DUMMYFUNCTION("""COMPUTED_VALUE"""),"DEPOSIT") -> DEPOSIT | F27: =IFERROR(__xludf.DUMMYFUNCTION("""COMPUTED_VALUE"""),71.0) -> 71 | G27: =IFERROR(__xludf.DUMMYFUNCTION("""COMPUTED_VALUE"""),20.0) -> 20 | H27: =IFERROR(__xludf.DUMMYFUNCTION("""COMPUTED_VALUE"""),91.0) -> 91 | L27: =IFERROR(__xludf.DUMMYFUNCTION("""COMPUTED_VALUE"""),"Success") -> Success
A28: =IFERROR(__xludf.DUMMYFUNCTION("""COMPUTED_VALUE"""),46164.359143518515) -> 46164.359 | B28: =IFERROR(__xludf.DUMMYFUNCTION("""COMPUTED_VALUE"""),46164.0) -> 46164 | C28: =IFERROR(__xludf.DUMMYFUNCTION("""COMPUTED_VALUE"""),"babde4c4") -> babde4c4 | D28: =IFERROR(__xludf.DUMMYFUNCTION("""COMPUTED_VALUE"""),"Ashley Guk") -> Ashley Guk | E28: =IFERROR(__xludf.DUMMYFUNCTION("""COMPUTED_VALUE"""),"DEPOSIT") -> DEPOSIT | F28: =IFERROR(__xludf.DUMMYFUNCTION("""COMPUTED_VALUE"""),16.0) -> 16 | G28: =IFERROR(__xludf.DUMMYFUNCTION("""COMPUTED_VALUE"""),40.0) -> 40 | H28: =IFERROR(__xludf.DUMMYFUNCTION("""COMPUTED_VALUE"""),56.0) -> 56 | L28: =IFERROR(__xludf.DUMMYFUNCTION("""COMPUTED_VALUE"""),"Success") -> Success
A29: =IFERROR(__xludf.DUMMYFUNCTION("""COMPUTED_VALUE"""),46168.33908564815) -> 46168.339 | B29: =IFERROR(__xludf.DUMMYFUNCTION("""COMPUTED_VALUE"""),46168.0) -> 46168 | C29: =IFERROR(__xludf.DUMMYFUNCTION("""COMPUTED_VALUE"""),"dc04eef4") -> dc04eef4 | D29: =IFERROR(__xludf.DUMMYFUNCTION("""COMPUTED_VALUE"""),"Joshua Jung") -> Joshua Jung | E29: =IFERROR(__xludf.DUMMYFUNCTION("""COMPUTED_VALUE"""),"REWARD") -> REWARD | F29: =IFERROR(__xludf.DUMMYFUNCTION("""COMPUTED_VALUE"""),10.0) -> 10 | G29: =IFERROR(__xludf.DUMMYFUNCTION("""COMPUTED_VALUE"""),40.0) -> 40 | H29: =IFERROR(__xludf.DUMMYFUNCTION("""COMPUTED_VALUE"""),50.0) -> 50 | K29: =IFERROR(__xludf.DUMMYFUNCTION("""COMPUTED_VALUE"""),"On-time attendance reward") -> On-time attendance reward | L29: =IFERROR(__xludf.DUMMYFUNCTION("""COMPUTED_VALUE"""),"Success") -> Success
A30: =IFERROR(__xludf.DUMMYFUNCTION("""COMPUTED_VALUE"""),46168.350902777776) -> 46168.351 | B30: =IFERROR(__xludf.DUMMYFUNCTION("""COMPUTED_VALUE"""),46168.0) -> 46168 | C30: =IFERROR(__xludf.DUMMYFUNCTION("""COMPUTED_VALUE"""),"5c07fef4") -> 5c07fef4 | D30: =IFERROR(__xludf.DUMMYFUNCTION("""COMPUTED_VALUE"""),"Tiffany Kim") -> Tiffany Kim | E30: =IFERROR(__xludf.DUMMYFUNCTION("""COMPUTED_VALUE"""),"REWARD") -> REWARD | F30: =IFERROR(__xludf.DUMMYFUNCTION("""COMPUTED_VALUE"""),10.0) -> 10 | G30: =IFERROR(__xludf.DUMMYFUNCTION("""COMPUTED_VALUE"""),20.0) -> 20 | H30: =IFERROR(__xludf.DUMMYFUNCTION("""COMPUTED_VALUE"""),30.0) -> 30 | K30: =IFERROR(__xludf.DUMMYFUNCTION("""COMPUTED_VALUE"""),"On-time attendance reward") -> On-time attendance reward | L30: =IFERROR(__xludf.DUMMYFUNCTION("""COMPUTED_VALUE"""),"Success") -> Success
A31: =IFERROR(__xludf.DUMMYFUNCTION("""COMPUTED_VALUE"""),46168.351643518516) -> 46168.352 | B31: =IFERROR(__xludf.DUMMYFUNCTION("""COMPUTED_VALUE"""),46168.0) -> 46168 | C31: =IFERROR(__xludf.DUMMYFUNCTION("""COMPUTED_VALUE"""),"ba912211") -> ba912211 | D31: =IFERROR(__xludf.DUMMYFUNCTION("""COMPUTED_VALUE"""),"Daisy Dou") -> Daisy Dou | E31: =IFERROR(__xludf.DUMMYFUNCTION("""COMPUTED_VALUE"""),"REWARD") -> REWARD | F31: =IFERROR(__xludf.DUMMYFUNCTION("""COMPUTED_VALUE"""),10.0) -> 10 | G31: =IFERROR(__xludf.DUMMYFUNCTION("""COMPUTED_VALUE"""),91.0) -> 91 | H31: =IFERROR(__xludf.DUMMYFUNCTION("""COMPUTED_VALUE"""),101.0) -> 101 | K31: =IFERROR(__xludf.DUMMYFUNCTION("""COMPUTED_VALUE"""),"On-time attendance reward") -> On-time attendance reward | L31: =IFERROR(__xludf.DUMMYFUNCTION("""COMPUTED_VALUE"""),"Success") -> Success
A32: =IFERROR(__xludf.DUMMYFUNCTION("""COMPUTED_VALUE"""),46168.35450231482) -> 46168.355 | B32: =IFERROR(__xludf.DUMMYFUNCTION("""COMPUTED_VALUE"""),46168.0) -> 46168 | C32: =IFERROR(__xludf.DUMMYFUNCTION("""COMPUTED_VALUE"""),"7c4e261e") -> 7c4e261e | D32: =IFERROR(__xludf.DUMMYFUNCTION("""COMPUTED_VALUE"""),"Suha Lee") -> Suha Lee | E32: =IFERROR(__xludf.DUMMYFUNCTION("""COMPUTED_VALUE"""),"REWARD") -> REWARD | F32: =IFERROR(__xludf.DUMMYFUNCTION("""COMPUTED_VALUE"""),10.0) -> 10 | G32: =IFERROR(__xludf.DUMMYFUNCTION("""COMPUTED_VALUE"""),40.0) -> 40 | H32: =IFERROR(__xludf.DUMMYFUNCTION("""COMPUTED_VALUE"""),50.0) -> 50 | K32: =IFERROR(__xludf.DUMMYFUNCTION("""COMPUTED_VALUE"""),"On-time attendance reward") -> On-time attendance reward | L32: =IFERROR(__xludf.DUMMYFUNCTION("""COMPUTED_VALUE"""),"Success") -> Success
A33: =IFERROR(__xludf.DUMMYFUNCTION("""COMPUTED_VALUE"""),46168.3559375) -> 46168.356 | B33: =IFERROR(__xludf.DUMMYFUNCTION("""COMPUTED_VALUE"""),46168.0) -> 46168 | C33: =IFERROR(__xludf.DUMMYFUNCTION("""COMPUTED_VALUE"""),"5a032611") -> 5a032611 | D33: =IFERROR(__xludf.DUMMYFUNCTION("""COMPUTED_VALUE"""),"Harold Dou") -> Harold Dou | E33: =IFERROR(__xludf.DUMMYFUNCTION("""COMPUTED_VALUE"""),"REWARD") -> REWARD | F33: =IFERROR(__xludf.DUMMYFUNCTION("""COMPUTED_VALUE"""),10.0) -> 10 | G33: =IFERROR(__xludf.DUMMYFUNCTION("""COMPUTED_VALUE"""),40.0) -> 40 | H33: =IFERROR(__xludf.DUMMYFUNCTION("""COMPUTED_VALUE"""),50.0) -> 50 | K33: =IFERROR(__xludf.DUMMYFUNCTION("""COMPUTED_VALUE"""),"On-time attendance reward") -> On-time attendance reward | L33: =IFERROR(__xludf.DUMMYFUNCTION("""COMPUTED_VALUE"""),"Success") -> Success
A34: =IFERROR(__xludf.DUMMYFUNCTION("""COMPUTED_VALUE"""),46168.35628472222) -> 46168.356 | B34: =IFERROR(__xludf.DUMMYFUNCTION("""COMPUTED_VALUE"""),46168.0) -> 46168 | C34: =IFERROR(__xludf.DUMMYFUNCTION("""COMPUTED_VALUE"""),"9a5f2811") -> 9a5f2811 | D34: =IFERROR(__xludf.DUMMYFUNCTION("""COMPUTED_VALUE"""),"Junyoung Yoo") -> Junyoung Yoo | E34: =IFERROR(__xludf.DUMMYFUNCTION("""COMPUTED_VALUE"""),"REWARD") -> REWARD | F34: =IFERROR(__xludf.DUMMYFUNCTION("""COMPUTED_VALUE"""),10.0) -> 10 | G34: =IFERROR(__xludf.DUMMYFUNCTION("""COMPUTED_VALUE"""),30.0) -> 30 | H34: =IFERROR(__xludf.DUMMYFUNCTION("""COMPUTED_VALUE"""),40.0) -> 40 | K34: =IFERROR(__xludf.DUMMYFUNCTION("""COMPUTED_VALUE"""),"On-time attendance reward") -> On-time attendance reward | L34: =IFERROR(__xludf.DUMMYFUNCTION("""COMPUTED_VALUE"""),"Success") -> Success
A35: =IFERROR(__xludf.DUMMYFUNCTION("""COMPUTED_VALUE"""),46168.35869212963) -> 46168.359 | B35: =IFERROR(__xludf.DUMMYFUNCTION("""COMPUTED_VALUE"""),46168.0) -> 46168 | C35: =IFERROR(__xludf.DUMMYFUNCTION("""COMPUTED_VALUE"""),"ba353911") -> ba353911 | D35: =IFERROR(__xludf.DUMMYFUNCTION("""COMPUTED_VALUE"""),"Dayeon Kang") -> Dayeon Kang | E35: =IFERROR(__xludf.DUMMYFUNCTION("""COMPUTED_VALUE"""),"FINE") -> FINE | F35: =IFERROR(__xludf.DUMMYFUNCTION("""COMPUTED_VALUE"""),10.0) -> 10 | G35: =IFERROR(__xludf.DUMMYFUNCTION("""COMPUTED_VALUE"""),20.0) -> 20 | H35: =IFERROR(__xludf.DUMMYFUNCTION("""COMPUTED_VALUE"""),10.0) -> 10 | K35: =IFERROR(__xludf.DUMMYFUNCTION("""COMPUTED_VALUE"""),"Late attendance penalty") -> Late attendance penalty | L35: =IFERROR(__xludf.DUMMYFUNCTION("""COMPUTED_VALUE"""),"Success") -> Success
A36: =IFERROR(__xludf.DUMMYFUNCTION("""COMPUTED_VALUE"""),46168.4943287037) -> 46168.494 | B36: =IFERROR(__xludf.DUMMYFUNCTION("""COMPUTED_VALUE"""),46168.0) -> 46168 | C36: =IFERROR(__xludf.DUMMYFUNCTION("""COMPUTED_VALUE"""),"ae072910") -> ae072910 | D36: =IFERROR(__xludf.DUMMYFUNCTION("""COMPUTED_VALUE"""),"Selena Jung") -> Selena Jung | E36: =IFERROR(__xludf.DUMMYFUNCTION("""COMPUTED_VALUE"""),"FINE") -> FINE | F36: =IFERROR(__xludf.DUMMYFUNCTION("""COMPUTED_VALUE"""),10.0) -> 10 | G36: =IFERROR(__xludf.DUMMYFUNCTION("""COMPUTED_VALUE"""),0.0) -> 0 | H36: =IFERROR(__xludf.DUMMYFUNCTION("""COMPUTED_VALUE"""),0.0) -> 0 | K36: =IFERROR(__xludf.DUMMYFUNCTION("""COMPUTED_VALUE"""),"Late attendance penalty") -> Late attendance penalty | L36: =IFERROR(__xludf.DUMMYFUNCTION("""COMPUTED_VALUE"""),"Denied - insufficient balance") -> Denied - insufficient balance
A37: =IFERROR(__xludf.DUMMYFUNCTION("""COMPUTED_VALUE"""),46168.65008101852) -> 46168.65 | B37: =IFERROR(__xludf.DUMMYFUNCTION("""COMPUTED_VALUE"""),46168.0) -> 46168 | C37: =IFERROR(__xludf.DUMMYFUNCTION("""COMPUTED_VALUE"""),"ba0fc5c4") -> ba0fc5c4 | D37: =IFERROR(__xludf.DUMMYFUNCTION("""COMPUTED_VALUE"""),"Junwoo Kang") -> Junwoo Kang | E37: =IFERROR(__xludf.DUMMYFUNCTION("""COMPUTED_VALUE"""),"FINE") -> FINE | F37: =IFERROR(__xludf.DUMMYFUNCTION("""COMPUTED_VALUE"""),10.0) -> 10 | G37: =IFERROR(__xludf.DUMMYFUNCTION("""COMPUTED_VALUE"""),0.0) -> 0 | H37: =IFERROR(__xludf.DUMMYFUNCTION("""COMPUTED_VALUE"""),0.0) -> 0 | K37: =IFERROR(__xludf.DUMMYFUNCTION("""COMPUTED_VALUE"""),"Late attendance penalty") -> Late attendance penalty | L37: =IFERROR(__xludf.DUMMYFUNCTION("""COMPUTED_VALUE"""),"Denied - insufficient balance") -> Denied - insufficient balance
A38: =IFERROR(__xludf.DUMMYFUNCTION("""COMPUTED_VALUE"""),46170.34722222222) -> 46170.347 | B38: =IFERROR(__xludf.DUMMYFUNCTION("""COMPUTED_VALUE"""),46170.0) -> 46170 | C38: =IFERROR(__xludf.DUMMYFUNCTION("""COMPUTED_VALUE"""),"ae072910") -> ae072910 | D38: =IFERROR(__xludf.DUMMYFUNCTION("""COMPUTED_VALUE"""),"Selena Jung") -> Selena Jung | E38: =IFERROR(__xludf.DUMMYFUNCTION("""COMPUTED_VALUE"""),"REWARD") -> REWARD | F38: =IFERROR(__xludf.DUMMYFUNCTION("""COMPUTED_VALUE"""),10.0) -> 10 | G38: =IFERROR(__xludf.DUMMYFUNCTION("""COMPUTED_VALUE"""),0.0) -> 0 | H38: =IFERROR(__xludf.DUMMYFUNCTION("""COMPUTED_VALUE"""),10.0) -> 10 | K38: =IFERROR(__xludf.DUMMYFUNCTION("""COMPUTED_VALUE"""),"On-time attendance reward") -> On-time attendance reward | L38: =IFERROR(__xludf.DUMMYFUNCTION("""COMPUTED_VALUE"""),"Success") -> Success
A39: =IFERROR(__xludf.DUMMYFUNCTION("""COMPUTED_VALUE"""),46170.35013888889) -> 46170.35 | B39: =IFERROR(__xludf.DUMMYFUNCTION("""COMPUTED_VALUE"""),46170.0) -> 46170 | C39: =IFERROR(__xludf.DUMMYFUNCTION("""COMPUTED_VALUE"""),"5c07fef4") -> 5c07fef4 | D39: =IFERROR(__xludf.DUMMYFUNCTION("""COMPUTED_VALUE"""),"Tiffany Kim") -> Tiffany Kim | E39: =IFERROR(__xludf.DUMMYFUNCTION("""COMPUTED_VALUE"""),"REWARD") -> REWARD | F39: =IFERROR(__xludf.DUMMYFUNCTION("""COMPUTED_VALUE"""),10.0) -> 10 | G39: =IFERROR(__xludf.DUMMYFUNCTION("""COMPUTED_VALUE"""),30.0) -> 30 | H39: =IFERROR(__xludf.DUMMYFUNCTION("""COMPUTED_VALUE"""),40.0) -> 40 | K39: =IFERROR(__xludf.DUMMYFUNCTION("""COMPUTED_VALUE"""),"On-time attendance reward") -> On-time attendance reward | L39: =IFERROR(__xludf.DUMMYFUNCTION("""COMPUTED_VALUE"""),"Success") -> Success
A40: =IFERROR(__xludf.DUMMYFUNCTION("""COMPUTED_VALUE"""),46170.35196759259) -> 46170.352 | B40: =IFERROR(__xludf.DUMMYFUNCTION("""COMPUTED_VALUE"""),46170.0) -> 46170 | C40: =IFERROR(__xludf.DUMMYFUNCTION("""COMPUTED_VALUE"""),"ba912211") -> ba912211 | D40: =IFERROR(__xludf.DUMMYFUNCTION("""COMPUTED_VALUE"""),"Daisy Dou") -> Daisy Dou | E40: =IFERROR(__xludf.DUMMYFUNCTION("""COMPUTED_VALUE"""),"REWARD") -> REWARD | F40: =IFERROR(__xludf.DUMMYFUNCTION("""COMPUTED_VALUE"""),10.0) -> 10 | G40: =IFERROR(__xludf.DUMMYFUNCTION("""COMPUTED_VALUE"""),101.0) -> 101 | H40: =IFERROR(__xludf.DUMMYFUNCTION("""COMPUTED_VALUE"""),111.0) -> 111 | K40: =IFERROR(__xludf.DUMMYFUNCTION("""COMPUTED_VALUE"""),"On-time attendance reward") -> On-time attendance reward | L40: =IFERROR(__xludf.DUMMYFUNCTION("""COMPUTED_VALUE"""),"Success") -> Success
A41: =IFERROR(__xludf.DUMMYFUNCTION("""COMPUTED_VALUE"""),46170.3521412037) -> 46170.352 | B41: =IFERROR(__xludf.DUMMYFUNCTION("""COMPUTED_VALUE"""),46170.0) -> 46170 | C41: =IFERROR(__xludf.DUMMYFUNCTION("""COMPUTED_VALUE"""),"7c4e261e") -> 7c4e261e | D41: =IFERROR(__xludf.DUMMYFUNCTION("""COMPUTED_VALUE"""),"Suha Lee") -> Suha Lee | E41: =IFERROR(__xludf.DUMMYFUNCTION("""COMPUTED_VALUE"""),"REWARD") -> REWARD | F41: =IFERROR(__xludf.DUMMYFUNCTION("""COMPUTED_VALUE"""),10.0) -> 10 | G41: =IFERROR(__xludf.DUMMYFUNCTION("""COMPUTED_VALUE"""),50.0) -> 50 | H41: =IFERROR(__xludf.DUMMYFUNCTION("""COMPUTED_VALUE"""),60.0) -> 60 | K41: =IFERROR(__xludf.DUMMYFUNCTION("""COMPUTED_VALUE"""),"On-time attendance reward") -> On-time attendance reward | L41: =IFERROR(__xludf.DUMMYFUNCTION("""COMPUTED_VALUE"""),"Success") -> Success
A42: =IFERROR(__xludf.DUMMYFUNCTION("""COMPUTED_VALUE"""),46170.35230324074) -> 46170.352 | B42: =IFERROR(__xludf.DUMMYFUNCTION("""COMPUTED_VALUE"""),46170.0) -> 46170 | C42: =IFERROR(__xludf.DUMMYFUNCTION("""COMPUTED_VALUE"""),"dc04eef4") -> dc04eef4 | D42: =IFERROR(__xludf.DUMMYFUNCTION("""COMPUTED_VALUE"""),"Joshua Jung") -> Joshua Jung | E42: =IFERROR(__xludf.DUMMYFUNCTION("""COMPUTED_VALUE"""),"REWARD") -> REWARD | F42: =IFERROR(__xludf.DUMMYFUNCTION("""COMPUTED_VALUE"""),10.0) -> 10 | G42: =IFERROR(__xludf.DUMMYFUNCTION("""COMPUTED_VALUE"""),50.0) -> 50 | H42: =IFERROR(__xludf.DUMMYFUNCTION("""COMPUTED_VALUE"""),60.0) -> 60 | K42: =IFERROR(__xludf.DUMMYFUNCTION("""COMPUTED_VALUE"""),"On-time attendance reward") -> On-time attendance reward | L42: =IFERROR(__xludf.DUMMYFUNCTION("""COMPUTED_VALUE"""),"Success") -> Success
A43: =IFERROR(__xludf.DUMMYFUNCTION("""COMPUTED_VALUE"""),46170.3540625) -> 46170.354 | B43: =IFERROR(__xludf.DUMMYFUNCTION("""COMPUTED_VALUE"""),46170.0) -> 46170 | C43: =IFERROR(__xludf.DUMMYFUNCTION("""COMPUTED_VALUE"""),"babde4c4") -> babde4c4 | D43: =IFERROR(__xludf.DUMMYFUNCTION("""COMPUTED_VALUE"""),"Ashley Guk") -> Ashley Guk | E43: =IFERROR(__xludf.DUMMYFUNCTION("""COMPUTED_VALUE"""),"REWARD") -> REWARD | F43: =IFERROR(__xludf.DUMMYFUNCTION("""COMPUTED_VALUE"""),10.0) -> 10 | G43: =IFERROR(__xludf.DUMMYFUNCTION("""COMPUTED_VALUE"""),56.0) -> 56 | H43: =IFERROR(__xludf.DUMMYFUNCTION("""COMPUTED_VALUE"""),66.0) -> 66 | K43: =IFERROR(__xludf.DUMMYFUNCTION("""COMPUTED_VALUE"""),"On-time attendance reward") -> On-time attendance reward | L43: =IFERROR(__xludf.DUMMYFUNCTION("""COMPUTED_VALUE"""),"Success") -> Success
A44: =IFERROR(__xludf.DUMMYFUNCTION("""COMPUTED_VALUE"""),46170.35631944444) -> 46170.356 | B44: =IFERROR(__xludf.DUMMYFUNCTION("""COMPUTED_VALUE"""),46170.0) -> 46170 | C44: =IFERROR(__xludf.DUMMYFUNCTION("""COMPUTED_VALUE"""),"ba353911") -> ba353911 | D44: =IFERROR(__xludf.DUMMYFUNCTION("""COMPUTED_VALUE"""),"Dayeon Kang") -> Dayeon Kang | E44: =IFERROR(__xludf.DUMMYFUNCTION("""COMPUTED_VALUE"""),"REWARD") -> REWARD | F44: =IFERROR(__xludf.DUMMYFUNCTION("""COMPUTED_VALUE"""),10.0) -> 10 | G44: =IFERROR(__xludf.DUMMYFUNCTION("""COMPUTED_VALUE"""),10.0) -> 10 | H44: =IFERROR(__xludf.DUMMYFUNCTION("""COMPUTED_VALUE"""),20.0) -> 20 | K44: =IFERROR(__xludf.DUMMYFUNCTION("""COMPUTED_VALUE"""),"On-time attendance reward") -> On-time attendance reward | L44: =IFERROR(__xludf.DUMMYFUNCTION("""COMPUTED_VALUE"""),"Success") -> Success
A45: =IFERROR(__xludf.DUMMYFUNCTION("""COMPUTED_VALUE"""),46170.357986111114) -> 46170.358 | B45: =IFERROR(__xludf.DUMMYFUNCTION("""COMPUTED_VALUE"""),46170.0) -> 46170 | C45: =IFERROR(__xludf.DUMMYFUNCTION("""COMPUTED_VALUE"""),"9a5f2811") -> 9a5f2811 | D45: =IFERROR(__xludf.DUMMYFUNCTION("""COMPUTED_VALUE"""),"Junyoung Yoo") -> Junyoung Yoo | E45: =IFERROR(__xludf.DUMMYFUNCTION("""COMPUTED_VALUE"""),"REWARD") -> REWARD | F45: =IFERROR(__xludf.DUMMYFUNCTION("""COMPUTED_VALUE"""),10.0) -> 10 | G45: =IFERROR(__xludf.DUMMYFUNCTION("""COMPUTED_VALUE"""),40.0) -> 40 | H45: =IFERROR(__xludf.DUMMYFUNCTION("""COMPUTED_VALUE"""),50.0) -> 50 | K45: =IFERROR(__xludf.DUMMYFUNCTION("""COMPUTED_VALUE"""),"On-time attendance reward") -> On-time attendance reward | L45: =IFERROR(__xludf.DUMMYFUNCTION("""COMPUTED_VALUE"""),"Success") -> Success
A46: =IFERROR(__xludf.DUMMYFUNCTION("""COMPUTED_VALUE"""),46170.37253472222) -> 46170.373 | B46: =IFERROR(__xludf.DUMMYFUNCTION("""COMPUTED_VALUE"""),46170.0) -> 46170 | C46: =IFERROR(__xludf.DUMMYFUNCTION("""COMPUTED_VALUE"""),"1e3e1410") -> 1e3e1410 | D46: =IFERROR(__xludf.DUMMYFUNCTION("""COMPUTED_VALUE"""),"Junjae Park") -> Junjae Park | E46: =IFERROR(__xludf.DUMMYFUNCTION("""COMPUTED_VALUE"""),"FINE") -> FINE | F46: =IFERROR(__xludf.DUMMYFUNCTION("""COMPUTED_VALUE"""),10.0) -> 10 | G46: =IFERROR(__xludf.DUMMYFUNCTION("""COMPUTED_VALUE"""),20.0) -> 20 | H46: =IFERROR(__xludf.DUMMYFUNCTION("""COMPUTED_VALUE"""),10.0) -> 10 | K46: =IFERROR(__xludf.DUMMYFUNCTION("""COMPUTED_VALUE"""),"Late attendance penalty") -> Late attendance penalty | L46: =IFERROR(__xludf.DUMMYFUNCTION("""COMPUTED_VALUE"""),"Success") -> Success
A47: =IFERROR(__xludf.DUMMYFUNCTION("""COMPUTED_VALUE"""),46170.37268518518) -> 46170.373 | B47: =IFERROR(__xludf.DUMMYFUNCTION("""COMPUTED_VALUE"""),46170.0) -> 46170 | C47: =IFERROR(__xludf.DUMMYFUNCTION("""COMPUTED_VALUE"""),"ba0fc5c4") -> ba0fc5c4 | D47: =IFERROR(__xludf.DUMMYFUNCTION("""COMPUTED_VALUE"""),"Junwoo Kang") -> Junwoo Kang | E47: =IFERROR(__xludf.DUMMYFUNCTION("""COMPUTED_VALUE"""),"FINE") -> FINE | F47: =IFERROR(__xludf.DUMMYFUNCTION("""COMPUTED_VALUE"""),10.0) -> 10 | G47: =IFERROR(__xludf.DUMMYFUNCTION("""COMPUTED_VALUE"""),0.0) -> 0 | H47: =IFERROR(__xludf.DUMMYFUNCTION("""COMPUTED_VALUE"""),0.0) -> 0 | K47: =IFERROR(__xludf.DUMMYFUNCTION("""COMPUTED_VALUE"""),"Late attendance penalty") -> Late attendance penalty | L47: =IFERROR(__xludf.DUMMYFUNCTION("""COMPUTED_VALUE"""),"Denied - insufficient balance") -> Denied - insufficient balance
A48: =IFERROR(__xludf.DUMMYFUNCTION("""COMPUTED_VALUE"""),46174.347962962966) -> 46174.348 | B48: =IFERROR(__xludf.DUMMYFUNCTION("""COMPUTED_VALUE"""),46174.0) -> 46174 | C48: =IFERROR(__xludf.DUMMYFUNCTION("""COMPUTED_VALUE"""),"ae072910") -> ae072910 | D48: =IFERROR(__xludf.DUMMYFUNCTION("""COMPUTED_VALUE"""),"Selena Jung") -> Selena Jung | E48: =IFERROR(__xludf.DUMMYFUNCTION("""COMPUTED_VALUE"""),"REWARD") -> REWARD | F48: =IFERROR(__xludf.DUMMYFUNCTION("""COMPUTED_VALUE"""),10.0) -> 10 | G48: =IFERROR(__xludf.DUMMYFUNCTION("""COMPUTED_VALUE"""),10.0) -> 10 | H48: =IFERROR(__xludf.DUMMYFUNCTION("""COMPUTED_VALUE"""),20.0) -> 20 | K48: =IFERROR(__xludf.DUMMYFUNCTION("""COMPUTED_VALUE"""),"On-time attendance reward") -> On-time attendance reward | L48: =IFERROR(__xludf.DUMMYFUNCTION("""COMPUTED_VALUE"""),"Success") -> Success
A49: =IFERROR(__xludf.DUMMYFUNCTION("""COMPUTED_VALUE"""),46174.34818287037) -> 46174.348 | B49: =IFERROR(__xludf.DUMMYFUNCTION("""COMPUTED_VALUE"""),46174.0) -> 46174 | C49: =IFERROR(__xludf.DUMMYFUNCTION("""COMPUTED_VALUE"""),"5c07fef4") -> 5c07fef4 | D49: =IFERROR(__xludf.DUMMYFUNCTION("""COMPUTED_VALUE"""),"Tiffany Kim") -> Tiffany Kim | E49: =IFERROR(__xludf.DUMMYFUNCTION("""COMPUTED_VALUE"""),"REWARD") -> REWARD | F49: =IFERROR(__xludf.DUMMYFUNCTION("""COMPUTED_VALUE"""),10.0) -> 10 | G49: =IFERROR(__xludf.DUMMYFUNCTION("""COMPUTED_VALUE"""),40.0) -> 40 | H49: =IFERROR(__xludf.DUMMYFUNCTION("""COMPUTED_VALUE"""),50.0) -> 50 | K49: =IFERROR(__xludf.DUMMYFUNCTION("""COMPUTED_VALUE"""),"On-time attendance reward") -> On-time attendance reward | L49: =IFERROR(__xludf.DUMMYFUNCTION("""COMPUTED_VALUE"""),"Success") -> Success
A50: =IFERROR(__xludf.DUMMYFUNCTION("""COMPUTED_VALUE"""),46174.348344907405) -> 46174.348 | B50: =IFERROR(__xludf.DUMMYFUNCTION("""COMPUTED_VALUE"""),46174.0) -> 46174 | C50: =IFERROR(__xludf.DUMMYFUNCTION("""COMPUTED_VALUE"""),"dc04eef4") -> dc04eef4 | D50: =IFERROR(__xludf.DUMMYFUNCTION("""COMPUTED_VALUE"""),"Joshua Jung") -> Joshua Jung | E50: =IFERROR(__xludf.DUMMYFUNCTION("""COMPUTED_VALUE"""),"REWARD") -> REWARD | F50: =IFERROR(__xludf.DUMMYFUNCTION("""COMPUTED_VALUE"""),10.0) -> 10 | G50: =IFERROR(__xludf.DUMMYFUNCTION("""COMPUTED_VALUE"""),60.0) -> 60 | H50: =IFERROR(__xludf.DUMMYFUNCTION("""COMPUTED_VALUE"""),70.0) -> 70 | K50: =IFERROR(__xludf.DUMMYFUNCTION("""COMPUTED_VALUE"""),"On-time attendance reward") -> On-time attendance reward | L50: =IFERROR(__xludf.DUMMYFUNCTION("""COMPUTED_VALUE"""),"Success") -> Success
A51: =IFERROR(__xludf.DUMMYFUNCTION("""COMPUTED_VALUE"""),46174.34916666667) -> 46174.349 | B51: =IFERROR(__xludf.DUMMYFUNCTION("""COMPUTED_VALUE"""),46174.0) -> 46174 | C51: =IFERROR(__xludf.DUMMYFUNCTION("""COMPUTED_VALUE"""),"ba912211") -> ba912211 | D51: =IFERROR(__xludf.DUMMYFUNCTION("""COMPUTED_VALUE"""),"Daisy Dou") -> Daisy Dou | E51: =IFERROR(__xludf.DUMMYFUNCTION("""COMPUTED_VALUE"""),"REWARD") -> REWARD | F51: =IFERROR(__xludf.DUMMYFUNCTION("""COMPUTED_VALUE"""),10.0) -> 10 | G51: =IFERROR(__xludf.DUMMYFUNCTION("""COMPUTED_VALUE"""),111.0) -> 111 | H51: =IFERROR(__xludf.DUMMYFUNCTION("""COMPUTED_VALUE"""),121.0) -> 121 | K51: =IFERROR(__xludf.DUMMYFUNCTION("""COMPUTED_VALUE"""),"On-time attendance reward") -> On-time attendance reward | L51: =IFERROR(__xludf.DUMMYFUNCTION("""COMPUTED_VALUE"""),"Success") -> Success
A52: =IFERROR(__xludf.DUMMYFUNCTION("""COMPUTED_VALUE"""),46174.35314814815) -> 46174.353 | B52: =IFERROR(__xludf.DUMMYFUNCTION("""COMPUTED_VALUE"""),46174.0) -> 46174 | C52: =IFERROR(__xludf.DUMMYFUNCTION("""COMPUTED_VALUE"""),"babde4c4") -> babde4c4 | D52: =IFERROR(__xludf.DUMMYFUNCTION("""COMPUTED_VALUE"""),"Ashley Guk") -> Ashley Guk | E52: =IFERROR(__xludf.DUMMYFUNCTION("""COMPUTED_VALUE"""),"REWARD") -> REWARD | F52: =IFERROR(__xludf.DUMMYFUNCTION("""COMPUTED_VALUE"""),10.0) -> 10 | G52: =IFERROR(__xludf.DUMMYFUNCTION("""COMPUTED_VALUE"""),66.0) -> 66 | H52: =IFERROR(__xludf.DUMMYFUNCTION("""COMPUTED_VALUE"""),76.0) -> 76 | K52: =IFERROR(__xludf.DUMMYFUNCTION("""COMPUTED_VALUE"""),"On-time attendance reward") -> On-time attendance reward | L52: =IFERROR(__xludf.DUMMYFUNCTION("""COMPUTED_VALUE"""),"Success") -> Success
A53: =IFERROR(__xludf.DUMMYFUNCTION("""COMPUTED_VALUE"""),46174.35422453703) -> 46174.354 | B53: =IFERROR(__xludf.DUMMYFUNCTION("""COMPUTED_VALUE"""),46174.0) -> 46174 | C53: =IFERROR(__xludf.DUMMYFUNCTION("""COMPUTED_VALUE"""),"ba353911") -> ba353911 | D53: =IFERROR(__xludf.DUMMYFUNCTION("""COMPUTED_VALUE"""),"Dayeon Kang") -> Dayeon Kang | E53: =IFERROR(__xludf.DUMMYFUNCTION("""COMPUTED_VALUE"""),"REWARD") -> REWARD | F53: =IFERROR(__xludf.DUMMYFUNCTION("""COMPUTED_VALUE"""),10.0) -> 10 | G53: =IFERROR(__xludf.DUMMYFUNCTION("""COMPUTED_VALUE"""),20.0) -> 20 | H53: =IFERROR(__xludf.DUMMYFUNCTION("""COMPUTED_VALUE"""),30.0) -> 30 | K53: =IFERROR(__xludf.DUMMYFUNCTION("""COMPUTED_VALUE"""),"On-time attendance reward") -> On-time attendance reward | L53: =IFERROR(__xludf.DUMMYFUNCTION("""COMPUTED_VALUE"""),"Success") -> Success
A54: =IFERROR(__xludf.DUMMYFUNCTION("""COMPUTED_VALUE"""),46174.35525462963) -> 46174.355 | B54: =IFERROR(__xludf.DUMMYFUNCTION("""COMPUTED_VALUE"""),46174.0) -> 46174 | C54: =IFERROR(__xludf.DUMMYFUNCTION("""COMPUTED_VALUE"""),"7c4e261e") -> 7c4e261e | D54: =IFERROR(__xludf.DUMMYFUNCTION("""COMPUTED_VALUE"""),"Suha Lee") -> Suha Lee | E54: =IFERROR(__xludf.DUMMYFUNCTION("""COMPUTED_VALUE"""),"REWARD") -> REWARD | F54: =IFERROR(__xludf.DUMMYFUNCTION("""COMPUTED_VALUE"""),10.0) -> 10 | G54: =IFERROR(__xludf.DUMMYFUNCTION("""COMPUTED_VALUE"""),60.0) -> 60 | H54: =IFERROR(__xludf.DUMMYFUNCTION("""COMPUTED_VALUE"""),70.0) -> 70 | K54: =IFERROR(__xludf.DUMMYFUNCTION("""COMPUTED_VALUE"""),"On-time attendance reward") -> On-time attendance reward | L54: =IFERROR(__xludf.DUMMYFUNCTION("""COMPUTED_VALUE"""),"Success") -> Success
A55: =IFERROR(__xludf.DUMMYFUNCTION("""COMPUTED_VALUE"""),46174.365694444445) -> 46174.366 | B55: =IFERROR(__xludf.DUMMYFUNCTION("""COMPUTED_VALUE"""),46174.0) -> 46174 | C55: =IFERROR(__xludf.DUMMYFUNCTION("""COMPUTED_VALUE"""),"5a032611") -> 5a032611 | D55: =IFERROR(__xludf.DUMMYFUNCTION("""COMPUTED_VALUE"""),"Harold Dou") -> Harold Dou | E55: =IFERROR(__xludf.DUMMYFUNCTION("""COMPUTED_VALUE"""),"FINE") -> FINE | F55: =IFERROR(__xludf.DUMMYFUNCTION("""COMPUTED_VALUE"""),10.0) -> 10 | G55: =IFERROR(__xludf.DUMMYFUNCTION("""COMPUTED_VALUE"""),50.0) -> 50 | H55: =IFERROR(__xludf.DUMMYFUNCTION("""COMPUTED_VALUE"""),40.0) -> 40 | K55: =IFERROR(__xludf.DUMMYFUNCTION("""COMPUTED_VALUE"""),"Late attendance penalty") -> Late attendance penalty | L55: =IFERROR(__xludf.DUMMYFUNCTION("""COMPUTED_VALUE"""),"Success") -> Success
A56: =IFERROR(__xludf.DUMMYFUNCTION("""COMPUTED_VALUE"""),46174.36770833333) -> 46174.368 | B56: =IFERROR(__xludf.DUMMYFUNCTION("""COMPUTED_VALUE"""),46174.0) -> 46174 | C56: =IFERROR(__xludf.DUMMYFUNCTION("""COMPUTED_VALUE"""),"9a5f2811") -> 9a5f2811 | D56: =IFERROR(__xludf.DUMMYFUNCTION("""COMPUTED_VALUE"""),"Junyoung Yoo") -> Junyoung Yoo | E56: =IFERROR(__xludf.DUMMYFUNCTION("""COMPUTED_VALUE"""),"FINE") -> FINE | F56: =IFERROR(__xludf.DUMMYFUNCTION("""COMPUTED_VALUE"""),10.0) -> 10 | G56: =IFERROR(__xludf.DUMMYFUNCTION("""COMPUTED_VALUE"""),50.0) -> 50 | H56: =IFERROR(__xludf.DUMMYFUNCTION("""COMPUTED_VALUE"""),40.0) -> 40 | K56: =IFERROR(__xludf.DUMMYFUNCTION("""COMPUTED_VALUE"""),"Late attendance penalty") -> Late attendance penalty | L56: =IFERROR(__xludf.DUMMYFUNCTION("""COMPUTED_VALUE"""),"Success") -> Success
A57: =IFERROR(__xludf.DUMMYFUNCTION("""COMPUTED_VALUE"""),46174.36913194445) -> 46174.369 | B57: =IFERROR(__xludf.DUMMYFUNCTION("""COMPUTED_VALUE"""),46174.0) -> 46174 | C57: =IFERROR(__xludf.DUMMYFUNCTION("""COMPUTED_VALUE"""),"ba0fc5c4") -> ba0fc5c4 | D57: =IFERROR(__xludf.DUMMYFUNCTION("""COMPUTED_VALUE"""),"Junwoo Kang") -> Junwoo Kang | E57: =IFERROR(__xludf.DUMMYFUNCTION("""COMPUTED_VALUE"""),"FINE") -> FINE | F57: =IFERROR(__xludf.DUMMYFUNCTION("""COMPUTED_VALUE"""),10.0) -> 10 | G57: =IFERROR(__xludf.DUMMYFUNCTION("""COMPUTED_VALUE"""),0.0) -> 0 | H57: =IFERROR(__xludf.DUMMYFUNCTION("""COMPUTED_VALUE"""),0.0) -> 0 | K57: =IFERROR(__xludf.DUMMYFUNCTION("""COMPUTED_VALUE"""),"Late attendance penalty") -> Late attendance penalty | L57: =IFERROR(__xludf.DUMMYFUNCTION("""COMPUTED_VALUE"""),"Denied - insufficient balance") -> Denied - insufficient balance
A58: =IFERROR(__xludf.DUMMYFUNCTION("""COMPUTED_VALUE"""),46174.375613425924) -> 46174.376 | B58: =IFERROR(__xludf.DUMMYFUNCTION("""COMPUTED_VALUE"""),46174.0) -> 46174 | C58: =IFERROR(__xludf.DUMMYFUNCTION("""COMPUTED_VALUE"""),"1e3e1410") -> 1e3e1410 | D58: =IFERROR(__xludf.DUMMYFUNCTION("""COMPUTED_VALUE"""),"Junjae Park") -> Junjae Park | E58: =IFERROR(__xludf.DUMMYFUNCTION("""COMPUTED_VALUE"""),"FINE") -> FINE | F58: =IFERROR(__xludf.DUMMYFUNCTION("""COMPUTED_VALUE"""),10.0) -> 10 | G58: =IFERROR(__xludf.DUMMYFUNCTION("""COMPUTED_VALUE"""),10.0) -> 10 | H58: =IFERROR(__xludf.DUMMYFUNCTION("""COMPUTED_VALUE"""),0.0) -> 0 | K58: =IFERROR(__xludf.DUMMYFUNCTION("""COMPUTED_VALUE"""),"Late attendance penalty") -> Late attendance penalty | L58: =IFERROR(__xludf.DUMMYFUNCTION("""COMPUTED_VALUE"""),"Success") -> Success
A59: =IFERROR(__xludf.DUMMYFUNCTION("""COMPUTED_VALUE"""),46175.34792824074) -> 46175.348 | B59: =IFERROR(__xludf.DUMMYFUNCTION("""COMPUTED_VALUE"""),46175.0) -> 46175 | C59: =IFERROR(__xludf.DUMMYFUNCTION("""COMPUTED_VALUE"""),"5c07fef4") -> 5c07fef4 | D59: =IFERROR(__xludf.DUMMYFUNCTION("""COMPUTED_VALUE"""),"Tiffany Kim") -> Tiffany Kim | E59: =IFERROR(__xludf.DUMMYFUNCTION("""COMPUTED_VALUE"""),"REWARD") -> REWARD | F59: =IFERROR(__xludf.DUMMYFUNCTION("""COMPUTED_VALUE"""),10.0) -> 10 | G59: =IFERROR(__xludf.DUMMYFUNCTION("""COMPUTED_VALUE"""),50.0) -> 50 | H59: =IFERROR(__xludf.DUMMYFUNCTION("""COMPUTED_VALUE"""),60.0) -> 60 | K59: =IFERROR(__xludf.DUMMYFUNCTION("""COMPUTED_VALUE"""),"On-time attendance reward") -> On-time attendance reward | L59: =IFERROR(__xludf.DUMMYFUNCTION("""COMPUTED_VALUE"""),"Success") -> Success
A60: =IFERROR(__xludf.DUMMYFUNCTION("""COMPUTED_VALUE"""),46175.34988425926) -> 46175.35 | B60: =IFERROR(__xludf.DUMMYFUNCTION("""COMPUTED_VALUE"""),46175.0) -> 46175 | C60: =IFERROR(__xludf.DUMMYFUNCTION("""COMPUTED_VALUE"""),"ae072910") -> ae072910 | D60: =IFERROR(__xludf.DUMMYFUNCTION("""COMPUTED_VALUE"""),"Selena Jung") -> Selena Jung | E60: =IFERROR(__xludf.DUMMYFUNCTION("""COMPUTED_VALUE"""),"REWARD") -> REWARD | F60: =IFERROR(__xludf.DUMMYFUNCTION("""COMPUTED_VALUE"""),10.0) -> 10 | G60: =IFERROR(__xludf.DUMMYFUNCTION("""COMPUTED_VALUE"""),20.0) -> 20 | H60: =IFERROR(__xludf.DUMMYFUNCTION("""COMPUTED_VALUE"""),30.0) -> 30 | K60: =IFERROR(__xludf.DUMMYFUNCTION("""COMPUTED_VALUE"""),"On-time attendance reward") -> On-time attendance reward | L60: =IFERROR(__xludf.DUMMYFUNCTION("""COMPUTED_VALUE"""),"Success") -> Success
A61: =IFERROR(__xludf.DUMMYFUNCTION("""COMPUTED_VALUE"""),46175.35037037037) -> 46175.35 | B61: =IFERROR(__xludf.DUMMYFUNCTION("""COMPUTED_VALUE"""),46175.0) -> 46175 | C61: =IFERROR(__xludf.DUMMYFUNCTION("""COMPUTED_VALUE"""),"dc04eef4") -> dc04eef4 | D61: =IFERROR(__xludf.DUMMYFUNCTION("""COMPUTED_VALUE"""),"Joshua Jung") -> Joshua Jung | E61: =IFERROR(__xludf.DUMMYFUNCTION("""COMPUTED_VALUE"""),"REWARD") -> REWARD | F61: =IFERROR(__xludf.DUMMYFUNCTION("""COMPUTED_VALUE"""),10.0) -> 10 | G61: =IFERROR(__xludf.DUMMYFUNCTION("""COMPUTED_VALUE"""),70.0) -> 70 | H61: =IFERROR(__xludf.DUMMYFUNCTION("""COMPUTED_VALUE"""),80.0) -> 80 | K61: =IFERROR(__xludf.DUMMYFUNCTION("""COMPUTED_VALUE"""),"On-time attendance reward") -> On-time attendance reward | L61: =IFERROR(__xludf.DUMMYFUNCTION("""COMPUTED_VALUE"""),"Success") -> Success
A62: =IFERROR(__xludf.DUMMYFUNCTION("""COMPUTED_VALUE"""),46175.351273148146) -> 46175.351 | B62: =IFERROR(__xludf.DUMMYFUNCTION("""COMPUTED_VALUE"""),46175.0) -> 46175 | C62: =IFERROR(__xludf.DUMMYFUNCTION("""COMPUTED_VALUE"""),"ba912211") -> ba912211 | D62: =IFERROR(__xludf.DUMMYFUNCTION("""COMPUTED_VALUE"""),"Daisy Dou") -> Daisy Dou | E62: =IFERROR(__xludf.DUMMYFUNCTION("""COMPUTED_VALUE"""),"REWARD") -> REWARD | F62: =IFERROR(__xludf.DUMMYFUNCTION("""COMPUTED_VALUE"""),10.0) -> 10 | G62: =IFERROR(__xludf.DUMMYFUNCTION("""COMPUTED_VALUE"""),121.0) -> 121 | H62: =IFERROR(__xludf.DUMMYFUNCTION("""COMPUTED_VALUE"""),131.0) -> 131 | K62: =IFERROR(__xludf.DUMMYFUNCTION("""COMPUTED_VALUE"""),"On-time attendance reward") -> On-time attendance reward | L62: =IFERROR(__xludf.DUMMYFUNCTION("""COMPUTED_VALUE"""),"Success") -> Success
A63: =IFERROR(__xludf.DUMMYFUNCTION("""COMPUTED_VALUE"""),46175.35251157408) -> 46175.353 | B63: =IFERROR(__xludf.DUMMYFUNCTION("""COMPUTED_VALUE"""),46175.0) -> 46175 | C63: =IFERROR(__xludf.DUMMYFUNCTION("""COMPUTED_VALUE"""),"babde4c4") -> babde4c4 | D63: =IFERROR(__xludf.DUMMYFUNCTION("""COMPUTED_VALUE"""),"Ashley Guk") -> Ashley Guk | E63: =IFERROR(__xludf.DUMMYFUNCTION("""COMPUTED_VALUE"""),"REWARD") -> REWARD | F63: =IFERROR(__xludf.DUMMYFUNCTION("""COMPUTED_VALUE"""),10.0) -> 10 | G63: =IFERROR(__xludf.DUMMYFUNCTION("""COMPUTED_VALUE"""),76.0) -> 76 | H63: =IFERROR(__xludf.DUMMYFUNCTION("""COMPUTED_VALUE"""),86.0) -> 86 | K63: =IFERROR(__xludf.DUMMYFUNCTION("""COMPUTED_VALUE"""),"On-time attendance reward") -> On-time attendance reward | L63: =IFERROR(__xludf.DUMMYFUNCTION("""COMPUTED_VALUE"""),"Success") -> Success
A64: =IFERROR(__xludf.DUMMYFUNCTION("""COMPUTED_VALUE"""),46175.355833333335) -> 46175.356 | B64: =IFERROR(__xludf.DUMMYFUNCTION("""COMPUTED_VALUE"""),46175.0) -> 46175 | C64: =IFERROR(__xludf.DUMMYFUNCTION("""COMPUTED_VALUE"""),"9a5f2811") -> 9a5f2811 | D64: =IFERROR(__xludf.DUMMYFUNCTION("""COMPUTED_VALUE"""),"Junyoung Yoo") -> Junyoung Yoo | E64: =IFERROR(__xludf.DUMMYFUNCTION("""COMPUTED_VALUE"""),"REWARD") -> REWARD | F64: =IFERROR(__xludf.DUMMYFUNCTION("""COMPUTED_VALUE"""),10.0) -> 10 | G64: =IFERROR(__xludf.DUMMYFUNCTION("""COMPUTED_VALUE"""),40.0) -> 40 | H64: =IFERROR(__xludf.DUMMYFUNCTION("""COMPUTED_VALUE"""),50.0) -> 50 | K64: =IFERROR(__xludf.DUMMYFUNCTION("""COMPUTED_VALUE"""),"On-time attendance reward") -> On-time attendance reward | L64: =IFERROR(__xludf.DUMMYFUNCTION("""COMPUTED_VALUE"""),"Success") -> Success
A65: =IFERROR(__xludf.DUMMYFUNCTION("""COMPUTED_VALUE"""),46175.3559837963) -> 46175.356 | B65: =IFERROR(__xludf.DUMMYFUNCTION("""COMPUTED_VALUE"""),46175.0) -> 46175 | C65: =IFERROR(__xludf.DUMMYFUNCTION("""COMPUTED_VALUE"""),"1e3e1410") -> 1e3e1410 | D65: =IFERROR(__xludf.DUMMYFUNCTION("""COMPUTED_VALUE"""),"Junjae Park") -> Junjae Park | E65: =IFERROR(__xludf.DUMMYFUNCTION("""COMPUTED_VALUE"""),"REWARD") -> REWARD | F65: =IFERROR(__xludf.DUMMYFUNCTION("""COMPUTED_VALUE"""),10.0) -> 10 | G65: =IFERROR(__xludf.DUMMYFUNCTION("""COMPUTED_VALUE"""),0.0) -> 0 | H65: =IFERROR(__xludf.DUMMYFUNCTION("""COMPUTED_VALUE"""),10.0) -> 10 | K65: =IFERROR(__xludf.DUMMYFUNCTION("""COMPUTED_VALUE"""),"On-time attendance reward") -> On-time attendance reward | L65: =IFERROR(__xludf.DUMMYFUNCTION("""COMPUTED_VALUE"""),"Success") -> Success
A66: =IFERROR(__xludf.DUMMYFUNCTION("""COMPUTED_VALUE"""),46175.35627314815) -> 46175.356 | B66: =IFERROR(__xludf.DUMMYFUNCTION("""COMPUTED_VALUE"""),46175.0) -> 46175 | C66: =IFERROR(__xludf.DUMMYFUNCTION("""COMPUTED_VALUE"""),"ba353911") -> ba353911 | D66: =IFERROR(__xludf.DUMMYFUNCTION("""COMPUTED_VALUE"""),"Dayeon Kang") -> Dayeon Kang | E66: =IFERROR(__xludf.DUMMYFUNCTION("""COMPUTED_VALUE"""),"REWARD") -> REWARD | F66: =IFERROR(__xludf.DUMMYFUNCTION("""COMPUTED_VALUE"""),10.0) -> 10 | G66: =IFERROR(__xludf.DUMMYFUNCTION("""COMPUTED_VALUE"""),30.0) -> 30 | H66: =IFERROR(__xludf.DUMMYFUNCTION("""COMPUTED_VALUE"""),40.0) -> 40 | K66: =IFERROR(__xludf.DUMMYFUNCTION("""COMPUTED_VALUE"""),"On-time attendance reward") -> On-time attendance reward | L66: =IFERROR(__xludf.DUMMYFUNCTION("""COMPUTED_VALUE"""),"Success") -> Success
A67: =IFERROR(__xludf.DUMMYFUNCTION("""COMPUTED_VALUE"""),46175.357569444444) -> 46175.358 | B67: =IFERROR(__xludf.DUMMYFUNCTION("""COMPUTED_VALUE"""),46175.0) -> 46175 | C67: =IFERROR(__xludf.DUMMYFUNCTION("""COMPUTED_VALUE"""),"5a032611") -> 5a032611 | D67: =IFERROR(__xludf.DUMMYFUNCTION("""COMPUTED_VALUE"""),"Harold Dou") -> Harold Dou | E67: =IFERROR(__xludf.DUMMYFUNCTION("""COMPUTED_VALUE"""),"REWARD") -> REWARD | F67: =IFERROR(__xludf.DUMMYFUNCTION("""COMPUTED_VALUE"""),10.0) -> 10 | G67: =IFERROR(__xludf.DUMMYFUNCTION("""COMPUTED_VALUE"""),40.0) -> 40 | H67: =IFERROR(__xludf.DUMMYFUNCTION("""COMPUTED_VALUE"""),50.0) -> 50 | K67: =IFERROR(__xludf.DUMMYFUNCTION("""COMPUTED_VALUE"""),"On-time attendance reward") -> On-time attendance reward | L67: =IFERROR(__xludf.DUMMYFUNCTION("""COMPUTED_VALUE"""),"Success") -> Success
A68: =IFERROR(__xludf.DUMMYFUNCTION("""COMPUTED_VALUE"""),46175.357719907406) -> 46175.358 | B68: =IFERROR(__xludf.DUMMYFUNCTION("""COMPUTED_VALUE"""),46175.0) -> 46175 | C68: =IFERROR(__xludf.DUMMYFUNCTION("""COMPUTED_VALUE"""),"7c4e261e") -> 7c4e261e | D68: =IFERROR(__xludf.DUMMYFUNCTION("""COMPUTED_VALUE"""),"Suha Lee") -> Suha Lee | E68: =IFERROR(__xludf.DUMMYFUNCTION("""COMPUTED_VALUE"""),"REWARD") -> REWARD | F68: =IFERROR(__xludf.DUMMYFUNCTION("""COMPUTED_VALUE"""),10.0) -> 10 | G68: =IFERROR(__xludf.DUMMYFUNCTION("""COMPUTED_VALUE"""),70.0) -> 70 | H68: =IFERROR(__xludf.DUMMYFUNCTION("""COMPUTED_VALUE"""),80.0) -> 80 | K68: =IFERROR(__xludf.DUMMYFUNCTION("""COMPUTED_VALUE"""),"On-time attendance reward") -> On-time attendance reward | L68: =IFERROR(__xludf.DUMMYFUNCTION("""COMPUTED_VALUE"""),"Success") -> Success
A69: =IFERROR(__xludf.DUMMYFUNCTION("""COMPUTED_VALUE"""),46175.37443287037) -> 46175.374 | B69: =IFERROR(__xludf.DUMMYFUNCTION("""COMPUTED_VALUE"""),46175.0) -> 46175 | C69: =IFERROR(__xludf.DUMMYFUNCTION("""COMPUTED_VALUE"""),"ba0fc5c4") -> ba0fc5c4 | D69: =IFERROR(__xludf.DUMMYFUNCTION("""COMPUTED_VALUE"""),"Junwoo Kang") -> Junwoo Kang | E69: =IFERROR(__xludf.DUMMYFUNCTION("""COMPUTED_VALUE"""),"FINE") -> FINE | F69: =IFERROR(__xludf.DUMMYFUNCTION("""COMPUTED_VALUE"""),10.0) -> 10 | G69: =IFERROR(__xludf.DUMMYFUNCTION("""COMPUTED_VALUE"""),0.0) -> 0 | H69: =IFERROR(__xludf.DUMMYFUNCTION("""COMPUTED_VALUE"""),0.0) -> 0 | K69: =IFERROR(__xludf.DUMMYFUNCTION("""COMPUTED_VALUE"""),"Late attendance penalty") -> Late attendance penalty | L69: =IFERROR(__xludf.DUMMYFUNCTION("""COMPUTED_VALUE"""),"Denied - insufficient balance") -> Denied - insufficient balance
A70: =IFERROR(__xludf.DUMMYFUNCTION("""COMPUTED_VALUE"""),46177.34890046297) -> 46177.349 | B70: =IFERROR(__xludf.DUMMYFUNCTION("""COMPUTED_VALUE"""),46177.0) -> 46177 | C70: =IFERROR(__xludf.DUMMYFUNCTION("""COMPUTED_VALUE"""),"babde4c4") -> babde4c4 | D70: =IFERROR(__xludf.DUMMYFUNCTION("""COMPUTED_VALUE"""),"Ashley Guk") -> Ashley Guk | E70: =IFERROR(__xludf.DUMMYFUNCTION("""COMPUTED_VALUE"""),"REWARD") -> REWARD | F70: =IFERROR(__xludf.DUMMYFUNCTION("""COMPUTED_VALUE"""),10.0) -> 10 | G70: =IFERROR(__xludf.DUMMYFUNCTION("""COMPUTED_VALUE"""),86.0) -> 86 | H70: =IFERROR(__xludf.DUMMYFUNCTION("""COMPUTED_VALUE"""),96.0) -> 96 | K70: =IFERROR(__xludf.DUMMYFUNCTION("""COMPUTED_VALUE"""),"On-time attendance reward") -> On-time attendance reward | L70: =IFERROR(__xludf.DUMMYFUNCTION("""COMPUTED_VALUE"""),"Success") -> Success
A71: =IFERROR(__xludf.DUMMYFUNCTION("""COMPUTED_VALUE"""),46177.3490625) -> 46177.349 | B71: =IFERROR(__xludf.DUMMYFUNCTION("""COMPUTED_VALUE"""),46177.0) -> 46177 | C71: =IFERROR(__xludf.DUMMYFUNCTION("""COMPUTED_VALUE"""),"ae072910") -> ae072910 | D71: =IFERROR(__xludf.DUMMYFUNCTION("""COMPUTED_VALUE"""),"Selena Jung") -> Selena Jung | E71: =IFERROR(__xludf.DUMMYFUNCTION("""COMPUTED_VALUE"""),"REWARD") -> REWARD | F71: =IFERROR(__xludf.DUMMYFUNCTION("""COMPUTED_VALUE"""),10.0) -> 10 | G71: =IFERROR(__xludf.DUMMYFUNCTION("""COMPUTED_VALUE"""),30.0) -> 30 | H71: =IFERROR(__xludf.DUMMYFUNCTION("""COMPUTED_VALUE"""),40.0) -> 40 | K71: =IFERROR(__xludf.DUMMYFUNCTION("""COMPUTED_VALUE"""),"On-time attendance reward") -> On-time attendance reward | L71: =IFERROR(__xludf.DUMMYFUNCTION("""COMPUTED_VALUE"""),"Success") -> Success
A72: =IFERROR(__xludf.DUMMYFUNCTION("""COMPUTED_VALUE"""),46177.349699074075) -> 46177.35 | B72: =IFERROR(__xludf.DUMMYFUNCTION("""COMPUTED_VALUE"""),46177.0) -> 46177 | C72: =IFERROR(__xludf.DUMMYFUNCTION("""COMPUTED_VALUE"""),"dc04eef4") -> dc04eef4 | D72: =IFERROR(__xludf.DUMMYFUNCTION("""COMPUTED_VALUE"""),"Joshua Jung") -> Joshua Jung | E72: =IFERROR(__xludf.DUMMYFUNCTION("""COMPUTED_VALUE"""),"REWARD") -> REWARD | F72: =IFERROR(__xludf.DUMMYFUNCTION("""COMPUTED_VALUE"""),10.0) -> 10 | G72: =IFERROR(__xludf.DUMMYFUNCTION("""COMPUTED_VALUE"""),80.0) -> 80 | H72: =IFERROR(__xludf.DUMMYFUNCTION("""COMPUTED_VALUE"""),90.0) -> 90 | K72: =IFERROR(__xludf.DUMMYFUNCTION("""COMPUTED_VALUE"""),"On-time attendance reward") -> On-time attendance reward | L72: =IFERROR(__xludf.DUMMYFUNCTION("""COMPUTED_VALUE"""),"Success") -> Success
A73: =IFERROR(__xludf.DUMMYFUNCTION("""COMPUTED_VALUE"""),46177.34989583334) -> 46177.35 | B73: =IFERROR(__xludf.DUMMYFUNCTION("""COMPUTED_VALUE"""),46177.0) -> 46177 | C73: =IFERROR(__xludf.DUMMYFUNCTION("""COMPUTED_VALUE"""),"5c07fef4") -> 5c07fef4 | D73: =IFERROR(__xludf.DUMMYFUNCTION("""COMPUTED_VALUE"""),"Tiffany Kim") -> Tiffany Kim | E73: =IFERROR(__xludf.DUMMYFUNCTION("""COMPUTED_VALUE"""),"REWARD") -> REWARD | F73: =IFERROR(__xludf.DUMMYFUNCTION("""COMPUTED_VALUE"""),10.0) -> 10 | G73: =IFERROR(__xludf.DUMMYFUNCTION("""COMPUTED_VALUE"""),60.0) -> 60 | H73: =IFERROR(__xludf.DUMMYFUNCTION("""COMPUTED_VALUE"""),70.0) -> 70 | K73: =IFERROR(__xludf.DUMMYFUNCTION("""COMPUTED_VALUE"""),"On-time attendance reward") -> On-time attendance reward | L73: =IFERROR(__xludf.DUMMYFUNCTION("""COMPUTED_VALUE"""),"Success") -> Success
A74: =IFERROR(__xludf.DUMMYFUNCTION("""COMPUTED_VALUE"""),46177.35613425926) -> 46177.356 | B74: =IFERROR(__xludf.DUMMYFUNCTION("""COMPUTED_VALUE"""),46177.0) -> 46177 | C74: =IFERROR(__xludf.DUMMYFUNCTION("""COMPUTED_VALUE"""),"ba912211") -> ba912211 | D74: =IFERROR(__xludf.DUMMYFUNCTION("""COMPUTED_VALUE"""),"Daisy Dou") -> Daisy Dou | E74: =IFERROR(__xludf.DUMMYFUNCTION("""COMPUTED_VALUE"""),"REWARD") -> REWARD | F74: =IFERROR(__xludf.DUMMYFUNCTION("""COMPUTED_VALUE"""),10.0) -> 10 | G74: =IFERROR(__xludf.DUMMYFUNCTION("""COMPUTED_VALUE"""),131.0) -> 131 | H74: =IFERROR(__xludf.DUMMYFUNCTION("""COMPUTED_VALUE"""),141.0) -> 141 | K74: =IFERROR(__xludf.DUMMYFUNCTION("""COMPUTED_VALUE"""),"On-time attendance reward") -> On-time attendance reward | L74: =IFERROR(__xludf.DUMMYFUNCTION("""COMPUTED_VALUE"""),"Success") -> Success
A75: =IFERROR(__xludf.DUMMYFUNCTION("""COMPUTED_VALUE"""),46177.35655092593) -> 46177.357 | B75: =IFERROR(__xludf.DUMMYFUNCTION("""COMPUTED_VALUE"""),46177.0) -> 46177 | C75: =IFERROR(__xludf.DUMMYFUNCTION("""COMPUTED_VALUE"""),"7c4e261e") -> 7c4e261e | D75: =IFERROR(__xludf.DUMMYFUNCTION("""COMPUTED_VALUE"""),"Suha Lee") -> Suha Lee | E75: =IFERROR(__xludf.DUMMYFUNCTION("""COMPUTED_VALUE"""),"REWARD") -> REWARD | F75: =IFERROR(__xludf.DUMMYFUNCTION("""COMPUTED_VALUE"""),10.0) -> 10 | G75: =IFERROR(__xludf.DUMMYFUNCTION("""COMPUTED_VALUE"""),80.0) -> 80 | H75: =IFERROR(__xludf.DUMMYFUNCTION("""COMPUTED_VALUE"""),90.0) -> 90 | K75: =IFERROR(__xludf.DUMMYFUNCTION("""COMPUTED_VALUE"""),"On-time attendance reward") -> On-time attendance reward | L75: =IFERROR(__xludf.DUMMYFUNCTION("""COMPUTED_VALUE"""),"Success") -> Success
A76: =IFERROR(__xludf.DUMMYFUNCTION("""COMPUTED_VALUE"""),46177.35769675926) -> 46177.358 | B76: =IFERROR(__xludf.DUMMYFUNCTION("""COMPUTED_VALUE"""),46177.0) -> 46177 | C76: =IFERROR(__xludf.DUMMYFUNCTION("""COMPUTED_VALUE"""),"1e3e1410") -> 1e3e1410 | D76: =IFERROR(__xludf.DUMMYFUNCTION("""COMPUTED_VALUE"""),"Junjae Park") -> Junjae Park | E76: =IFERROR(__xludf.DUMMYFUNCTION("""COMPUTED_VALUE"""),"REWARD") -> REWARD | F76: =IFERROR(__xludf.DUMMYFUNCTION("""COMPUTED_VALUE"""),10.0) -> 10 | G76: =IFERROR(__xludf.DUMMYFUNCTION("""COMPUTED_VALUE"""),10.0) -> 10 | H76: =IFERROR(__xludf.DUMMYFUNCTION("""COMPUTED_VALUE"""),20.0) -> 20 | K76: =IFERROR(__xludf.DUMMYFUNCTION("""COMPUTED_VALUE"""),"On-time attendance reward") -> On-time attendance reward | L76: =IFERROR(__xludf.DUMMYFUNCTION("""COMPUTED_VALUE"""),"Success") -> Success
A77: =IFERROR(__xludf.DUMMYFUNCTION("""COMPUTED_VALUE"""),46177.35804398148) -> 46177.358 | B77: =IFERROR(__xludf.DUMMYFUNCTION("""COMPUTED_VALUE"""),46177.0) -> 46177 | C77: =IFERROR(__xludf.DUMMYFUNCTION("""COMPUTED_VALUE"""),"5a032611") -> 5a032611 | D77: =IFERROR(__xludf.DUMMYFUNCTION("""COMPUTED_VALUE"""),"Harold Dou") -> Harold Dou | E77: =IFERROR(__xludf.DUMMYFUNCTION("""COMPUTED_VALUE"""),"REWARD") -> REWARD | F77: =IFERROR(__xludf.DUMMYFUNCTION("""COMPUTED_VALUE"""),10.0) -> 10 | G77: =IFERROR(__xludf.DUMMYFUNCTION("""COMPUTED_VALUE"""),50.0) -> 50 | H77: =IFERROR(__xludf.DUMMYFUNCTION("""COMPUTED_VALUE"""),60.0) -> 60 | K77: =IFERROR(__xludf.DUMMYFUNCTION("""COMPUTED_VALUE"""),"On-time attendance reward") -> On-time attendance reward | L77: =IFERROR(__xludf.DUMMYFUNCTION("""COMPUTED_VALUE"""),"Success") -> Success
A78: =IFERROR(__xludf.DUMMYFUNCTION("""COMPUTED_VALUE"""),46177.35815972222) -> 46177.358 | B78: =IFERROR(__xludf.DUMMYFUNCTION("""COMPUTED_VALUE"""),46177.0) -> 46177 | C78: =IFERROR(__xludf.DUMMYFUNCTION("""COMPUTED_VALUE"""),"9a5f2811") -> 9a5f2811 | D78: =IFERROR(__xludf.DUMMYFUNCTION("""COMPUTED_VALUE"""),"Junyoung Yoo") -> Junyoung Yoo | E78: =IFERROR(__xludf.DUMMYFUNCTION("""COMPUTED_VALUE"""),"REWARD") -> REWARD | F78: =IFERROR(__xludf.DUMMYFUNCTION("""COMPUTED_VALUE"""),10.0) -> 10 | G78: =IFERROR(__xludf.DUMMYFUNCTION("""COMPUTED_VALUE"""),50.0) -> 50 | H78: =IFERROR(__xludf.DUMMYFUNCTION("""COMPUTED_VALUE"""),60.0) -> 60 | K78: =IFERROR(__xludf.DUMMYFUNCTION("""COMPUTED_VALUE"""),"On-time attendance reward") -> On-time attendance reward | L78: =IFERROR(__xludf.DUMMYFUNCTION("""COMPUTED_VALUE"""),"Success") -> Success
A79: =IFERROR(__xludf.DUMMYFUNCTION("""COMPUTED_VALUE"""),46177.3590625) -> 46177.359 | B79: =IFERROR(__xludf.DUMMYFUNCTION("""COMPUTED_VALUE"""),46177.0) -> 46177 | C79: =IFERROR(__xludf.DUMMYFUNCTION("""COMPUTED_VALUE"""),"ba353911") -> ba353911 | D79: =IFERROR(__xludf.DUMMYFUNCTION("""COMPUTED_VALUE"""),"Dayeon Kang") -> Dayeon Kang | E79: =IFERROR(__xludf.DUMMYFUNCTION("""COMPUTED_VALUE"""),"FINE") -> FINE | F79: =IFERROR(__xludf.DUMMYFUNCTION("""COMPUTED_VALUE"""),10.0) -> 10 | G79: =IFERROR(__xludf.DUMMYFUNCTION("""COMPUTED_VALUE"""),40.0) -> 40 | H79: =IFERROR(__xludf.DUMMYFUNCTION("""COMPUTED_VALUE"""),30.0) -> 30 | K79: =IFERROR(__xludf.DUMMYFUNCTION("""COMPUTED_VALUE"""),"Late attendance penalty") -> Late attendance penalty | L79: =IFERROR(__xludf.DUMMYFUNCTION("""COMPUTED_VALUE"""),"Success") -> Success
A80: =IFERROR(__xludf.DUMMYFUNCTION("""COMPUTED_VALUE"""),46177.36456018518) -> 46177.365 | B80: =IFERROR(__xludf.DUMMYFUNCTION("""COMPUTED_VALUE"""),46177.0) -> 46177 | C80: =IFERROR(__xludf.DUMMYFUNCTION("""COMPUTED_VALUE"""),"ba0fc5c4") -> ba0fc5c4 | D80: =IFERROR(__xludf.DUMMYFUNCTION("""COMPUTED_VALUE"""),"Junwoo Kang") -> Junwoo Kang | E80: =IFERROR(__xludf.DUMMYFUNCTION("""COMPUTED_VALUE"""),"FINE") -> FINE | F80: =IFERROR(__xludf.DUMMYFUNCTION("""COMPUTED_VALUE"""),10.0) -> 10 | G80: =IFERROR(__xludf.DUMMYFUNCTION("""COMPUTED_VALUE"""),0.0) -> 0 | H80: =IFERROR(__xludf.DUMMYFUNCTION("""COMPUTED_VALUE"""),0.0) -> 0 | K80: =IFERROR(__xludf.DUMMYFUNCTION("""COMPUTED_VALUE"""),"Late attendance penalty") -> Late attendance penalty | L80: =IFERROR(__xludf.DUMMYFUNCTION("""COMPUTED_VALUE"""),"Denied - insufficient balance") -> Denied - insufficient balance
A81: =IFERROR(__xludf.DUMMYFUNCTION("""COMPUTED_VALUE"""),46178.34515046296) -> 46178.345 | B81: =IFERROR(__xludf.DUMMYFUNCTION("""COMPUTED_VALUE"""),46178.0) -> 46178 | C81: =IFERROR(__xludf.DUMMYFUNCTION("""COMPUTED_VALUE"""),"ba912211") -> ba912211 | D81: =IFERROR(__xludf.DUMMYFUNCTION("""COMPUTED_VALUE"""),"Daisy Dou") -> Daisy Dou | E81: =IFERROR(__xludf.DUMMYFUNCTION("""COMPUTED_VALUE"""),"REWARD") -> REWARD | F81: =IFERROR(__xludf.DUMMYFUNCTION("""COMPUTED_VALUE"""),10.0) -> 10 | G81: =IFERROR(__xludf.DUMMYFUNCTION("""COMPUTED_VALUE"""),141.0) -> 141 | H81: =IFERROR(__xludf.DUMMYFUNCTION("""COMPUTED_VALUE"""),151.0) -> 151 | K81: =IFERROR(__xludf.DUMMYFUNCTION("""COMPUTED_VALUE"""),"On-time attendance reward") -> On-time attendance reward | L81: =IFERROR(__xludf.DUMMYFUNCTION("""COMPUTED_VALUE"""),"Success") -> Success
A82: =IFERROR(__xludf.DUMMYFUNCTION("""COMPUTED_VALUE"""),46178.34532407407) -> 46178.345 | B82: =IFERROR(__xludf.DUMMYFUNCTION("""COMPUTED_VALUE"""),46178.0) -> 46178 | C82: =IFERROR(__xludf.DUMMYFUNCTION("""COMPUTED_VALUE"""),"5c07fef4") -> 5c07fef4 | D82: =IFERROR(__xludf.DUMMYFUNCTION("""COMPUTED_VALUE"""),"Tiffany Kim") -> Tiffany Kim | E82: =IFERROR(__xludf.DUMMYFUNCTION("""COMPUTED_VALUE"""),"REWARD") -> REWARD | F82: =IFERROR(__xludf.DUMMYFUNCTION("""COMPUTED_VALUE"""),10.0) -> 10 | G82: =IFERROR(__xludf.DUMMYFUNCTION("""COMPUTED_VALUE"""),70.0) -> 70 | H82: =IFERROR(__xludf.DUMMYFUNCTION("""COMPUTED_VALUE"""),80.0) -> 80 | K82: =IFERROR(__xludf.DUMMYFUNCTION("""COMPUTED_VALUE"""),"On-time attendance reward") -> On-time attendance reward | L82: =IFERROR(__xludf.DUMMYFUNCTION("""COMPUTED_VALUE"""),"Success") -> Success
A83: =IFERROR(__xludf.DUMMYFUNCTION("""COMPUTED_VALUE"""),46178.34637731482) -> 46178.346 | B83: =IFERROR(__xludf.DUMMYFUNCTION("""COMPUTED_VALUE"""),46178.0) -> 46178 | C83: =IFERROR(__xludf.DUMMYFUNCTION("""COMPUTED_VALUE"""),"ba912211") -> ba912211 | D83: =IFERROR(__xludf.DUMMYFUNCTION("""COMPUTED_VALUE"""),"Daisy Dou") -> Daisy Dou | E83: =IFERROR(__xludf.DUMMYFUNCTION("""COMPUTED_VALUE"""),"DEPOSIT") -> DEPOSIT | F83: =IFERROR(__xludf.DUMMYFUNCTION("""COMPUTED_VALUE"""),121.0) -> 121 | G83: =IFERROR(__xludf.DUMMYFUNCTION("""COMPUTED_VALUE"""),151.0) -> 151 | H83: =IFERROR(__xludf.DUMMYFUNCTION("""COMPUTED_VALUE"""),272.0) -> 272 | L83: =IFERROR(__xludf.DUMMYFUNCTION("""COMPUTED_VALUE"""),"Success") -> Success
A84: =IFERROR(__xludf.DUMMYFUNCTION("""COMPUTED_VALUE"""),46178.349594907406) -> 46178.35 | B84: =IFERROR(__xludf.DUMMYFUNCTION("""COMPUTED_VALUE"""),46178.0) -> 46178 | C84: =IFERROR(__xludf.DUMMYFUNCTION("""COMPUTED_VALUE"""),"ae072910") -> ae072910 | D84: =IFERROR(__xludf.DUMMYFUNCTION("""COMPUTED_VALUE"""),"Selena Jung") -> Selena Jung | E84: =IFERROR(__xludf.DUMMYFUNCTION("""COMPUTED_VALUE"""),"REWARD") -> REWARD | F84: =IFERROR(__xludf.DUMMYFUNCTION("""COMPUTED_VALUE"""),10.0) -> 10 | G84: =IFERROR(__xludf.DUMMYFUNCTION("""COMPUTED_VALUE"""),40.0) -> 40 | H84: =IFERROR(__xludf.DUMMYFUNCTION("""COMPUTED_VALUE"""),50.0) -> 50 | K84: =IFERROR(__xludf.DUMMYFUNCTION("""COMPUTED_VALUE"""),"On-time attendance reward") -> On-time attendance reward | L84: =IFERROR(__xludf.DUMMYFUNCTION("""COMPUTED_VALUE"""),"Success") -> Success
A85: =IFERROR(__xludf.DUMMYFUNCTION("""COMPUTED_VALUE"""),46178.35016203704) -> 46178.35 | B85: =IFERROR(__xludf.DUMMYFUNCTION("""COMPUTED_VALUE"""),46178.0) -> 46178 | C85: =IFERROR(__xludf.DUMMYFUNCTION("""COMPUTED_VALUE"""),"dc04eef4") -> dc04eef4 | D85: =IFERROR(__xludf.DUMMYFUNCTION("""COMPUTED_VALUE"""),"Joshua Jung") -> Joshua Jung | E85: =IFERROR(__xludf.DUMMYFUNCTION("""COMPUTED_VALUE"""),"REWARD") -> REWARD | F85: =IFERROR(__xludf.DUMMYFUNCTION("""COMPUTED_VALUE"""),10.0) -> 10 | G85: =IFERROR(__xludf.DUMMYFUNCTION("""COMPUTED_VALUE"""),90.0) -> 90 | H85: =IFERROR(__xludf.DUMMYFUNCTION("""COMPUTED_VALUE"""),100.0) -> 100 | K85: =IFERROR(__xludf.DUMMYFUNCTION("""COMPUTED_VALUE"""),"On-time attendance reward") -> On-time attendance reward | L85: =IFERROR(__xludf.DUMMYFUNCTION("""COMPUTED_VALUE"""),"Success") -> Success
A86: =IFERROR(__xludf.DUMMYFUNCTION("""COMPUTED_VALUE"""),46178.35517361111) -> 46178.355 | B86: =IFERROR(__xludf.DUMMYFUNCTION("""COMPUTED_VALUE"""),46178.0) -> 46178 | C86: =IFERROR(__xludf.DUMMYFUNCTION("""COMPUTED_VALUE"""),"7c4e261e") -> 7c4e261e | D86: =IFERROR(__xludf.DUMMYFUNCTION("""COMPUTED_VALUE"""),"Suha Lee") -> Suha Lee | E86: =IFERROR(__xludf.DUMMYFUNCTION("""COMPUTED_VALUE"""),"REWARD") -> REWARD | F86: =IFERROR(__xludf.DUMMYFUNCTION("""COMPUTED_VALUE"""),10.0) -> 10 | G86: =IFERROR(__xludf.DUMMYFUNCTION("""COMPUTED_VALUE"""),90.0) -> 90 | H86: =IFERROR(__xludf.DUMMYFUNCTION("""COMPUTED_VALUE"""),100.0) -> 100 | K86: =IFERROR(__xludf.DUMMYFUNCTION("""COMPUTED_VALUE"""),"On-time attendance reward") -> On-time attendance reward | L86: =IFERROR(__xludf.DUMMYFUNCTION("""COMPUTED_VALUE"""),"Success") -> Success
A87: =IFERROR(__xludf.DUMMYFUNCTION("""COMPUTED_VALUE"""),46178.35550925926) -> 46178.356 | B87: =IFERROR(__xludf.DUMMYFUNCTION("""COMPUTED_VALUE"""),46178.0) -> 46178 | C87: =IFERROR(__xludf.DUMMYFUNCTION("""COMPUTED_VALUE"""),"ae072910") -> ae072910 | D87: =IFERROR(__xludf.DUMMYFUNCTION("""COMPUTED_VALUE"""),"Selena Jung") -> Selena Jung | E87: =IFERROR(__xludf.DUMMYFUNCTION("""COMPUTED_VALUE"""),"DEPOSIT") -> DEPOSIT | F87: =IFERROR(__xludf.DUMMYFUNCTION("""COMPUTED_VALUE"""),5.0) -> 5 | G87: =IFERROR(__xludf.DUMMYFUNCTION("""COMPUTED_VALUE"""),50.0) -> 50 | H87: =IFERROR(__xludf.DUMMYFUNCTION("""COMPUTED_VALUE"""),55.0) -> 55 | L87: =IFERROR(__xludf.DUMMYFUNCTION("""COMPUTED_VALUE"""),"Success") -> Success
A88: =IFERROR(__xludf.DUMMYFUNCTION("""COMPUTED_VALUE"""),46178.3565625) -> 46178.357 | B88: =IFERROR(__xludf.DUMMYFUNCTION("""COMPUTED_VALUE"""),46178.0) -> 46178 | C88: =IFERROR(__xludf.DUMMYFUNCTION("""COMPUTED_VALUE"""),"9a5f2811") -> 9a5f2811 | D88: =IFERROR(__xludf.DUMMYFUNCTION("""COMPUTED_VALUE"""),"Junyoung Yoo") -> Junyoung Yoo | E88: =IFERROR(__xludf.DUMMYFUNCTION("""COMPUTED_VALUE"""),"REWARD") -> REWARD | F88: =IFERROR(__xludf.DUMMYFUNCTION("""COMPUTED_VALUE"""),10.0) -> 10 | G88: =IFERROR(__xludf.DUMMYFUNCTION("""COMPUTED_VALUE"""),60.0) -> 60 | H88: =IFERROR(__xludf.DUMMYFUNCTION("""COMPUTED_VALUE"""),70.0) -> 70 | K88: =IFERROR(__xludf.DUMMYFUNCTION("""COMPUTED_VALUE"""),"On-time attendance reward") -> On-time attendance reward | L88: =IFERROR(__xludf.DUMMYFUNCTION("""COMPUTED_VALUE"""),"Success") -> Success
A89: =IFERROR(__xludf.DUMMYFUNCTION("""COMPUTED_VALUE"""),46178.3578125) -> 46178.358 | B89: =IFERROR(__xludf.DUMMYFUNCTION("""COMPUTED_VALUE"""),46178.0) -> 46178 | C89: =IFERROR(__xludf.DUMMYFUNCTION("""COMPUTED_VALUE"""),"ba353911") -> ba353911 | D89: =IFERROR(__xludf.DUMMYFUNCTION("""COMPUTED_VALUE"""),"Dayeon Kang") -> Dayeon Kang | E89: =IFERROR(__xludf.DUMMYFUNCTION("""COMPUTED_VALUE"""),"REWARD") -> REWARD | F89: =IFERROR(__xludf.DUMMYFUNCTION("""COMPUTED_VALUE"""),10.0) -> 10 | G89: =IFERROR(__xludf.DUMMYFUNCTION("""COMPUTED_VALUE"""),30.0) -> 30 | H89: =IFERROR(__xludf.DUMMYFUNCTION("""COMPUTED_VALUE"""),40.0) -> 40 | K89: =IFERROR(__xludf.DUMMYFUNCTION("""COMPUTED_VALUE"""),"On-time attendance reward") -> On-time attendance reward | L89: =IFERROR(__xludf.DUMMYFUNCTION("""COMPUTED_VALUE"""),"Success") -> Success
A90: =IFERROR(__xludf.DUMMYFUNCTION("""COMPUTED_VALUE"""),46178.375185185185) -> 46178.375 | B90: =IFERROR(__xludf.DUMMYFUNCTION("""COMPUTED_VALUE"""),46178.0) -> 46178 | C90: =IFERROR(__xludf.DUMMYFUNCTION("""COMPUTED_VALUE"""),"5a032611") -> 5a032611 | D90: =IFERROR(__xludf.DUMMYFUNCTION("""COMPUTED_VALUE"""),"Harold Dou") -> Harold Dou | E90: =IFERROR(__xludf.DUMMYFUNCTION("""COMPUTED_VALUE"""),"FINE") -> FINE | F90: =IFERROR(__xludf.DUMMYFUNCTION("""COMPUTED_VALUE"""),10.0) -> 10 | G90: =IFERROR(__xludf.DUMMYFUNCTION("""COMPUTED_VALUE"""),60.0) -> 60 | H90: =IFERROR(__xludf.DUMMYFUNCTION("""COMPUTED_VALUE"""),50.0) -> 50 | K90: =IFERROR(__xludf.DUMMYFUNCTION("""COMPUTED_VALUE"""),"Late attendance penalty") -> Late attendance penalty | L90: =IFERROR(__xludf.DUMMYFUNCTION("""COMPUTED_VALUE"""),"Success") -> Success
A91: =IFERROR(__xludf.DUMMYFUNCTION("""COMPUTED_VALUE"""),46178.55496527778) -> 46178.555 | B91: =IFERROR(__xludf.DUMMYFUNCTION("""COMPUTED_VALUE"""),46178.0) -> 46178 | C91: =IFERROR(__xludf.DUMMYFUNCTION("""COMPUTED_VALUE"""),"5a032611") -> 5a032611 | D91: =IFERROR(__xludf.DUMMYFUNCTION("""COMPUTED_VALUE"""),"Harold Dou") -> Harold Dou | E91: =IFERROR(__xludf.DUMMYFUNCTION("""COMPUTED_VALUE"""),"DEPOSIT") -> DEPOSIT | F91: =IFERROR(__xludf.DUMMYFUNCTION("""COMPUTED_VALUE"""),15.0) -> 15 | G91: =IFERROR(__xludf.DUMMYFUNCTION("""COMPUTED_VALUE"""),50.0) -> 50 | H91: =IFERROR(__xludf.DUMMYFUNCTION("""COMPUTED_VALUE"""),65.0) -> 65 | L91: =IFERROR(__xludf.DUMMYFUNCTION("""COMPUTED_VALUE"""),"Success") -> Success
A92: =IFERROR(__xludf.DUMMYFUNCTION("""COMPUTED_VALUE"""),46181.34355324074) -> 46181.344 | B92: =IFERROR(__xludf.DUMMYFUNCTION("""COMPUTED_VALUE"""),46181.0) -> 46181 | C92: =IFERROR(__xludf.DUMMYFUNCTION("""COMPUTED_VALUE"""),"ae072910") -> ae072910 | D92: =IFERROR(__xludf.DUMMYFUNCTION("""COMPUTED_VALUE"""),"Selena Jung") -> Selena Jung | E92: =IFERROR(__xludf.DUMMYFUNCTION("""COMPUTED_VALUE"""),"REWARD") -> REWARD | F92: =IFERROR(__xludf.DUMMYFUNCTION("""COMPUTED_VALUE"""),10.0) -> 10 | G92: =IFERROR(__xludf.DUMMYFUNCTION("""COMPUTED_VALUE"""),472.79) -> 472.79 | H92: =IFERROR(__xludf.DUMMYFUNCTION("""COMPUTED_VALUE"""),482.79) -> 482.79 | K92: =IFERROR(__xludf.DUMMYFUNCTION("""COMPUTED_VALUE"""),"On-time attendance reward") -> On-time attendance reward | L92: =IFERROR(__xludf.DUMMYFUNCTION("""COMPUTED_VALUE"""),"Success") -> Success
A93: =IFERROR(__xludf.DUMMYFUNCTION("""COMPUTED_VALUE"""),46181.34873842593) -> 46181.349 | B93: =IFERROR(__xludf.DUMMYFUNCTION("""COMPUTED_VALUE"""),46181.0) -> 46181 | C93: =IFERROR(__xludf.DUMMYFUNCTION("""COMPUTED_VALUE"""),"dc04eef4") -> dc04eef4 | D93: =IFERROR(__xludf.DUMMYFUNCTION("""COMPUTED_VALUE"""),"Joshua Jung") -> Joshua Jung | E93: =IFERROR(__xludf.DUMMYFUNCTION("""COMPUTED_VALUE"""),"REWARD") -> REWARD | F93: =IFERROR(__xludf.DUMMYFUNCTION("""COMPUTED_VALUE"""),10.0) -> 10 | G93: =IFERROR(__xludf.DUMMYFUNCTION("""COMPUTED_VALUE"""),275.16) -> 275.16 | H93: =IFERROR(__xludf.DUMMYFUNCTION("""COMPUTED_VALUE"""),285.16) -> 285.16 | K93: =IFERROR(__xludf.DUMMYFUNCTION("""COMPUTED_VALUE"""),"On-time attendance reward") -> On-time attendance reward | L93: =IFERROR(__xludf.DUMMYFUNCTION("""COMPUTED_VALUE"""),"Success") -> Success
A94: =IFERROR(__xludf.DUMMYFUNCTION("""COMPUTED_VALUE"""),46181.34923611111) -> 46181.349 | B94: =IFERROR(__xludf.DUMMYFUNCTION("""COMPUTED_VALUE"""),46181.0) -> 46181 | C94: =IFERROR(__xludf.DUMMYFUNCTION("""COMPUTED_VALUE"""),"5c07fef4") -> 5c07fef4 | D94: =IFERROR(__xludf.DUMMYFUNCTION("""COMPUTED_VALUE"""),"Tiffany Kim") -> Tiffany Kim | E94: =IFERROR(__xludf.DUMMYFUNCTION("""COMPUTED_VALUE"""),"REWARD") -> REWARD | F94: =IFERROR(__xludf.DUMMYFUNCTION("""COMPUTED_VALUE"""),10.0) -> 10 | G94: =IFERROR(__xludf.DUMMYFUNCTION("""COMPUTED_VALUE"""),580.0) -> 580 | H94: =IFERROR(__xludf.DUMMYFUNCTION("""COMPUTED_VALUE"""),590.0) -> 590 | K94: =IFERROR(__xludf.DUMMYFUNCTION("""COMPUTED_VALUE"""),"On-time attendance reward") -> On-time attendance reward | L94: =IFERROR(__xludf.DUMMYFUNCTION("""COMPUTED_VALUE"""),"Success") -> Success
A95: =IFERROR(__xludf.DUMMYFUNCTION("""COMPUTED_VALUE"""),46181.35068287037) -> 46181.351 | B95: =IFERROR(__xludf.DUMMYFUNCTION("""COMPUTED_VALUE"""),46181.0) -> 46181 | C95: =IFERROR(__xludf.DUMMYFUNCTION("""COMPUTED_VALUE"""),"5a032611") -> 5a032611 | D95: =IFERROR(__xludf.DUMMYFUNCTION("""COMPUTED_VALUE"""),"Harold Dou") -> Harold Dou | E95: =IFERROR(__xludf.DUMMYFUNCTION("""COMPUTED_VALUE"""),"REWARD") -> REWARD | F95: =IFERROR(__xludf.DUMMYFUNCTION("""COMPUTED_VALUE"""),10.0) -> 10 | G95: =IFERROR(__xludf.DUMMYFUNCTION("""COMPUTED_VALUE"""),565.0) -> 565 | H95: =IFERROR(__xludf.DUMMYFUNCTION("""COMPUTED_VALUE"""),575.0) -> 575 | K95: =IFERROR(__xludf.DUMMYFUNCTION("""COMPUTED_VALUE"""),"On-time attendance reward") -> On-time attendance reward | L95: =IFERROR(__xludf.DUMMYFUNCTION("""COMPUTED_VALUE"""),"Success") -> Success
A96: =IFERROR(__xludf.DUMMYFUNCTION("""COMPUTED_VALUE"""),46181.35196759259) -> 46181.352 | B96: =IFERROR(__xludf.DUMMYFUNCTION("""COMPUTED_VALUE"""),46181.0) -> 46181 | C96: =IFERROR(__xludf.DUMMYFUNCTION("""COMPUTED_VALUE"""),"ba912211") -> ba912211 | D96: =IFERROR(__xludf.DUMMYFUNCTION("""COMPUTED_VALUE"""),"Daisy Doh") -> Daisy Doh | E96: =IFERROR(__xludf.DUMMYFUNCTION("""COMPUTED_VALUE"""),"REWARD") -> REWARD | F96: =IFERROR(__xludf.DUMMYFUNCTION("""COMPUTED_VALUE"""),10.0) -> 10 | G96: =IFERROR(__xludf.DUMMYFUNCTION("""COMPUTED_VALUE"""),696.29) -> 696.29 | H96: =IFERROR(__xludf.DUMMYFUNCTION("""COMPUTED_VALUE"""),706.29) -> 706.29 | K96: =IFERROR(__xludf.DUMMYFUNCTION("""COMPUTED_VALUE"""),"On-time attendance reward") -> On-time attendance reward | L96: =IFERROR(__xludf.DUMMYFUNCTION("""COMPUTED_VALUE"""),"Success") -> Success
A97: =IFERROR(__xludf.DUMMYFUNCTION("""COMPUTED_VALUE"""),46181.354097222225) -> 46181.354 | B97: =IFERROR(__xludf.DUMMYFUNCTION("""COMPUTED_VALUE"""),46181.0) -> 46181 | C97: =IFERROR(__xludf.DUMMYFUNCTION("""COMPUTED_VALUE"""),"babde4c4") -> babde4c4 | D97: =IFERROR(__xludf.DUMMYFUNCTION("""COMPUTED_VALUE"""),"Ashley Guk") -> Ashley Guk | E97: =IFERROR(__xludf.DUMMYFUNCTION("""COMPUTED_VALUE"""),"REWARD") -> REWARD | F97: =IFERROR(__xludf.DUMMYFUNCTION("""COMPUTED_VALUE"""),10.0) -> 10 | G97: =IFERROR(__xludf.DUMMYFUNCTION("""COMPUTED_VALUE"""),596.0) -> 596 | H97: =IFERROR(__xludf.DUMMYFUNCTION("""COMPUTED_VALUE"""),606.0) -> 606 | K97: =IFERROR(__xludf.DUMMYFUNCTION("""COMPUTED_VALUE"""),"On-time attendance reward") -> On-time attendance reward | L97: =IFERROR(__xludf.DUMMYFUNCTION("""COMPUTED_VALUE"""),"Success") -> Success
A98: =IFERROR(__xludf.DUMMYFUNCTION("""COMPUTED_VALUE"""),46181.35700231481) -> 46181.357 | B98: =IFERROR(__xludf.DUMMYFUNCTION("""COMPUTED_VALUE"""),46181.0) -> 46181 | C98: =IFERROR(__xludf.DUMMYFUNCTION("""COMPUTED_VALUE"""),"9a5f2811") -> 9a5f2811 | D98: =IFERROR(__xludf.DUMMYFUNCTION("""COMPUTED_VALUE"""),"Junyoung Yoo") -> Junyoung Yoo | E98: =IFERROR(__xludf.DUMMYFUNCTION("""COMPUTED_VALUE"""),"REWARD") -> REWARD | F98: =IFERROR(__xludf.DUMMYFUNCTION("""COMPUTED_VALUE"""),10.0) -> 10 | G98: =IFERROR(__xludf.DUMMYFUNCTION("""COMPUTED_VALUE"""),44.4) -> 44.4 | H98: =IFERROR(__xludf.DUMMYFUNCTION("""COMPUTED_VALUE"""),54.4) -> 54.4 | K98: =IFERROR(__xludf.DUMMYFUNCTION("""COMPUTED_VALUE"""),"On-time attendance reward") -> On-time attendance reward | L98: =IFERROR(__xludf.DUMMYFUNCTION("""COMPUTED_VALUE"""),"Success") -> Success
A99: =IFERROR(__xludf.DUMMYFUNCTION("""COMPUTED_VALUE"""),46181.35716435185) -> 46181.357 | B99: =IFERROR(__xludf.DUMMYFUNCTION("""COMPUTED_VALUE"""),46181.0) -> 46181 | C99: =IFERROR(__xludf.DUMMYFUNCTION("""COMPUTED_VALUE"""),"1e3e1410") -> 1e3e1410 | D99: =IFERROR(__xludf.DUMMYFUNCTION("""COMPUTED_VALUE"""),"Junjae Park") -> Junjae Park | E99: =IFERROR(__xludf.DUMMYFUNCTION("""COMPUTED_VALUE"""),"REWARD") -> REWARD | F99: =IFERROR(__xludf.DUMMYFUNCTION("""COMPUTED_VALUE"""),10.0) -> 10 | G99: =IFERROR(__xludf.DUMMYFUNCTION("""COMPUTED_VALUE"""),44.8) -> 44.8 | H99: =IFERROR(__xludf.DUMMYFUNCTION("""COMPUTED_VALUE"""),54.8) -> 54.8 | K99: =IFERROR(__xludf.DUMMYFUNCTION("""COMPUTED_VALUE"""),"On-time attendance reward") -> On-time attendance reward | L99: =IFERROR(__xludf.DUMMYFUNCTION("""COMPUTED_VALUE"""),"Success") -> Success
A100: =IFERROR(__xludf.DUMMYFUNCTION("""COMPUTED_VALUE"""),46181.357407407406) -> 46181.357 | B100: =IFERROR(__xludf.DUMMYFUNCTION("""COMPUTED_VALUE"""),46181.0) -> 46181 | C100: =IFERROR(__xludf.DUMMYFUNCTION("""COMPUTED_VALUE"""),"ba353911") -> ba353911 | D100: =IFERROR(__xludf.DUMMYFUNCTION("""COMPUTED_VALUE"""),"Dayeon Kang") -> Dayeon Kang | E100: =IFERROR(__xludf.DUMMYFUNCTION("""COMPUTED_VALUE"""),"REWARD") -> REWARD | F100: =IFERROR(__xludf.DUMMYFUNCTION("""COMPUTED_VALUE"""),10.0) -> 10 | G100: =IFERROR(__xludf.DUMMYFUNCTION("""COMPUTED_VALUE"""),301.98) -> 301.98 | H100: =IFERROR(__xludf.DUMMYFUNCTION("""COMPUTED_VALUE"""),311.98) -> 311.98 | K100: =IFERROR(__xludf.DUMMYFUNCTION("""COMPUTED_VALUE"""),"On-time attendance reward") -> On-time attendance reward | L100: =IFERROR(__xludf.DUMMYFUNCTION("""COMPUTED_VALUE"""),"Success") -> Success
A101: =IFERROR(__xludf.DUMMYFUNCTION("""COMPUTED_VALUE"""),46181.36615740741) -> 46181.366 | B101: =IFERROR(__xludf.DUMMYFUNCTION("""COMPUTED_VALUE"""),46181.0) -> 46181 | C101: =IFERROR(__xludf.DUMMYFUNCTION("""COMPUTED_VALUE"""),"ba0fc5c4") -> ba0fc5c4 | D101: =IFERROR(__xludf.DUMMYFUNCTION("""COMPUTED_VALUE"""),"Junwoo Kang") -> Junwoo Kang | E101: =IFERROR(__xludf.DUMMYFUNCTION("""COMPUTED_VALUE"""),"FINE") -> FINE | F101: =IFERROR(__xludf.DUMMYFUNCTION("""COMPUTED_VALUE"""),10.0) -> 10 | G101: =IFERROR(__xludf.DUMMYFUNCTION("""COMPUTED_VALUE"""),20.08) -> 20.08 | H101: =IFERROR(__xludf.DUMMYFUNCTION("""COMPUTED_VALUE"""),10.079999999999998) -> 10.08 | K101: =IFERROR(__xludf.DUMMYFUNCTION("""COMPUTED_VALUE"""),"Late attendance penalty") -> Late attendance penalty | L101: =IFERROR(__xludf.DUMMYFUNCTION("""COMPUTED_VALUE"""),"Success") -> Success
...

Sheet Imported_Attendance
A1: =IFERROR(__xludf.DUMMYFUNCTION("IMPORTRANGE(""https://docs.google.com/spreadsheets/d/1xmGsP2eOXdfhJ9DjzCOVFJKoZ2DuuwRb_dbNg1M77M8/edit?gid=138364344#gid=138364344"",""Attendance_Log!A:M"")"),"Raw Attendance Scan Log") -> Raw Attendance Scan Log
A3: =IFERROR(__xludf.DUMMYFUNCTION("""COMPUTED_VALUE"""),"Timestamp") -> Timestamp | B3: =IFERROR(__xludf.DUMMYFUNCTION("""COMPUTED_VALUE"""),"Date") -> Date | C3: =IFERROR(__xludf.DUMMYFUNCTION("""COMPUTED_VALUE"""),"Card_ID") -> Card_ID | D3: =IFERROR(__xludf.DUMMYFUNCTION("""COMPUTED_VALUE"""),"Student_Name") -> Student_Name | E3: =IFERROR(__xludf.DUMMYFUNCTION("""COMPUTED_VALUE"""),"Grade") -> Grade | F3: =IFERROR(__xludf.DUMMYFUNCTION("""COMPUTED_VALUE"""),"Homeroom") -> Homeroom | G3: =IFERROR(__xludf.DUMMYFUNCTION("""COMPUTED_VALUE"""),"Class_Period") -> Class_Period | H3: =IFERROR(__xludf.DUMMYFUNCTION("""COMPUTED_VALUE"""),"Status") -> Status | I3: =IFERROR(__xludf.DUMMYFUNCTION("""COMPUTED_VALUE"""),"Check_In_Time") -> Check_In_Time | J3: =IFERROR(__xludf.DUMMYFUNCTION("""COMPUTED_VALUE"""),"Streak_After_Scan") -> Streak_After_Scan | K3: =IFERROR(__xludf.DUMMYFUNCTION("""COMPUTED_VALUE"""),"Bonus_Applied") -> Bonus_Applied | L3: =IFERROR(__xludf.DUMMYFUNCTION("""COMPUTED_VALUE"""),"Note") -> Note | M3: =IFERROR(__xludf.DUMMYFUNCTION("""COMPUTED_VALUE"""),"System_Status") -> System_Status
A4: =IFERROR(__xludf.DUMMYFUNCTION("""COMPUTED_VALUE"""),46163.34707175926) -> 46163.347 | B4: =IFERROR(__xludf.DUMMYFUNCTION("""COMPUTED_VALUE"""),46163.0) -> 46163 | C4: =IFERROR(__xludf.DUMMYFUNCTION("""COMPUTED_VALUE"""),"5c07fef4") -> 5c07fef4 | D4: =IFERROR(__xludf.DUMMYFUNCTION("""COMPUTED_VALUE"""),"Tiffany Kim") -> Tiffany Kim | E4: =IFERROR(__xludf.DUMMYFUNCTION("""COMPUTED_VALUE"""),10.0) -> 10 | F4: =IFERROR(__xludf.DUMMYFUNCTION("""COMPUTED_VALUE"""),"HS202") -> HS202 | G4: =IFERROR(__xludf.DUMMYFUNCTION("""COMPUTED_VALUE"""),"Homeroom") -> Homeroom | H4: =IFERROR(__xludf.DUMMYFUNCTION("""COMPUTED_VALUE"""),"Present") -> Present | I4: =IFERROR(__xludf.DUMMYFUNCTION("""COMPUTED_VALUE"""),0.34707175925925926) -> 0.34707176 | J4: =IFERROR(__xludf.DUMMYFUNCTION("""COMPUTED_VALUE"""),1.0) -> 1 | K4: =IFERROR(__xludf.DUMMYFUNCTION("""COMPUTED_VALUE"""),10.0) -> 10 | L4: =IFERROR(__xludf.DUMMYFUNCTION("""COMPUTED_VALUE"""),"On-time reward applied") -> On-time reward applied | M4: =IFERROR(__xludf.DUMMYFUNCTION("""COMPUTED_VALUE"""),"Success") -> Success
A5: =IFERROR(__xludf.DUMMYFUNCTION("""COMPUTED_VALUE"""),46163.348229166666) -> 46163.348 | B5: =IFERROR(__xludf.DUMMYFUNCTION("""COMPUTED_VALUE"""),46163.0) -> 46163 | C5: =IFERROR(__xludf.DUMMYFUNCTION("""COMPUTED_VALUE"""),"ba912211") -> ba912211 | D5: =IFERROR(__xludf.DUMMYFUNCTION("""COMPUTED_VALUE"""),"Daisy Dou") -> Daisy Dou | E5: =IFERROR(__xludf.DUMMYFUNCTION("""COMPUTED_VALUE"""),10.0) -> 10 | F5: =IFERROR(__xludf.DUMMYFUNCTION("""COMPUTED_VALUE"""),"HS202") -> HS202 | G5: =IFERROR(__xludf.DUMMYFUNCTION("""COMPUTED_VALUE"""),"Homeroom") -> Homeroom | H5: =IFERROR(__xludf.DUMMYFUNCTION("""COMPUTED_VALUE"""),"Present") -> Present | I5: =IFERROR(__xludf.DUMMYFUNCTION("""COMPUTED_VALUE"""),0.34822916666666665) -> 0.34822917 | J5: =IFERROR(__xludf.DUMMYFUNCTION("""COMPUTED_VALUE"""),1.0) -> 1 | K5: =IFERROR(__xludf.DUMMYFUNCTION("""COMPUTED_VALUE"""),10.0) -> 10 | L5: =IFERROR(__xludf.DUMMYFUNCTION("""COMPUTED_VALUE"""),"On-time reward applied") -> On-time reward applied | M5: =IFERROR(__xludf.DUMMYFUNCTION("""COMPUTED_VALUE"""),"Success") -> Success
A6: =IFERROR(__xludf.DUMMYFUNCTION("""COMPUTED_VALUE"""),46163.348449074074) -> 46163.348 | B6: =IFERROR(__xludf.DUMMYFUNCTION("""COMPUTED_VALUE"""),46163.0) -> 46163 | C6: =IFERROR(__xludf.DUMMYFUNCTION("""COMPUTED_VALUE"""),"babde4c4") -> babde4c4 | D6: =IFERROR(__xludf.DUMMYFUNCTION("""COMPUTED_VALUE"""),"Ashley Guk") -> Ashley Guk | E6: =IFERROR(__xludf.DUMMYFUNCTION("""COMPUTED_VALUE"""),10.0) -> 10 | F6: =IFERROR(__xludf.DUMMYFUNCTION("""COMPUTED_VALUE"""),"HS202") -> HS202 | G6: =IFERROR(__xludf.DUMMYFUNCTION("""COMPUTED_VALUE"""),"Homeroom") -> Homeroom | H6: =IFERROR(__xludf.DUMMYFUNCTION("""COMPUTED_VALUE"""),"Present") -> Present | I6: =IFERROR(__xludf.DUMMYFUNCTION("""COMPUTED_VALUE"""),0.34844907407407405) -> 0.34844907 | J6: =IFERROR(__xludf.DUMMYFUNCTION("""COMPUTED_VALUE"""),1.0) -> 1 | K6: =IFERROR(__xludf.DUMMYFUNCTION("""COMPUTED_VALUE"""),10.0) -> 10 | L6: =IFERROR(__xludf.DUMMYFUNCTION("""COMPUTED_VALUE"""),"On-time reward applied") -> On-time reward applied | M6: =IFERROR(__xludf.DUMMYFUNCTION("""COMPUTED_VALUE"""),"Success") -> Success
A7: =IFERROR(__xludf.DUMMYFUNCTION("""COMPUTED_VALUE"""),46163.349444444444) -> 46163.349 | B7: =IFERROR(__xludf.DUMMYFUNCTION("""COMPUTED_VALUE"""),46163.0) -> 46163 | C7: =IFERROR(__xludf.DUMMYFUNCTION("""COMPUTED_VALUE"""),"dc04eef4") -> dc04eef4 | D7: =IFERROR(__xludf.DUMMYFUNCTION("""COMPUTED_VALUE"""),"Joshua Jung") -> Joshua Jung | E7: =IFERROR(__xludf.DUMMYFUNCTION("""COMPUTED_VALUE"""),10.0) -> 10 | F7: =IFERROR(__xludf.DUMMYFUNCTION("""COMPUTED_VALUE"""),"HS202") -> HS202 | G7: =IFERROR(__xludf.DUMMYFUNCTION("""COMPUTED_VALUE"""),"Homeroom") -> Homeroom | H7: =IFERROR(__xludf.DUMMYFUNCTION("""COMPUTED_VALUE"""),"Present") -> Present | I7: =IFERROR(__xludf.DUMMYFUNCTION("""COMPUTED_VALUE"""),0.34944444444444445) -> 0.34944444 | J7: =IFERROR(__xludf.DUMMYFUNCTION("""COMPUTED_VALUE"""),1.0) -> 1 | K7: =IFERROR(__xludf.DUMMYFUNCTION("""COMPUTED_VALUE"""),10.0) -> 10 | L7: =IFERROR(__xludf.DUMMYFUNCTION("""COMPUTED_VALUE"""),"On-time reward applied") -> On-time reward applied | M7: =IFERROR(__xludf.DUMMYFUNCTION("""COMPUTED_VALUE"""),"Success") -> Success
A8: =IFERROR(__xludf.DUMMYFUNCTION("""COMPUTED_VALUE"""),46163.35587962963) -> 46163.356 | B8: =IFERROR(__xludf.DUMMYFUNCTION("""COMPUTED_VALUE"""),46163.0) -> 46163 | C8: =IFERROR(__xludf.DUMMYFUNCTION("""COMPUTED_VALUE"""),"5a032611") -> 5a032611 | D8: =IFERROR(__xludf.DUMMYFUNCTION("""COMPUTED_VALUE"""),"Harold Dou") -> Harold Dou | E8: =IFERROR(__xludf.DUMMYFUNCTION("""COMPUTED_VALUE"""),10.0) -> 10 | F8: =IFERROR(__xludf.DUMMYFUNCTION("""COMPUTED_VALUE"""),"HS202") -> HS202 | G8: =IFERROR(__xludf.DUMMYFUNCTION("""COMPUTED_VALUE"""),"Homeroom") -> Homeroom | H8: =IFERROR(__xludf.DUMMYFUNCTION("""COMPUTED_VALUE"""),"Present") -> Present | I8: =IFERROR(__xludf.DUMMYFUNCTION("""COMPUTED_VALUE"""),0.35587962962962966) -> 0.35587963 | J8: =IFERROR(__xludf.DUMMYFUNCTION("""COMPUTED_VALUE"""),1.0) -> 1 | K8: =IFERROR(__xludf.DUMMYFUNCTION("""COMPUTED_VALUE"""),10.0) -> 10 | L8: =IFERROR(__xludf.DUMMYFUNCTION("""COMPUTED_VALUE"""),"On-time reward applied") -> On-time reward applied | M8: =IFERROR(__xludf.DUMMYFUNCTION("""COMPUTED_VALUE"""),"Success") -> Success
A9: =IFERROR(__xludf.DUMMYFUNCTION("""COMPUTED_VALUE"""),46163.35612268518) -> 46163.356 | B9: =IFERROR(__xludf.DUMMYFUNCTION("""COMPUTED_VALUE"""),46163.0) -> 46163 | C9: =IFERROR(__xludf.DUMMYFUNCTION("""COMPUTED_VALUE"""),"7c4e261e") -> 7c4e261e | D9: =IFERROR(__xludf.DUMMYFUNCTION("""COMPUTED_VALUE"""),"Suha Lee") -> Suha Lee | E9: =IFERROR(__xludf.DUMMYFUNCTION("""COMPUTED_VALUE"""),10.0) -> 10 | F9: =IFERROR(__xludf.DUMMYFUNCTION("""COMPUTED_VALUE"""),"HS203") -> HS203 | G9: =IFERROR(__xludf.DUMMYFUNCTION("""COMPUTED_VALUE"""),"Homeroom") -> Homeroom | H9: =IFERROR(__xludf.DUMMYFUNCTION("""COMPUTED_VALUE"""),"Present") -> Present | I9: =IFERROR(__xludf.DUMMYFUNCTION("""COMPUTED_VALUE"""),0.3975462962962963) -> 0.3975463 | J9: =IFERROR(__xludf.DUMMYFUNCTION("""COMPUTED_VALUE"""),1.0) -> 1 | K9: =IFERROR(__xludf.DUMMYFUNCTION("""COMPUTED_VALUE"""),10.0) -> 10 | L9: =IFERROR(__xludf.DUMMYFUNCTION("""COMPUTED_VALUE"""),"On-time reward applied") -> On-time reward applied | M9: =IFERROR(__xludf.DUMMYFUNCTION("""COMPUTED_VALUE"""),"Success") -> Success
A10: =IFERROR(__xludf.DUMMYFUNCTION("""COMPUTED_VALUE"""),46163.35622685185) -> 46163.356 | B10: =IFERROR(__xludf.DUMMYFUNCTION("""COMPUTED_VALUE"""),46163.0) -> 46163 | C10: =IFERROR(__xludf.DUMMYFUNCTION("""COMPUTED_VALUE"""),"ba353911") -> ba353911 | D10: =IFERROR(__xludf.DUMMYFUNCTION("""COMPUTED_VALUE"""),"Dayeon Kang") -> Dayeon Kang | E10: =IFERROR(__xludf.DUMMYFUNCTION("""COMPUTED_VALUE"""),10.0) -> 10 | F10: =IFERROR(__xludf.DUMMYFUNCTION("""COMPUTED_VALUE"""),"HS202") -> HS202 | G10: =IFERROR(__xludf.DUMMYFUNCTION("""COMPUTED_VALUE"""),"Homeroom") -> Homeroom | H10: =IFERROR(__xludf.DUMMYFUNCTION("""COMPUTED_VALUE"""),"Present") -> Present | I10: =IFERROR(__xludf.DUMMYFUNCTION("""COMPUTED_VALUE"""),0.3562268518518519) -> 0.35622685 | J10: =IFERROR(__xludf.DUMMYFUNCTION("""COMPUTED_VALUE"""),1.0) -> 1 | K10: =IFERROR(__xludf.DUMMYFUNCTION("""COMPUTED_VALUE"""),10.0) -> 10 | L10: =IFERROR(__xludf.DUMMYFUNCTION("""COMPUTED_VALUE"""),"On-time reward applied") -> On-time reward applied | M10: =IFERROR(__xludf.DUMMYFUNCTION("""COMPUTED_VALUE"""),"Success") -> Success
A11: =IFERROR(__xludf.DUMMYFUNCTION("""COMPUTED_VALUE"""),46163.35988425926) -> 46163.36 | B11: =IFERROR(__xludf.DUMMYFUNCTION("""COMPUTED_VALUE"""),46163.0) -> 46163 | C11: =IFERROR(__xludf.DUMMYFUNCTION("""COMPUTED_VALUE"""),"7c4e261e") -> 7c4e261e | D11: =IFERROR(__xludf.DUMMYFUNCTION("""COMPUTED_VALUE"""),"Suha Lee") -> Suha Lee | E11: =IFERROR(__xludf.DUMMYFUNCTION("""COMPUTED_VALUE"""),10.0) -> 10 | F11: =IFERROR(__xludf.DUMMYFUNCTION("""COMPUTED_VALUE"""),"HS202") -> HS202 | G11: =IFERROR(__xludf.DUMMYFUNCTION("""COMPUTED_VALUE"""),"Homeroom") -> Homeroom | H11: =IFERROR(__xludf.DUMMYFUNCTION("""COMPUTED_VALUE"""),"Duplicate") -> Duplicate | I11: =IFERROR(__xludf.DUMMYFUNCTION("""COMPUTED_VALUE"""),0.35988425925925926) -> 0.35988426 | K11: =IFERROR(__xludf.DUMMYFUNCTION("""COMPUTED_VALUE"""),0.0) -> 0 | L11: =IFERROR(__xludf.DUMMYFUNCTION("""COMPUTED_VALUE"""),"Duplicate scan") -> Duplicate scan | M11: =IFERROR(__xludf.DUMMYFUNCTION("""COMPUTED_VALUE"""),"Denied - duplicate attendance") -> Denied - duplicate attendance
A12: =IFERROR(__xludf.DUMMYFUNCTION("""COMPUTED_VALUE"""),46163.36289351852) -> 46163.363 | B12: =IFERROR(__xludf.DUMMYFUNCTION("""COMPUTED_VALUE"""),46163.0) -> 46163 | C12: =IFERROR(__xludf.DUMMYFUNCTION("""COMPUTED_VALUE"""),"1e3e1410") -> 1e3e1410 | D12: =IFERROR(__xludf.DUMMYFUNCTION("""COMPUTED_VALUE"""),"Junjae Park") -> Junjae Park | E12: =IFERROR(__xludf.DUMMYFUNCTION("""COMPUTED_VALUE"""),10.0) -> 10 | F12: =IFERROR(__xludf.DUMMYFUNCTION("""COMPUTED_VALUE"""),"HS202") -> HS202 | G12: =IFERROR(__xludf.DUMMYFUNCTION("""COMPUTED_VALUE"""),"Homeroom") -> Homeroom | H12: =IFERROR(__xludf.DUMMYFUNCTION("""COMPUTED_VALUE"""),"Late") -> Late | I12: =IFERROR(__xludf.DUMMYFUNCTION("""COMPUTED_VALUE"""),0.36289351851851853) -> 0.36289352 | J12: =IFERROR(__xludf.DUMMYFUNCTION("""COMPUTED_VALUE"""),0.0) -> 0 | K12: =IFERROR(__xludf.DUMMYFUNCTION("""COMPUTED_VALUE"""),0.0) -> 0 | L12: =IFERROR(__xludf.DUMMYFUNCTION("""COMPUTED_VALUE"""),"Late scan") -> Late scan | M12: =IFERROR(__xludf.DUMMYFUNCTION("""COMPUTED_VALUE"""),"Success") -> Success
A13: =IFERROR(__xludf.DUMMYFUNCTION("""COMPUTED_VALUE"""),46163.36681712963) -> 46163.367 | B13: =IFERROR(__xludf.DUMMYFUNCTION("""COMPUTED_VALUE"""),46163.0) -> 46163 | C13: =IFERROR(__xludf.DUMMYFUNCTION("""COMPUTED_VALUE"""),"9a5f2811") -> 9a5f2811 | D13: =IFERROR(__xludf.DUMMYFUNCTION("""COMPUTED_VALUE"""),"Junyoung Yoo") -> Junyoung Yoo | E13: =IFERROR(__xludf.DUMMYFUNCTION("""COMPUTED_VALUE"""),10.0) -> 10 | F13: =IFERROR(__xludf.DUMMYFUNCTION("""COMPUTED_VALUE"""),"HS202") -> HS202 | G13: =IFERROR(__xludf.DUMMYFUNCTION("""COMPUTED_VALUE"""),"Homeroom") -> Homeroom | H13: =IFERROR(__xludf.DUMMYFUNCTION("""COMPUTED_VALUE"""),"Late") -> Late | I13: =IFERROR(__xludf.DUMMYFUNCTION("""COMPUTED_VALUE"""),0.36681712962962965) -> 0.36681713 | J13: =IFERROR(__xludf.DUMMYFUNCTION("""COMPUTED_VALUE"""),0.0) -> 0 | K13: =IFERROR(__xludf.DUMMYFUNCTION("""COMPUTED_VALUE"""),0.0) -> 0 | L13: =IFERROR(__xludf.DUMMYFUNCTION("""COMPUTED_VALUE"""),"Late penalty not applied: insufficient balance") -> Late penalty not applied: insufficient balance | M13: =IFERROR(__xludf.DUMMYFUNCTION("""COMPUTED_VALUE"""),"Success") -> Success
A14: =IFERROR(__xludf.DUMMYFUNCTION("""COMPUTED_VALUE"""),46164.34453703704) -> 46164.345 | B14: =IFERROR(__xludf.DUMMYFUNCTION("""COMPUTED_VALUE"""),46164.0) -> 46164 | C14: =IFERROR(__xludf.DUMMYFUNCTION("""COMPUTED_VALUE"""),"5c07fef4") -> 5c07fef4 | D14: =IFERROR(__xludf.DUMMYFUNCTION("""COMPUTED_VALUE"""),"Tiffany Kim") -> Tiffany Kim | E14: =IFERROR(__xludf.DUMMYFUNCTION("""COMPUTED_VALUE"""),10.0) -> 10 | F14: =IFERROR(__xludf.DUMMYFUNCTION("""COMPUTED_VALUE"""),"HS202") -> HS202 | G14: =IFERROR(__xludf.DUMMYFUNCTION("""COMPUTED_VALUE"""),"Homeroom") -> Homeroom | H14: =IFERROR(__xludf.DUMMYFUNCTION("""COMPUTED_VALUE"""),"Present") -> Present | I14: =IFERROR(__xludf.DUMMYFUNCTION("""COMPUTED_VALUE"""),0.34453703703703703) -> 0.34453704 | J14: =IFERROR(__xludf.DUMMYFUNCTION("""COMPUTED_VALUE"""),2.0) -> 2 | K14: =IFERROR(__xludf.DUMMYFUNCTION("""COMPUTED_VALUE"""),10.0) -> 10 | L14: =IFERROR(__xludf.DUMMYFUNCTION("""COMPUTED_VALUE"""),"On-time reward applied") -> On-time reward applied | M14: =IFERROR(__xludf.DUMMYFUNCTION("""COMPUTED_VALUE"""),"Success") -> Success
A15: =IFERROR(__xludf.DUMMYFUNCTION("""COMPUTED_VALUE"""),46164.35334490741) -> 46164.353 | B15: =IFERROR(__xludf.DUMMYFUNCTION("""COMPUTED_VALUE"""),46164.0) -> 46164 | C15: =IFERROR(__xludf.DUMMYFUNCTION("""COMPUTED_VALUE"""),"dc04eef4") -> dc04eef4 | D15: =IFERROR(__xludf.DUMMYFUNCTION("""COMPUTED_VALUE"""),"Joshua Jung") -> Joshua Jung | E15: =IFERROR(__xludf.DUMMYFUNCTION("""COMPUTED_VALUE"""),10.0) -> 10 | F15: =IFERROR(__xludf.DUMMYFUNCTION("""COMPUTED_VALUE"""),"HS202") -> HS202 | G15: =IFERROR(__xludf.DUMMYFUNCTION("""COMPUTED_VALUE"""),"Homeroom") -> Homeroom | H15: =IFERROR(__xludf.DUMMYFUNCTION("""COMPUTED_VALUE"""),"Present") -> Present | I15: =IFERROR(__xludf.DUMMYFUNCTION("""COMPUTED_VALUE"""),0.3533449074074074) -> 0.35334491 | J15: =IFERROR(__xludf.DUMMYFUNCTION("""COMPUTED_VALUE"""),2.0) -> 2 | K15: =IFERROR(__xludf.DUMMYFUNCTION("""COMPUTED_VALUE"""),10.0) -> 10 | L15: =IFERROR(__xludf.DUMMYFUNCTION("""COMPUTED_VALUE"""),"On-time reward applied") -> On-time reward applied | M15: =IFERROR(__xludf.DUMMYFUNCTION("""COMPUTED_VALUE"""),"Success") -> Success
A16: =IFERROR(__xludf.DUMMYFUNCTION("""COMPUTED_VALUE"""),46164.353483796294) -> 46164.353 | B16: =IFERROR(__xludf.DUMMYFUNCTION("""COMPUTED_VALUE"""),46164.0) -> 46164 | C16: =IFERROR(__xludf.DUMMYFUNCTION("""COMPUTED_VALUE"""),"ba912211") -> ba912211 | D16: =IFERROR(__xludf.DUMMYFUNCTION("""COMPUTED_VALUE"""),"Daisy Dou") -> Daisy Dou | E16: =IFERROR(__xludf.DUMMYFUNCTION("""COMPUTED_VALUE"""),10.0) -> 10 | F16: =IFERROR(__xludf.DUMMYFUNCTION("""COMPUTED_VALUE"""),"HS202") -> HS202 | G16: =IFERROR(__xludf.DUMMYFUNCTION("""COMPUTED_VALUE"""),"Homeroom") -> Homeroom | H16: =IFERROR(__xludf.DUMMYFUNCTION("""COMPUTED_VALUE"""),"Present") -> Present | I16: =IFERROR(__xludf.DUMMYFUNCTION("""COMPUTED_VALUE"""),0.3534837962962963) -> 0.3534838 | J16: =IFERROR(__xludf.DUMMYFUNCTION("""COMPUTED_VALUE"""),2.0) -> 2 | K16: =IFERROR(__xludf.DUMMYFUNCTION("""COMPUTED_VALUE"""),10.0) -> 10 | L16: =IFERROR(__xludf.DUMMYFUNCTION("""COMPUTED_VALUE"""),"On-time reward applied") -> On-time reward applied | M16: =IFERROR(__xludf.DUMMYFUNCTION("""COMPUTED_VALUE"""),"Success") -> Success
A17: =IFERROR(__xludf.DUMMYFUNCTION("""COMPUTED_VALUE"""),46164.35361111111) -> 46164.354 | B17: =IFERROR(__xludf.DUMMYFUNCTION("""COMPUTED_VALUE"""),46164.0) -> 46164 | C17: =IFERROR(__xludf.DUMMYFUNCTION("""COMPUTED_VALUE"""),"babde4c4") -> babde4c4 | D17: =IFERROR(__xludf.DUMMYFUNCTION("""COMPUTED_VALUE"""),"Ashley Guk") -> Ashley Guk | E17: =IFERROR(__xludf.DUMMYFUNCTION("""COMPUTED_VALUE"""),10.0) -> 10 | F17: =IFERROR(__xludf.DUMMYFUNCTION("""COMPUTED_VALUE"""),"HS202") -> HS202 | G17: =IFERROR(__xludf.DUMMYFUNCTION("""COMPUTED_VALUE"""),"Homeroom") -> Homeroom | H17: =IFERROR(__xludf.DUMMYFUNCTION("""COMPUTED_VALUE"""),"Present") -> Present | I17: =IFERROR(__xludf.DUMMYFUNCTION("""COMPUTED_VALUE"""),0.3536111111111111) -> 0.35361111 | J17: =IFERROR(__xludf.DUMMYFUNCTION("""COMPUTED_VALUE"""),2.0) -> 2 | K17: =IFERROR(__xludf.DUMMYFUNCTION("""COMPUTED_VALUE"""),10.0) -> 10 | L17: =IFERROR(__xludf.DUMMYFUNCTION("""COMPUTED_VALUE"""),"On-time reward applied") -> On-time reward applied | M17: =IFERROR(__xludf.DUMMYFUNCTION("""COMPUTED_VALUE"""),"Success") -> Success
A18: =IFERROR(__xludf.DUMMYFUNCTION("""COMPUTED_VALUE"""),46164.35439814815) -> 46164.354 | B18: =IFERROR(__xludf.DUMMYFUNCTION("""COMPUTED_VALUE"""),46164.0) -> 46164 | C18: =IFERROR(__xludf.DUMMYFUNCTION("""COMPUTED_VALUE"""),"7c4e261e") -> 7c4e261e | D18: =IFERROR(__xludf.DUMMYFUNCTION("""COMPUTED_VALUE"""),"Suha Lee") -> Suha Lee | E18: =IFERROR(__xludf.DUMMYFUNCTION("""COMPUTED_VALUE"""),10.0) -> 10 | F18: =IFERROR(__xludf.DUMMYFUNCTION("""COMPUTED_VALUE"""),"HS202") -> HS202 | G18: =IFERROR(__xludf.DUMMYFUNCTION("""COMPUTED_VALUE"""),"Homeroom") -> Homeroom | H18: =IFERROR(__xludf.DUMMYFUNCTION("""COMPUTED_VALUE"""),"Present") -> Present | I18: =IFERROR(__xludf.DUMMYFUNCTION("""COMPUTED_VALUE"""),0.35439814814814813) -> 0.35439815 | J18: =IFERROR(__xludf.DUMMYFUNCTION("""COMPUTED_VALUE"""),2.0) -> 2 | K18: =IFERROR(__xludf.DUMMYFUNCTION("""COMPUTED_VALUE"""),10.0) -> 10 | L18: =IFERROR(__xludf.DUMMYFUNCTION("""COMPUTED_VALUE"""),"On-time reward applied") -> On-time reward applied | M18: =IFERROR(__xludf.DUMMYFUNCTION("""COMPUTED_VALUE"""),"Success") -> Success
A19: =IFERROR(__xludf.DUMMYFUNCTION("""COMPUTED_VALUE"""),46164.35686342593) -> 46164.357 | B19: =IFERROR(__xludf.DUMMYFUNCTION("""COMPUTED_VALUE"""),46164.0) -> 46164 | C19: =IFERROR(__xludf.DUMMYFUNCTION("""COMPUTED_VALUE"""),"ba353911") -> ba353911 | D19: =IFERROR(__xludf.DUMMYFUNCTION("""COMPUTED_VALUE"""),"Dayeon Kang") -> Dayeon Kang | E19: =IFERROR(__xludf.DUMMYFUNCTION("""COMPUTED_VALUE"""),10.0) -> 10 | F19: =IFERROR(__xludf.DUMMYFUNCTION("""COMPUTED_VALUE"""),"HS202") -> HS202 | G19: =IFERROR(__xludf.DUMMYFUNCTION("""COMPUTED_VALUE"""),"Homeroom") -> Homeroom | H19: =IFERROR(__xludf.DUMMYFUNCTION("""COMPUTED_VALUE"""),"Present") -> Present | I19: =IFERROR(__xludf.DUMMYFUNCTION("""COMPUTED_VALUE"""),0.3568634259259259) -> 0.35686343 | J19: =IFERROR(__xludf.DUMMYFUNCTION("""COMPUTED_VALUE"""),2.0) -> 2 | K19: =IFERROR(__xludf.DUMMYFUNCTION("""COMPUTED_VALUE"""),10.0) -> 10 | L19: =IFERROR(__xludf.DUMMYFUNCTION("""COMPUTED_VALUE"""),"On-time reward applied") -> On-time reward applied | M19: =IFERROR(__xludf.DUMMYFUNCTION("""COMPUTED_VALUE"""),"Success") -> Success
A20: =IFERROR(__xludf.DUMMYFUNCTION("""COMPUTED_VALUE"""),46164.35702546296) -> 46164.357 | B20: =IFERROR(__xludf.DUMMYFUNCTION("""COMPUTED_VALUE"""),46164.0) -> 46164 | C20: =IFERROR(__xludf.DUMMYFUNCTION("""COMPUTED_VALUE"""),"5a032611") -> 5a032611 | D20: =IFERROR(__xludf.DUMMYFUNCTION("""COMPUTED_VALUE"""),"Harold Dou") -> Harold Dou | E20: =IFERROR(__xludf.DUMMYFUNCTION("""COMPUTED_VALUE"""),10.0) -> 10 | F20: =IFERROR(__xludf.DUMMYFUNCTION("""COMPUTED_VALUE"""),"HS202") -> HS202 | G20: =IFERROR(__xludf.DUMMYFUNCTION("""COMPUTED_VALUE"""),"Homeroom") -> Homeroom | H20: =IFERROR(__xludf.DUMMYFUNCTION("""COMPUTED_VALUE"""),"Present") -> Present | I20: =IFERROR(__xludf.DUMMYFUNCTION("""COMPUTED_VALUE"""),0.35702546296296295) -> 0.35702546 | J20: =IFERROR(__xludf.DUMMYFUNCTION("""COMPUTED_VALUE"""),2.0) -> 2 | K20: =IFERROR(__xludf.DUMMYFUNCTION("""COMPUTED_VALUE"""),10.0) -> 10 | L20: =IFERROR(__xludf.DUMMYFUNCTION("""COMPUTED_VALUE"""),"On-time reward applied") -> On-time reward applied | M20: =IFERROR(__xludf.DUMMYFUNCTION("""COMPUTED_VALUE"""),"Success") -> Success
A21: =IFERROR(__xludf.DUMMYFUNCTION("""COMPUTED_VALUE"""),46164.357152777775) -> 46164.357 | B21: =IFERROR(__xludf.DUMMYFUNCTION("""COMPUTED_VALUE"""),46164.0) -> 46164 | C21: =IFERROR(__xludf.DUMMYFUNCTION("""COMPUTED_VALUE"""),"9a5f2811") -> 9a5f2811 | D21: =IFERROR(__xludf.DUMMYFUNCTION("""COMPUTED_VALUE"""),"Junyoung Yoo") -> Junyoung Yoo | E21: =IFERROR(__xludf.DUMMYFUNCTION("""COMPUTED_VALUE"""),10.0) -> 10 | F21: =IFERROR(__xludf.DUMMYFUNCTION("""COMPUTED_VALUE"""),"HS202") -> HS202 | G21: =IFERROR(__xludf.DUMMYFUNCTION("""COMPUTED_VALUE"""),"Homeroom") -> Homeroom | H21: =IFERROR(__xludf.DUMMYFUNCTION("""COMPUTED_VALUE"""),"Present") -> Present | I21: =IFERROR(__xludf.DUMMYFUNCTION("""COMPUTED_VALUE"""),0.35715277777777776) -> 0.35715278 | J21: =IFERROR(__xludf.DUMMYFUNCTION("""COMPUTED_VALUE"""),1.0) -> 1 | K21: =IFERROR(__xludf.DUMMYFUNCTION("""COMPUTED_VALUE"""),10.0) -> 10 | L21: =IFERROR(__xludf.DUMMYFUNCTION("""COMPUTED_VALUE"""),"On-time reward applied") -> On-time reward applied | M21: =IFERROR(__xludf.DUMMYFUNCTION("""COMPUTED_VALUE"""),"Success") -> Success
A22: =IFERROR(__xludf.DUMMYFUNCTION("""COMPUTED_VALUE"""),46168.33902777778) -> 46168.339 | B22: =IFERROR(__xludf.DUMMYFUNCTION("""COMPUTED_VALUE"""),46168.0) -> 46168 | C22: =IFERROR(__xludf.DUMMYFUNCTION("""COMPUTED_VALUE"""),"dc04eef4") -> dc04eef4 | D22: =IFERROR(__xludf.DUMMYFUNCTION("""COMPUTED_VALUE"""),"Joshua Jung") -> Joshua Jung | E22: =IFERROR(__xludf.DUMMYFUNCTION("""COMPUTED_VALUE"""),10.0) -> 10 | F22: =IFERROR(__xludf.DUMMYFUNCTION("""COMPUTED_VALUE"""),"HS202") -> HS202 | G22: =IFERROR(__xludf.DUMMYFUNCTION("""COMPUTED_VALUE"""),"Homeroom") -> Homeroom | H22: =IFERROR(__xludf.DUMMYFUNCTION("""COMPUTED_VALUE"""),"Present") -> Present | I22: =IFERROR(__xludf.DUMMYFUNCTION("""COMPUTED_VALUE"""),0.33902777777777776) -> 0.33902778 | J22: =IFERROR(__xludf.DUMMYFUNCTION("""COMPUTED_VALUE"""),1.0) -> 1 | K22: =IFERROR(__xludf.DUMMYFUNCTION("""COMPUTED_VALUE"""),10.0) -> 10 | L22: =IFERROR(__xludf.DUMMYFUNCTION("""COMPUTED_VALUE"""),"On-time reward applied") -> On-time reward applied | M22: =IFERROR(__xludf.DUMMYFUNCTION("""COMPUTED_VALUE"""),"Success") -> Success
A23: =IFERROR(__xludf.DUMMYFUNCTION("""COMPUTED_VALUE"""),46168.35086805555) -> 46168.351 | B23: =IFERROR(__xludf.DUMMYFUNCTION("""COMPUTED_VALUE"""),46168.0) -> 46168 | C23: =IFERROR(__xludf.DUMMYFUNCTION("""COMPUTED_VALUE"""),"5c07fef4") -> 5c07fef4 | D23: =IFERROR(__xludf.DUMMYFUNCTION("""COMPUTED_VALUE"""),"Tiffany Kim") -> Tiffany Kim | E23: =IFERROR(__xludf.DUMMYFUNCTION("""COMPUTED_VALUE"""),10.0) -> 10 | F23: =IFERROR(__xludf.DUMMYFUNCTION("""COMPUTED_VALUE"""),"HS202") -> HS202 | G23: =IFERROR(__xludf.DUMMYFUNCTION("""COMPUTED_VALUE"""),"Homeroom") -> Homeroom | H23: =IFERROR(__xludf.DUMMYFUNCTION("""COMPUTED_VALUE"""),"Present") -> Present | I23: =IFERROR(__xludf.DUMMYFUNCTION("""COMPUTED_VALUE"""),0.35086805555555556) -> 0.35086806 | J23: =IFERROR(__xludf.DUMMYFUNCTION("""COMPUTED_VALUE"""),1.0) -> 1 | K23: =IFERROR(__xludf.DUMMYFUNCTION("""COMPUTED_VALUE"""),10.0) -> 10 | L23: =IFERROR(__xludf.DUMMYFUNCTION("""COMPUTED_VALUE"""),"On-time reward applied") -> On-time reward applied | M23: =IFERROR(__xludf.DUMMYFUNCTION("""COMPUTED_VALUE"""),"Success") -> Success
A24: =IFERROR(__xludf.DUMMYFUNCTION("""COMPUTED_VALUE"""),46168.35162037037) -> 46168.352 | B24: =IFERROR(__xludf.DUMMYFUNCTION("""COMPUTED_VALUE"""),46168.0) -> 46168 | C24: =IFERROR(__xludf.DUMMYFUNCTION("""COMPUTED_VALUE"""),"ba912211") -> ba912211 | D24: =IFERROR(__xludf.DUMMYFUNCTION("""COMPUTED_VALUE"""),"Daisy Dou") -> Daisy Dou | E24: =IFERROR(__xludf.DUMMYFUNCTION("""COMPUTED_VALUE"""),10.0) -> 10 | F24: =IFERROR(__xludf.DUMMYFUNCTION("""COMPUTED_VALUE"""),"HS202") -> HS202 | G24: =IFERROR(__xludf.DUMMYFUNCTION("""COMPUTED_VALUE"""),"Homeroom") -> Homeroom | H24: =IFERROR(__xludf.DUMMYFUNCTION("""COMPUTED_VALUE"""),"Present") -> Present | I24: =IFERROR(__xludf.DUMMYFUNCTION("""COMPUTED_VALUE"""),0.35162037037037036) -> 0.35162037 | J24: =IFERROR(__xludf.DUMMYFUNCTION("""COMPUTED_VALUE"""),1.0) -> 1 | K24: =IFERROR(__xludf.DUMMYFUNCTION("""COMPUTED_VALUE"""),10.0) -> 10 | L24: =IFERROR(__xludf.DUMMYFUNCTION("""COMPUTED_VALUE"""),"On-time reward applied") -> On-time reward applied | M24: =IFERROR(__xludf.DUMMYFUNCTION("""COMPUTED_VALUE"""),"Success") -> Success
A25: =IFERROR(__xludf.DUMMYFUNCTION("""COMPUTED_VALUE"""),46168.35445601852) -> 46168.354 | B25: =IFERROR(__xludf.DUMMYFUNCTION("""COMPUTED_VALUE"""),46168.0) -> 46168 | C25: =IFERROR(__xludf.DUMMYFUNCTION("""COMPUTED_VALUE"""),"7c4e261e") -> 7c4e261e | D25: =IFERROR(__xludf.DUMMYFUNCTION("""COMPUTED_VALUE"""),"Suha Lee") -> Suha Lee | E25: =IFERROR(__xludf.DUMMYFUNCTION("""COMPUTED_VALUE"""),10.0) -> 10 | F25: =IFERROR(__xludf.DUMMYFUNCTION("""COMPUTED_VALUE"""),"HS202") -> HS202 | G25: =IFERROR(__xludf.DUMMYFUNCTION("""COMPUTED_VALUE"""),"Homeroom") -> Homeroom | H25: =IFERROR(__xludf.DUMMYFUNCTION("""COMPUTED_VALUE"""),"Present") -> Present | I25: =IFERROR(__xludf.DUMMYFUNCTION("""COMPUTED_VALUE"""),0.35445601851851855) -> 0.35445602 | J25: =IFERROR(__xludf.DUMMYFUNCTION("""COMPUTED_VALUE"""),1.0) -> 1 | K25: =IFERROR(__xludf.DUMMYFUNCTION("""COMPUTED_VALUE"""),10.0) -> 10 | L25: =IFERROR(__xludf.DUMMYFUNCTION("""COMPUTED_VALUE"""),"On-time reward applied") -> On-time reward applied | M25: =IFERROR(__xludf.DUMMYFUNCTION("""COMPUTED_VALUE"""),"Success") -> Success
A26: =IFERROR(__xludf.DUMMYFUNCTION("""COMPUTED_VALUE"""),46168.35590277778) -> 46168.356 | B26: =IFERROR(__xludf.DUMMYFUNCTION("""COMPUTED_VALUE"""),46168.0) -> 46168 | C26: =IFERROR(__xludf.DUMMYFUNCTION("""COMPUTED_VALUE"""),"5a032611") -> 5a032611 | D26: =IFERROR(__xludf.DUMMYFUNCTION("""COMPUTED_VALUE"""),"Harold Dou") -> Harold Dou | E26: =IFERROR(__xludf.DUMMYFUNCTION("""COMPUTED_VALUE"""),10.0) -> 10 | F26: =IFERROR(__xludf.DUMMYFUNCTION("""COMPUTED_VALUE"""),"HS202") -> HS202 | G26: =IFERROR(__xludf.DUMMYFUNCTION("""COMPUTED_VALUE"""),"Homeroom") -> Homeroom | H26: =IFERROR(__xludf.DUMMYFUNCTION("""COMPUTED_VALUE"""),"Present") -> Present | I26: =IFERROR(__xludf.DUMMYFUNCTION("""COMPUTED_VALUE"""),0.3559027777777778) -> 0.35590278 | J26: =IFERROR(__xludf.DUMMYFUNCTION("""COMPUTED_VALUE"""),1.0) -> 1 | K26: =IFERROR(__xludf.DUMMYFUNCTION("""COMPUTED_VALUE"""),10.0) -> 10 | L26: =IFERROR(__xludf.DUMMYFUNCTION("""COMPUTED_VALUE"""),"On-time reward applied") -> On-time reward applied | M26: =IFERROR(__xludf.DUMMYFUNCTION("""COMPUTED_VALUE"""),"Success") -> Success
A27: =IFERROR(__xludf.DUMMYFUNCTION("""COMPUTED_VALUE"""),46168.356261574074) -> 46168.356 | B27: =IFERROR(__xludf.DUMMYFUNCTION("""COMPUTED_VALUE"""),46168.0) -> 46168 | C27: =IFERROR(__xludf.DUMMYFUNCTION("""COMPUTED_VALUE"""),"9a5f2811") -> 9a5f2811 | D27: =IFERROR(__xludf.DUMMYFUNCTION("""COMPUTED_VALUE"""),"Junyoung Yoo") -> Junyoung Yoo | E27: =IFERROR(__xludf.DUMMYFUNCTION("""COMPUTED_VALUE"""),10.0) -> 10 | F27: =IFERROR(__xludf.DUMMYFUNCTION("""COMPUTED_VALUE"""),"HS202") -> HS202 | G27: =IFERROR(__xludf.DUMMYFUNCTION("""COMPUTED_VALUE"""),"Homeroom") -> Homeroom | H27: =IFERROR(__xludf.DUMMYFUNCTION("""COMPUTED_VALUE"""),"Present") -> Present | I27: =IFERROR(__xludf.DUMMYFUNCTION("""COMPUTED_VALUE"""),0.35626157407407405) -> 0.35626157 | J27: =IFERROR(__xludf.DUMMYFUNCTION("""COMPUTED_VALUE"""),1.0) -> 1 | K27: =IFERROR(__xludf.DUMMYFUNCTION("""COMPUTED_VALUE"""),10.0) -> 10 | L27: =IFERROR(__xludf.DUMMYFUNCTION("""COMPUTED_VALUE"""),"On-time reward applied") -> On-time reward applied | M27: =IFERROR(__xludf.DUMMYFUNCTION("""COMPUTED_VALUE"""),"Success") -> Success
A28: =IFERROR(__xludf.DUMMYFUNCTION("""COMPUTED_VALUE"""),46168.35865740741) -> 46168.359 | B28: =IFERROR(__xludf.DUMMYFUNCTION("""COMPUTED_VALUE"""),46168.0) -> 46168 | C28: =IFERROR(__xludf.DUMMYFUNCTION("""COMPUTED_VALUE"""),"ba353911") -> ba353911 | D28: =IFERROR(__xludf.DUMMYFUNCTION("""COMPUTED_VALUE"""),"Dayeon Kang") -> Dayeon Kang | E28: =IFERROR(__xludf.DUMMYFUNCTION("""COMPUTED_VALUE"""),10.0) -> 10 | F28: =IFERROR(__xludf.DUMMYFUNCTION("""COMPUTED_VALUE"""),"HS202") -> HS202 | G28: =IFERROR(__xludf.DUMMYFUNCTION("""COMPUTED_VALUE"""),"Homeroom") -> Homeroom | H28: =IFERROR(__xludf.DUMMYFUNCTION("""COMPUTED_VALUE"""),"Late") -> Late | I28: =IFERROR(__xludf.DUMMYFUNCTION("""COMPUTED_VALUE"""),0.3586574074074074) -> 0.35865741 | J28: =IFERROR(__xludf.DUMMYFUNCTION("""COMPUTED_VALUE"""),0.0) -> 0 | K28: =IFERROR(__xludf.DUMMYFUNCTION("""COMPUTED_VALUE"""),0.0) -> 0 | L28: =IFERROR(__xludf.DUMMYFUNCTION("""COMPUTED_VALUE"""),"Late penalty applied") -> Late penalty applied | M28: =IFERROR(__xludf.DUMMYFUNCTION("""COMPUTED_VALUE"""),"Success") -> Success
A29: =IFERROR(__xludf.DUMMYFUNCTION("""COMPUTED_VALUE"""),46168.49429398148) -> 46168.494 | B29: =IFERROR(__xludf.DUMMYFUNCTION("""COMPUTED_VALUE"""),46168.0) -> 46168 | C29: =IFERROR(__xludf.DUMMYFUNCTION("""COMPUTED_VALUE"""),"ae072910") -> ae072910 | D29: =IFERROR(__xludf.DUMMYFUNCTION("""COMPUTED_VALUE"""),"Selena Jung") -> Selena Jung | E29: =IFERROR(__xludf.DUMMYFUNCTION("""COMPUTED_VALUE"""),10.0) -> 10 | F29: =IFERROR(__xludf.DUMMYFUNCTION("""COMPUTED_VALUE"""),"HS202") -> HS202 | G29: =IFERROR(__xludf.DUMMYFUNCTION("""COMPUTED_VALUE"""),"Homeroom") -> Homeroom | H29: =IFERROR(__xludf.DUMMYFUNCTION("""COMPUTED_VALUE"""),"Late") -> Late | I29: =IFERROR(__xludf.DUMMYFUNCTION("""COMPUTED_VALUE"""),0.49429398148148146) -> 0.49429398 | J29: =IFERROR(__xludf.DUMMYFUNCTION("""COMPUTED_VALUE"""),0.0) -> 0 | K29: =IFERROR(__xludf.DUMMYFUNCTION("""COMPUTED_VALUE"""),0.0) -> 0 | L29: =IFERROR(__xludf.DUMMYFUNCTION("""COMPUTED_VALUE"""),"Late penalty not applied: insufficient balance") -> Late penalty not applied: insufficient balance | M29: =IFERROR(__xludf.DUMMYFUNCTION("""COMPUTED_VALUE"""),"Success") -> Success
A30: =IFERROR(__xludf.DUMMYFUNCTION("""COMPUTED_VALUE"""),46168.65002314815) -> 46168.65 | B30: =IFERROR(__xludf.DUMMYFUNCTION("""COMPUTED_VALUE"""),46168.0) -> 46168 | C30: =IFERROR(__xludf.DUMMYFUNCTION("""COMPUTED_VALUE"""),"ba0fc5c4") -> ba0fc5c4 | D30: =IFERROR(__xludf.DUMMYFUNCTION("""COMPUTED_VALUE"""),"Junwoo Kang") -> Junwoo Kang | E30: =IFERROR(__xludf.DUMMYFUNCTION("""COMPUTED_VALUE"""),10.0) -> 10 | F30: =IFERROR(__xludf.DUMMYFUNCTION("""COMPUTED_VALUE"""),"HS202") -> HS202 | G30: =IFERROR(__xludf.DUMMYFUNCTION("""COMPUTED_VALUE"""),"Homeroom") -> Homeroom | H30: =IFERROR(__xludf.DUMMYFUNCTION("""COMPUTED_VALUE"""),"Late") -> Late | I30: =IFERROR(__xludf.DUMMYFUNCTION("""COMPUTED_VALUE"""),0.6500231481481481) -> 0.65002315 | J30: =IFERROR(__xludf.DUMMYFUNCTION("""COMPUTED_VALUE"""),0.0) -> 0 | K30: =IFERROR(__xludf.DUMMYFUNCTION("""COMPUTED_VALUE"""),0.0) -> 0 | L30: =IFERROR(__xludf.DUMMYFUNCTION("""COMPUTED_VALUE"""),"Late penalty not applied: insufficient balance") -> Late penalty not applied: insufficient balance | M30: =IFERROR(__xludf.DUMMYFUNCTION("""COMPUTED_VALUE"""),"Success") -> Success
A31: =IFERROR(__xludf.DUMMYFUNCTION("""COMPUTED_VALUE"""),46169.37300925926) -> 46169.373 | B31: =IFERROR(__xludf.DUMMYFUNCTION("""COMPUTED_VALUE"""),46169.0) -> 46169 | C31: =IFERROR(__xludf.DUMMYFUNCTION("""COMPUTED_VALUE"""),"ba353911") -> ba353911 | D31: =IFERROR(__xludf.DUMMYFUNCTION("""COMPUTED_VALUE"""),"Dayeon Kang") -> Dayeon Kang | E31: =IFERROR(__xludf.DUMMYFUNCTION("""COMPUTED_VALUE"""),10.0) -> 10 | F31: =IFERROR(__xludf.DUMMYFUNCTION("""COMPUTED_VALUE"""),"HS202") -> HS202 | G31: =IFERROR(__xludf.DUMMYFUNCTION("""COMPUTED_VALUE"""),"Homeroom") -> Homeroom | H31: =IFERROR(__xludf.DUMMYFUNCTION("""COMPUTED_VALUE"""),"Duplicate") -> Duplicate | I31: =IFERROR(__xludf.DUMMYFUNCTION("""COMPUTED_VALUE"""),0.37300925925925926) -> 0.37300926 | K31: =IFERROR(__xludf.DUMMYFUNCTION("""COMPUTED_VALUE"""),0.0) -> 0 | L31: =IFERROR(__xludf.DUMMYFUNCTION("""COMPUTED_VALUE"""),"Duplicate scan") -> Duplicate scan | M31: =IFERROR(__xludf.DUMMYFUNCTION("""COMPUTED_VALUE"""),"Denied - duplicate attendance") -> Denied - duplicate attendance
A32: =IFERROR(__xludf.DUMMYFUNCTION("""COMPUTED_VALUE"""),46170.34717592593) -> 46170.347 | B32: =IFERROR(__xludf.DUMMYFUNCTION("""COMPUTED_VALUE"""),46170.0) -> 46170 | C32: =IFERROR(__xludf.DUMMYFUNCTION("""COMPUTED_VALUE"""),"ae072910") -> ae072910 | D32: =IFERROR(__xludf.DUMMYFUNCTION("""COMPUTED_VALUE"""),"Selena Jung") -> Selena Jung | E32: =IFERROR(__xludf.DUMMYFUNCTION("""COMPUTED_VALUE"""),10.0) -> 10 | F32: =IFERROR(__xludf.DUMMYFUNCTION("""COMPUTED_VALUE"""),"HS202") -> HS202 | G32: =IFERROR(__xludf.DUMMYFUNCTION("""COMPUTED_VALUE"""),"Homeroom") -> Homeroom | H32: =IFERROR(__xludf.DUMMYFUNCTION("""COMPUTED_VALUE"""),"Present") -> Present | I32: =IFERROR(__xludf.DUMMYFUNCTION("""COMPUTED_VALUE"""),0.34717592592592594) -> 0.34717593 | J32: =IFERROR(__xludf.DUMMYFUNCTION("""COMPUTED_VALUE"""),1.0) -> 1 | K32: =IFERROR(__xludf.DUMMYFUNCTION("""COMPUTED_VALUE"""),10.0) -> 10 | L32: =IFERROR(__xludf.DUMMYFUNCTION("""COMPUTED_VALUE"""),"On-time reward applied") -> On-time reward applied | M32: =IFERROR(__xludf.DUMMYFUNCTION("""COMPUTED_VALUE"""),"Success") -> Success
A33: =IFERROR(__xludf.DUMMYFUNCTION("""COMPUTED_VALUE"""),46170.35011574074) -> 46170.35 | B33: =IFERROR(__xludf.DUMMYFUNCTION("""COMPUTED_VALUE"""),46170.0) -> 46170 | C33: =IFERROR(__xludf.DUMMYFUNCTION("""COMPUTED_VALUE"""),"5c07fef4") -> 5c07fef4 | D33: =IFERROR(__xludf.DUMMYFUNCTION("""COMPUTED_VALUE"""),"Tiffany Kim") -> Tiffany Kim | E33: =IFERROR(__xludf.DUMMYFUNCTION("""COMPUTED_VALUE"""),10.0) -> 10 | F33: =IFERROR(__xludf.DUMMYFUNCTION("""COMPUTED_VALUE"""),"HS202") -> HS202 | G33: =IFERROR(__xludf.DUMMYFUNCTION("""COMPUTED_VALUE"""),"Homeroom") -> Homeroom | H33: =IFERROR(__xludf.DUMMYFUNCTION("""COMPUTED_VALUE"""),"Present") -> Present | I33: =IFERROR(__xludf.DUMMYFUNCTION("""COMPUTED_VALUE"""),0.35011574074074076) -> 0.35011574 | J33: =IFERROR(__xludf.DUMMYFUNCTION("""COMPUTED_VALUE"""),1.0) -> 1 | K33: =IFERROR(__xludf.DUMMYFUNCTION("""COMPUTED_VALUE"""),10.0) -> 10 | L33: =IFERROR(__xludf.DUMMYFUNCTION("""COMPUTED_VALUE"""),"On-time reward applied") -> On-time reward applied | M33: =IFERROR(__xludf.DUMMYFUNCTION("""COMPUTED_VALUE"""),"Success") -> Success
A34: =IFERROR(__xludf.DUMMYFUNCTION("""COMPUTED_VALUE"""),46170.35193287037) -> 46170.352 | B34: =IFERROR(__xludf.DUMMYFUNCTION("""COMPUTED_VALUE"""),46170.0) -> 46170 | C34: =IFERROR(__xludf.DUMMYFUNCTION("""COMPUTED_VALUE"""),"ba912211") -> ba912211 | D34: =IFERROR(__xludf.DUMMYFUNCTION("""COMPUTED_VALUE"""),"Daisy Dou") -> Daisy Dou | E34: =IFERROR(__xludf.DUMMYFUNCTION("""COMPUTED_VALUE"""),10.0) -> 10 | F34: =IFERROR(__xludf.DUMMYFUNCTION("""COMPUTED_VALUE"""),"HS202") -> HS202 | G34: =IFERROR(__xludf.DUMMYFUNCTION("""COMPUTED_VALUE"""),"Homeroom") -> Homeroom | H34: =IFERROR(__xludf.DUMMYFUNCTION("""COMPUTED_VALUE"""),"Present") -> Present | I34: =IFERROR(__xludf.DUMMYFUNCTION("""COMPUTED_VALUE"""),0.35193287037037035) -> 0.35193287 | J34: =IFERROR(__xludf.DUMMYFUNCTION("""COMPUTED_VALUE"""),1.0) -> 1 | K34: =IFERROR(__xludf.DUMMYFUNCTION("""COMPUTED_VALUE"""),10.0) -> 10 | L34: =IFERROR(__xludf.DUMMYFUNCTION("""COMPUTED_VALUE"""),"On-time reward applied") -> On-time reward applied | M34: =IFERROR(__xludf.DUMMYFUNCTION("""COMPUTED_VALUE"""),"Success") -> Success
A35: =IFERROR(__xludf.DUMMYFUNCTION("""COMPUTED_VALUE"""),46170.352118055554) -> 46170.352 | B35: =IFERROR(__xludf.DUMMYFUNCTION("""COMPUTED_VALUE"""),46170.0) -> 46170 | C35: =IFERROR(__xludf.DUMMYFUNCTION("""COMPUTED_VALUE"""),"7c4e261e") -> 7c4e261e | D35: =IFERROR(__xludf.DUMMYFUNCTION("""COMPUTED_VALUE"""),"Suha Lee") -> Suha Lee | E35: =IFERROR(__xludf.DUMMYFUNCTION("""COMPUTED_VALUE"""),10.0) -> 10 | F35: =IFERROR(__xludf.DUMMYFUNCTION("""COMPUTED_VALUE"""),"HS202") -> HS202 | G35: =IFERROR(__xludf.DUMMYFUNCTION("""COMPUTED_VALUE"""),"Homeroom") -> Homeroom | H35: =IFERROR(__xludf.DUMMYFUNCTION("""COMPUTED_VALUE"""),"Present") -> Present | I35: =IFERROR(__xludf.DUMMYFUNCTION("""COMPUTED_VALUE"""),0.35211805555555553) -> 0.35211806 | J35: =IFERROR(__xludf.DUMMYFUNCTION("""COMPUTED_VALUE"""),1.0) -> 1 | K35: =IFERROR(__xludf.DUMMYFUNCTION("""COMPUTED_VALUE"""),10.0) -> 10 | L35: =IFERROR(__xludf.DUMMYFUNCTION("""COMPUTED_VALUE"""),"On-time reward applied") -> On-time reward applied | M35: =IFERROR(__xludf.DUMMYFUNCTION("""COMPUTED_VALUE"""),"Success") -> Success
A36: =IFERROR(__xludf.DUMMYFUNCTION("""COMPUTED_VALUE"""),46170.352268518516) -> 46170.352 | B36: =IFERROR(__xludf.DUMMYFUNCTION("""COMPUTED_VALUE"""),46170.0) -> 46170 | C36: =IFERROR(__xludf.DUMMYFUNCTION("""COMPUTED_VALUE"""),"dc04eef4") -> dc04eef4 | D36: =IFERROR(__xludf.DUMMYFUNCTION("""COMPUTED_VALUE"""),"Joshua Jung") -> Joshua Jung | E36: =IFERROR(__xludf.DUMMYFUNCTION("""COMPUTED_VALUE"""),10.0) -> 10 | F36: =IFERROR(__xludf.DUMMYFUNCTION("""COMPUTED_VALUE"""),"HS202") -> HS202 | G36: =IFERROR(__xludf.DUMMYFUNCTION("""COMPUTED_VALUE"""),"Homeroom") -> Homeroom | H36: =IFERROR(__xludf.DUMMYFUNCTION("""COMPUTED_VALUE"""),"Present") -> Present | I36: =IFERROR(__xludf.DUMMYFUNCTION("""COMPUTED_VALUE"""),0.35226851851851854) -> 0.35226852 | J36: =IFERROR(__xludf.DUMMYFUNCTION("""COMPUTED_VALUE"""),1.0) -> 1 | K36: =IFERROR(__xludf.DUMMYFUNCTION("""COMPUTED_VALUE"""),10.0) -> 10 | L36: =IFERROR(__xludf.DUMMYFUNCTION("""COMPUTED_VALUE"""),"On-time reward applied") -> On-time reward applied | M36: =IFERROR(__xludf.DUMMYFUNCTION("""COMPUTED_VALUE"""),"Success") -> Success
A37: =IFERROR(__xludf.DUMMYFUNCTION("""COMPUTED_VALUE"""),46170.35403935185) -> 46170.354 | B37: =IFERROR(__xludf.DUMMYFUNCTION("""COMPUTED_VALUE"""),46170.0) -> 46170 | C37: =IFERROR(__xludf.DUMMYFUNCTION("""COMPUTED_VALUE"""),"babde4c4") -> babde4c4 | D37: =IFERROR(__xludf.DUMMYFUNCTION("""COMPUTED_VALUE"""),"Ashley Guk") -> Ashley Guk | E37: =IFERROR(__xludf.DUMMYFUNCTION("""COMPUTED_VALUE"""),10.0) -> 10 | F37: =IFERROR(__xludf.DUMMYFUNCTION("""COMPUTED_VALUE"""),"HS202") -> HS202 | G37: =IFERROR(__xludf.DUMMYFUNCTION("""COMPUTED_VALUE"""),"Homeroom") -> Homeroom | H37: =IFERROR(__xludf.DUMMYFUNCTION("""COMPUTED_VALUE"""),"Present") -> Present | I37: =IFERROR(__xludf.DUMMYFUNCTION("""COMPUTED_VALUE"""),0.35403935185185187) -> 0.35403935 | J37: =IFERROR(__xludf.DUMMYFUNCTION("""COMPUTED_VALUE"""),1.0) -> 1 | K37: =IFERROR(__xludf.DUMMYFUNCTION("""COMPUTED_VALUE"""),10.0) -> 10 | L37: =IFERROR(__xludf.DUMMYFUNCTION("""COMPUTED_VALUE"""),"On-time reward applied") -> On-time reward applied | M37: =IFERROR(__xludf.DUMMYFUNCTION("""COMPUTED_VALUE"""),"Success") -> Success
A38: =IFERROR(__xludf.DUMMYFUNCTION("""COMPUTED_VALUE"""),46170.35628472222) -> 46170.356 | B38: =IFERROR(__xludf.DUMMYFUNCTION("""COMPUTED_VALUE"""),46170.0) -> 46170 | C38: =IFERROR(__xludf.DUMMYFUNCTION("""COMPUTED_VALUE"""),"ba353911") -> ba353911 | D38: =IFERROR(__xludf.DUMMYFUNCTION("""COMPUTED_VALUE"""),"Dayeon Kang") -> Dayeon Kang | E38: =IFERROR(__xludf.DUMMYFUNCTION("""COMPUTED_VALUE"""),10.0) -> 10 | F38: =IFERROR(__xludf.DUMMYFUNCTION("""COMPUTED_VALUE"""),"HS202") -> HS202 | G38: =IFERROR(__xludf.DUMMYFUNCTION("""COMPUTED_VALUE"""),"Homeroom") -> Homeroom | H38: =IFERROR(__xludf.DUMMYFUNCTION("""COMPUTED_VALUE"""),"Present") -> Present | I38: =IFERROR(__xludf.DUMMYFUNCTION("""COMPUTED_VALUE"""),0.35628472222222224) -> 0.35628472 | J38: =IFERROR(__xludf.DUMMYFUNCTION("""COMPUTED_VALUE"""),1.0) -> 1 | K38: =IFERROR(__xludf.DUMMYFUNCTION("""COMPUTED_VALUE"""),10.0) -> 10 | L38: =IFERROR(__xludf.DUMMYFUNCTION("""COMPUTED_VALUE"""),"On-time reward applied") -> On-time reward applied | M38: =IFERROR(__xludf.DUMMYFUNCTION("""COMPUTED_VALUE"""),"Success") -> Success
A39: =IFERROR(__xludf.DUMMYFUNCTION("""COMPUTED_VALUE"""),46170.35795138889) -> 46170.358 | B39: =IFERROR(__xludf.DUMMYFUNCTION("""COMPUTED_VALUE"""),46170.0) -> 46170 | C39: =IFERROR(__xludf.DUMMYFUNCTION("""COMPUTED_VALUE"""),"9a5f2811") -> 9a5f2811 | D39: =IFERROR(__xludf.DUMMYFUNCTION("""COMPUTED_VALUE"""),"Junyoung Yoo") -> Junyoung Yoo | E39: =IFERROR(__xludf.DUMMYFUNCTION("""COMPUTED_VALUE"""),10.0) -> 10 | F39: =IFERROR(__xludf.DUMMYFUNCTION("""COMPUTED_VALUE"""),"HS202") -> HS202 | G39: =IFERROR(__xludf.DUMMYFUNCTION("""COMPUTED_VALUE"""),"Homeroom") -> Homeroom | H39: =IFERROR(__xludf.DUMMYFUNCTION("""COMPUTED_VALUE"""),"Present") -> Present | I39: =IFERROR(__xludf.DUMMYFUNCTION("""COMPUTED_VALUE"""),0.3579513888888889) -> 0.35795139 | J39: =IFERROR(__xludf.DUMMYFUNCTION("""COMPUTED_VALUE"""),1.0) -> 1 | K39: =IFERROR(__xludf.DUMMYFUNCTION("""COMPUTED_VALUE"""),10.0) -> 10 | L39: =IFERROR(__xludf.DUMMYFUNCTION("""COMPUTED_VALUE"""),"On-time reward applied") -> On-time reward applied | M39: =IFERROR(__xludf.DUMMYFUNCTION("""COMPUTED_VALUE"""),"Success") -> Success
A40: =IFERROR(__xludf.DUMMYFUNCTION("""COMPUTED_VALUE"""),46170.3725) -> 46170.372 | B40: =IFERROR(__xludf.DUMMYFUNCTION("""COMPUTED_VALUE"""),46170.0) -> 46170 | C40: =IFERROR(__xludf.DUMMYFUNCTION("""COMPUTED_VALUE"""),"1e3e1410") -> 1e3e1410 | D40: =IFERROR(__xludf.DUMMYFUNCTION("""COMPUTED_VALUE"""),"Junjae Park") -> Junjae Park | E40: =IFERROR(__xludf.DUMMYFUNCTION("""COMPUTED_VALUE"""),10.0) -> 10 | F40: =IFERROR(__xludf.DUMMYFUNCTION("""COMPUTED_VALUE"""),"HS202") -> HS202 | G40: =IFERROR(__xludf.DUMMYFUNCTION("""COMPUTED_VALUE"""),"Homeroom") -> Homeroom | H40: =IFERROR(__xludf.DUMMYFUNCTION("""COMPUTED_VALUE"""),"Late") -> Late | I40: =IFERROR(__xludf.DUMMYFUNCTION("""COMPUTED_VALUE"""),0.3725) -> 0.3725 | J40: =IFERROR(__xludf.DUMMYFUNCTION("""COMPUTED_VALUE"""),0.0) -> 0 | K40: =IFERROR(__xludf.DUMMYFUNCTION("""COMPUTED_VALUE"""),0.0) -> 0 | L40: =IFERROR(__xludf.DUMMYFUNCTION("""COMPUTED_VALUE"""),"Late penalty applied") -> Late penalty applied | M40: =IFERROR(__xludf.DUMMYFUNCTION("""COMPUTED_VALUE"""),"Success") -> Success
A41: =IFERROR(__xludf.DUMMYFUNCTION("""COMPUTED_VALUE"""),46170.37265046296) -> 46170.373 | B41: =IFERROR(__xludf.DUMMYFUNCTION("""COMPUTED_VALUE"""),46170.0) -> 46170 | C41: =IFERROR(__xludf.DUMMYFUNCTION("""COMPUTED_VALUE"""),"ba0fc5c4") -> ba0fc5c4 | D41: =IFERROR(__xludf.DUMMYFUNCTION("""COMPUTED_VALUE"""),"Junwoo Kang") -> Junwoo Kang | E41: =IFERROR(__xludf.DUMMYFUNCTION("""COMPUTED_VALUE"""),10.0) -> 10 | F41: =IFERROR(__xludf.DUMMYFUNCTION("""COMPUTED_VALUE"""),"HS202") -> HS202 | G41: =IFERROR(__xludf.DUMMYFUNCTION("""COMPUTED_VALUE"""),"Homeroom") -> Homeroom | H41: =IFERROR(__xludf.DUMMYFUNCTION("""COMPUTED_VALUE"""),"Late") -> Late | I41: =IFERROR(__xludf.DUMMYFUNCTION("""COMPUTED_VALUE"""),0.37265046296296295) -> 0.37265046 | J41: =IFERROR(__xludf.DUMMYFUNCTION("""COMPUTED_VALUE"""),0.0) -> 0 | K41: =IFERROR(__xludf.DUMMYFUNCTION("""COMPUTED_VALUE"""),0.0) -> 0 | L41: =IFERROR(__xludf.DUMMYFUNCTION("""COMPUTED_VALUE"""),"Late penalty not applied: insufficient balance") -> Late penalty not applied: insufficient balance | M41: =IFERROR(__xludf.DUMMYFUNCTION("""COMPUTED_VALUE"""),"Success") -> Success
A42: =IFERROR(__xludf.DUMMYFUNCTION("""COMPUTED_VALUE"""),46174.34792824074) -> 46174.348 | B42: =IFERROR(__xludf.DUMMYFUNCTION("""COMPUTED_VALUE"""),46174.0) -> 46174 | C42: =IFERROR(__xludf.DUMMYFUNCTION("""COMPUTED_VALUE"""),"ae072910") -> ae072910 | D42: =IFERROR(__xludf.DUMMYFUNCTION("""COMPUTED_VALUE"""),"Selena Jung") -> Selena Jung | E42: =IFERROR(__xludf.DUMMYFUNCTION("""COMPUTED_VALUE"""),10.0) -> 10 | F42: =IFERROR(__xludf.DUMMYFUNCTION("""COMPUTED_VALUE"""),"HS202") -> HS202 | G42: =IFERROR(__xludf.DUMMYFUNCTION("""COMPUTED_VALUE"""),"Homeroom") -> Homeroom | H42: =IFERROR(__xludf.DUMMYFUNCTION("""COMPUTED_VALUE"""),"Present") -> Present | I42: =IFERROR(__xludf.DUMMYFUNCTION("""COMPUTED_VALUE"""),0.34792824074074075) -> 0.34792824 | J42: =IFERROR(__xludf.DUMMYFUNCTION("""COMPUTED_VALUE"""),1.0) -> 1 | K42: =IFERROR(__xludf.DUMMYFUNCTION("""COMPUTED_VALUE"""),10.0) -> 10 | L42: =IFERROR(__xludf.DUMMYFUNCTION("""COMPUTED_VALUE"""),"On-time reward applied") -> On-time reward applied | M42: =IFERROR(__xludf.DUMMYFUNCTION("""COMPUTED_VALUE"""),"Success") -> Success
A43: =IFERROR(__xludf.DUMMYFUNCTION("""COMPUTED_VALUE"""),46174.34815972222) -> 46174.348 | B43: =IFERROR(__xludf.DUMMYFUNCTION("""COMPUTED_VALUE"""),46174.0) -> 46174 | C43: =IFERROR(__xludf.DUMMYFUNCTION("""COMPUTED_VALUE"""),"5c07fef4") -> 5c07fef4 | D43: =IFERROR(__xludf.DUMMYFUNCTION("""COMPUTED_VALUE"""),"Tiffany Kim") -> Tiffany Kim | E43: =IFERROR(__xludf.DUMMYFUNCTION("""COMPUTED_VALUE"""),10.0) -> 10 | F43: =IFERROR(__xludf.DUMMYFUNCTION("""COMPUTED_VALUE"""),"HS202") -> HS202 | G43: =IFERROR(__xludf.DUMMYFUNCTION("""COMPUTED_VALUE"""),"Homeroom") -> Homeroom | H43: =IFERROR(__xludf.DUMMYFUNCTION("""COMPUTED_VALUE"""),"Present") -> Present | I43: =IFERROR(__xludf.DUMMYFUNCTION("""COMPUTED_VALUE"""),0.34815972222222225) -> 0.34815972 | J43: =IFERROR(__xludf.DUMMYFUNCTION("""COMPUTED_VALUE"""),1.0) -> 1 | K43: =IFERROR(__xludf.DUMMYFUNCTION("""COMPUTED_VALUE"""),10.0) -> 10 | L43: =IFERROR(__xludf.DUMMYFUNCTION("""COMPUTED_VALUE"""),"On-time reward applied") -> On-time reward applied | M43: =IFERROR(__xludf.DUMMYFUNCTION("""COMPUTED_VALUE"""),"Success") -> Success
A44: =IFERROR(__xludf.DUMMYFUNCTION("""COMPUTED_VALUE"""),46174.34831018518) -> 46174.348 | B44: =IFERROR(__xludf.DUMMYFUNCTION("""COMPUTED_VALUE"""),46174.0) -> 46174 | C44: =IFERROR(__xludf.DUMMYFUNCTION("""COMPUTED_VALUE"""),"dc04eef4") -> dc04eef4 | D44: =IFERROR(__xludf.DUMMYFUNCTION("""COMPUTED_VALUE"""),"Joshua Jung") -> Joshua Jung | E44: =IFERROR(__xludf.DUMMYFUNCTION("""COMPUTED_VALUE"""),10.0) -> 10 | F44: =IFERROR(__xludf.DUMMYFUNCTION("""COMPUTED_VALUE"""),"HS202") -> HS202 | G44: =IFERROR(__xludf.DUMMYFUNCTION("""COMPUTED_VALUE"""),"Homeroom") -> Homeroom | H44: =IFERROR(__xludf.DUMMYFUNCTION("""COMPUTED_VALUE"""),"Present") -> Present | I44: =IFERROR(__xludf.DUMMYFUNCTION("""COMPUTED_VALUE"""),0.3483101851851852) -> 0.34831019 | J44: =IFERROR(__xludf.DUMMYFUNCTION("""COMPUTED_VALUE"""),1.0) -> 1 | K44: =IFERROR(__xludf.DUMMYFUNCTION("""COMPUTED_VALUE"""),10.0) -> 10 | L44: =IFERROR(__xludf.DUMMYFUNCTION("""COMPUTED_VALUE"""),"On-time reward applied") -> On-time reward applied | M44: =IFERROR(__xludf.DUMMYFUNCTION("""COMPUTED_VALUE"""),"Success") -> Success
A45: =IFERROR(__xludf.DUMMYFUNCTION("""COMPUTED_VALUE"""),46174.34914351852) -> 46174.349 | B45: =IFERROR(__xludf.DUMMYFUNCTION("""COMPUTED_VALUE"""),46174.0) -> 46174 | C45: =IFERROR(__xludf.DUMMYFUNCTION("""COMPUTED_VALUE"""),"ba912211") -> ba912211 | D45: =IFERROR(__xludf.DUMMYFUNCTION("""COMPUTED_VALUE"""),"Daisy Dou") -> Daisy Dou | E45: =IFERROR(__xludf.DUMMYFUNCTION("""COMPUTED_VALUE"""),10.0) -> 10 | F45: =IFERROR(__xludf.DUMMYFUNCTION("""COMPUTED_VALUE"""),"HS202") -> HS202 | G45: =IFERROR(__xludf.DUMMYFUNCTION("""COMPUTED_VALUE"""),"Homeroom") -> Homeroom | H45: =IFERROR(__xludf.DUMMYFUNCTION("""COMPUTED_VALUE"""),"Present") -> Present | I45: =IFERROR(__xludf.DUMMYFUNCTION("""COMPUTED_VALUE"""),0.3491435185185185) -> 0.34914352 | J45: =IFERROR(__xludf.DUMMYFUNCTION("""COMPUTED_VALUE"""),1.0) -> 1 | K45: =IFERROR(__xludf.DUMMYFUNCTION("""COMPUTED_VALUE"""),10.0) -> 10 | L45: =IFERROR(__xludf.DUMMYFUNCTION("""COMPUTED_VALUE"""),"On-time reward applied") -> On-time reward applied | M45: =IFERROR(__xludf.DUMMYFUNCTION("""COMPUTED_VALUE"""),"Success") -> Success
A46: =IFERROR(__xludf.DUMMYFUNCTION("""COMPUTED_VALUE"""),46174.353125) -> 46174.353 | B46: =IFERROR(__xludf.DUMMYFUNCTION("""COMPUTED_VALUE"""),46174.0) -> 46174 | C46: =IFERROR(__xludf.DUMMYFUNCTION("""COMPUTED_VALUE"""),"babde4c4") -> babde4c4 | D46: =IFERROR(__xludf.DUMMYFUNCTION("""COMPUTED_VALUE"""),"Ashley Guk") -> Ashley Guk | E46: =IFERROR(__xludf.DUMMYFUNCTION("""COMPUTED_VALUE"""),10.0) -> 10 | F46: =IFERROR(__xludf.DUMMYFUNCTION("""COMPUTED_VALUE"""),"HS202") -> HS202 | G46: =IFERROR(__xludf.DUMMYFUNCTION("""COMPUTED_VALUE"""),"Homeroom") -> Homeroom | H46: =IFERROR(__xludf.DUMMYFUNCTION("""COMPUTED_VALUE"""),"Present") -> Present | I46: =IFERROR(__xludf.DUMMYFUNCTION("""COMPUTED_VALUE"""),0.353125) -> 0.353125 | J46: =IFERROR(__xludf.DUMMYFUNCTION("""COMPUTED_VALUE"""),1.0) -> 1 | K46: =IFERROR(__xludf.DUMMYFUNCTION("""COMPUTED_VALUE"""),10.0) -> 10 | L46: =IFERROR(__xludf.DUMMYFUNCTION("""COMPUTED_VALUE"""),"On-time reward applied") -> On-time reward applied | M46: =IFERROR(__xludf.DUMMYFUNCTION("""COMPUTED_VALUE"""),"Success") -> Success
A47: =IFERROR(__xludf.DUMMYFUNCTION("""COMPUTED_VALUE"""),46174.35418981482) -> 46174.354 | B47: =IFERROR(__xludf.DUMMYFUNCTION("""COMPUTED_VALUE"""),46174.0) -> 46174 | C47: =IFERROR(__xludf.DUMMYFUNCTION("""COMPUTED_VALUE"""),"ba353911") -> ba353911 | D47: =IFERROR(__xludf.DUMMYFUNCTION("""COMPUTED_VALUE"""),"Dayeon Kang") -> Dayeon Kang | E47: =IFERROR(__xludf.DUMMYFUNCTION("""COMPUTED_VALUE"""),10.0) -> 10 | F47: =IFERROR(__xludf.DUMMYFUNCTION("""COMPUTED_VALUE"""),"HS202") -> HS202 | G47: =IFERROR(__xludf.DUMMYFUNCTION("""COMPUTED_VALUE"""),"Homeroom") -> Homeroom | H47: =IFERROR(__xludf.DUMMYFUNCTION("""COMPUTED_VALUE"""),"Present") -> Present | I47: =IFERROR(__xludf.DUMMYFUNCTION("""COMPUTED_VALUE"""),0.3541898148148148) -> 0.35418981 | J47: =IFERROR(__xludf.DUMMYFUNCTION("""COMPUTED_VALUE"""),1.0) -> 1 | K47: =IFERROR(__xludf.DUMMYFUNCTION("""COMPUTED_VALUE"""),10.0) -> 10 | L47: =IFERROR(__xludf.DUMMYFUNCTION("""COMPUTED_VALUE"""),"On-time reward applied") -> On-time reward applied | M47: =IFERROR(__xludf.DUMMYFUNCTION("""COMPUTED_VALUE"""),"Success") -> Success
A48: =IFERROR(__xludf.DUMMYFUNCTION("""COMPUTED_VALUE"""),46174.35523148148) -> 46174.355 | B48: =IFERROR(__xludf.DUMMYFUNCTION("""COMPUTED_VALUE"""),46174.0) -> 46174 | C48: =IFERROR(__xludf.DUMMYFUNCTION("""COMPUTED_VALUE"""),"7c4e261e") -> 7c4e261e | D48: =IFERROR(__xludf.DUMMYFUNCTION("""COMPUTED_VALUE"""),"Suha Lee") -> Suha Lee | E48: =IFERROR(__xludf.DUMMYFUNCTION("""COMPUTED_VALUE"""),10.0) -> 10 | F48: =IFERROR(__xludf.DUMMYFUNCTION("""COMPUTED_VALUE"""),"HS202") -> HS202 | G48: =IFERROR(__xludf.DUMMYFUNCTION("""COMPUTED_VALUE"""),"Homeroom") -> Homeroom | H48: =IFERROR(__xludf.DUMMYFUNCTION("""COMPUTED_VALUE"""),"Present") -> Present | I48: =IFERROR(__xludf.DUMMYFUNCTION("""COMPUTED_VALUE"""),0.3552314814814815) -> 0.35523148 | J48: =IFERROR(__xludf.DUMMYFUNCTION("""COMPUTED_VALUE"""),1.0) -> 1 | K48: =IFERROR(__xludf.DUMMYFUNCTION("""COMPUTED_VALUE"""),10.0) -> 10 | L48: =IFERROR(__xludf.DUMMYFUNCTION("""COMPUTED_VALUE"""),"On-time reward applied") -> On-time reward applied | M48: =IFERROR(__xludf.DUMMYFUNCTION("""COMPUTED_VALUE"""),"Success") -> Success
A49: =IFERROR(__xludf.DUMMYFUNCTION("""COMPUTED_VALUE"""),46174.36565972222) -> 46174.366 | B49: =IFERROR(__xludf.DUMMYFUNCTION("""COMPUTED_VALUE"""),46174.0) -> 46174 | C49: =IFERROR(__xludf.DUMMYFUNCTION("""COMPUTED_VALUE"""),"5a032611") -> 5a032611 | D49: =IFERROR(__xludf.DUMMYFUNCTION("""COMPUTED_VALUE"""),"Harold Dou") -> Harold Dou | E49: =IFERROR(__xludf.DUMMYFUNCTION("""COMPUTED_VALUE"""),10.0) -> 10 | F49: =IFERROR(__xludf.DUMMYFUNCTION("""COMPUTED_VALUE"""),"HS202") -> HS202 | G49: =IFERROR(__xludf.DUMMYFUNCTION("""COMPUTED_VALUE"""),"Homeroom") -> Homeroom | H49: =IFERROR(__xludf.DUMMYFUNCTION("""COMPUTED_VALUE"""),"Late") -> Late | I49: =IFERROR(__xludf.DUMMYFUNCTION("""COMPUTED_VALUE"""),0.3656597222222222) -> 0.36565972 | J49: =IFERROR(__xludf.DUMMYFUNCTION("""COMPUTED_VALUE"""),0.0) -> 0 | K49: =IFERROR(__xludf.DUMMYFUNCTION("""COMPUTED_VALUE"""),0.0) -> 0 | L49: =IFERROR(__xludf.DUMMYFUNCTION("""COMPUTED_VALUE"""),"Late penalty applied") -> Late penalty applied | M49: =IFERROR(__xludf.DUMMYFUNCTION("""COMPUTED_VALUE"""),"Success") -> Success
A50: =IFERROR(__xludf.DUMMYFUNCTION("""COMPUTED_VALUE"""),46174.367685185185) -> 46174.368 | B50: =IFERROR(__xludf.DUMMYFUNCTION("""COMPUTED_VALUE"""),46174.0) -> 46174 | C50: =IFERROR(__xludf.DUMMYFUNCTION("""COMPUTED_VALUE"""),"9a5f2811") -> 9a5f2811 | D50: =IFERROR(__xludf.DUMMYFUNCTION("""COMPUTED_VALUE"""),"Junyoung Yoo") -> Junyoung Yoo | E50: =IFERROR(__xludf.DUMMYFUNCTION("""COMPUTED_VALUE"""),10.0) -> 10 | F50: =IFERROR(__xludf.DUMMYFUNCTION("""COMPUTED_VALUE"""),"HS202") -> HS202 | G50: =IFERROR(__xludf.DUMMYFUNCTION("""COMPUTED_VALUE"""),"Homeroom") -> Homeroom | H50: =IFERROR(__xludf.DUMMYFUNCTION("""COMPUTED_VALUE"""),"Late") -> Late | I50: =IFERROR(__xludf.DUMMYFUNCTION("""COMPUTED_VALUE"""),0.36768518518518517) -> 0.36768519 | J50: =IFERROR(__xludf.DUMMYFUNCTION("""COMPUTED_VALUE"""),0.0) -> 0 | K50: =IFERROR(__xludf.DUMMYFUNCTION("""COMPUTED_VALUE"""),0.0) -> 0 | L50: =IFERROR(__xludf.DUMMYFUNCTION("""COMPUTED_VALUE"""),"Late penalty applied") -> Late penalty applied | M50: =IFERROR(__xludf.DUMMYFUNCTION("""COMPUTED_VALUE"""),"Success") -> Success
A51: =IFERROR(__xludf.DUMMYFUNCTION("""COMPUTED_VALUE"""),46174.369108796294) -> 46174.369 | B51: =IFERROR(__xludf.DUMMYFUNCTION("""COMPUTED_VALUE"""),46174.0) -> 46174 | C51: =IFERROR(__xludf.DUMMYFUNCTION("""COMPUTED_VALUE"""),"ba0fc5c4") -> ba0fc5c4 | D51: =IFERROR(__xludf.DUMMYFUNCTION("""COMPUTED_VALUE"""),"Junwoo Kang") -> Junwoo Kang | E51: =IFERROR(__xludf.DUMMYFUNCTION("""COMPUTED_VALUE"""),10.0) -> 10 | F51: =IFERROR(__xludf.DUMMYFUNCTION("""COMPUTED_VALUE"""),"HS202") -> HS202 | G51: =IFERROR(__xludf.DUMMYFUNCTION("""COMPUTED_VALUE"""),"Homeroom") -> Homeroom | H51: =IFERROR(__xludf.DUMMYFUNCTION("""COMPUTED_VALUE"""),"Late") -> Late | I51: =IFERROR(__xludf.DUMMYFUNCTION("""COMPUTED_VALUE"""),0.3691087962962963) -> 0.3691088 | J51: =IFERROR(__xludf.DUMMYFUNCTION("""COMPUTED_VALUE"""),0.0) -> 0 | K51: =IFERROR(__xludf.DUMMYFUNCTION("""COMPUTED_VALUE"""),0.0) -> 0 | L51: =IFERROR(__xludf.DUMMYFUNCTION("""COMPUTED_VALUE"""),"Late penalty not applied: insufficient balance") -> Late penalty not applied: insufficient balance | M51: =IFERROR(__xludf.DUMMYFUNCTION("""COMPUTED_VALUE"""),"Success") -> Success
A52: =IFERROR(__xludf.DUMMYFUNCTION("""COMPUTED_VALUE"""),46174.37559027778) -> 46174.376 | B52: =IFERROR(__xludf.DUMMYFUNCTION("""COMPUTED_VALUE"""),46174.0) -> 46174 | C52: =IFERROR(__xludf.DUMMYFUNCTION("""COMPUTED_VALUE"""),"1e3e1410") -> 1e3e1410 | D52: =IFERROR(__xludf.DUMMYFUNCTION("""COMPUTED_VALUE"""),"Junjae Park") -> Junjae Park | E52: =IFERROR(__xludf.DUMMYFUNCTION("""COMPUTED_VALUE"""),10.0) -> 10 | F52: =IFERROR(__xludf.DUMMYFUNCTION("""COMPUTED_VALUE"""),"HS202") -> HS202 | G52: =IFERROR(__xludf.DUMMYFUNCTION("""COMPUTED_VALUE"""),"Homeroom") -> Homeroom | H52: =IFERROR(__xludf.DUMMYFUNCTION("""COMPUTED_VALUE"""),"Late") -> Late | I52: =IFERROR(__xludf.DUMMYFUNCTION("""COMPUTED_VALUE"""),0.37559027777777776) -> 0.37559028 | J52: =IFERROR(__xludf.DUMMYFUNCTION("""COMPUTED_VALUE"""),0.0) -> 0 | K52: =IFERROR(__xludf.DUMMYFUNCTION("""COMPUTED_VALUE"""),0.0) -> 0 | L52: =IFERROR(__xludf.DUMMYFUNCTION("""COMPUTED_VALUE"""),"Late penalty applied") -> Late penalty applied | M52: =IFERROR(__xludf.DUMMYFUNCTION("""COMPUTED_VALUE"""),"Success") -> Success
A53: =IFERROR(__xludf.DUMMYFUNCTION("""COMPUTED_VALUE"""),46175.34787037037) -> 46175.348 | B53: =IFERROR(__xludf.DUMMYFUNCTION("""COMPUTED_VALUE"""),46175.0) -> 46175 | C53: =IFERROR(__xludf.DUMMYFUNCTION("""COMPUTED_VALUE"""),"5c07fef4") -> 5c07fef4 | D53: =IFERROR(__xludf.DUMMYFUNCTION("""COMPUTED_VALUE"""),"Tiffany Kim") -> Tiffany Kim | E53: =IFERROR(__xludf.DUMMYFUNCTION("""COMPUTED_VALUE"""),10.0) -> 10 | F53: =IFERROR(__xludf.DUMMYFUNCTION("""COMPUTED_VALUE"""),"HS202") -> HS202 | G53: =IFERROR(__xludf.DUMMYFUNCTION("""COMPUTED_VALUE"""),"Homeroom") -> Homeroom | H53: =IFERROR(__xludf.DUMMYFUNCTION("""COMPUTED_VALUE"""),"Present") -> Present | I53: =IFERROR(__xludf.DUMMYFUNCTION("""COMPUTED_VALUE"""),0.3478703703703704) -> 0.34787037 | J53: =IFERROR(__xludf.DUMMYFUNCTION("""COMPUTED_VALUE"""),2.0) -> 2 | K53: =IFERROR(__xludf.DUMMYFUNCTION("""COMPUTED_VALUE"""),10.0) -> 10 | L53: =IFERROR(__xludf.DUMMYFUNCTION("""COMPUTED_VALUE"""),"On-time reward applied") -> On-time reward applied | M53: =IFERROR(__xludf.DUMMYFUNCTION("""COMPUTED_VALUE"""),"Success") -> Success
A54: =IFERROR(__xludf.DUMMYFUNCTION("""COMPUTED_VALUE"""),46175.34984953704) -> 46175.35 | B54: =IFERROR(__xludf.DUMMYFUNCTION("""COMPUTED_VALUE"""),46175.0) -> 46175 | C54: =IFERROR(__xludf.DUMMYFUNCTION("""COMPUTED_VALUE"""),"ae072910") -> ae072910 | D54: =IFERROR(__xludf.DUMMYFUNCTION("""COMPUTED_VALUE"""),"Selena Jung") -> Selena Jung | E54: =IFERROR(__xludf.DUMMYFUNCTION("""COMPUTED_VALUE"""),10.0) -> 10 | F54: =IFERROR(__xludf.DUMMYFUNCTION("""COMPUTED_VALUE"""),"HS202") -> HS202 | G54: =IFERROR(__xludf.DUMMYFUNCTION("""COMPUTED_VALUE"""),"Homeroom") -> Homeroom | H54: =IFERROR(__xludf.DUMMYFUNCTION("""COMPUTED_VALUE"""),"Present") -> Present | I54: =IFERROR(__xludf.DUMMYFUNCTION("""COMPUTED_VALUE"""),0.34984953703703703) -> 0.34984954 | J54: =IFERROR(__xludf.DUMMYFUNCTION("""COMPUTED_VALUE"""),2.0) -> 2 | K54: =IFERROR(__xludf.DUMMYFUNCTION("""COMPUTED_VALUE"""),10.0) -> 10 | L54: =IFERROR(__xludf.DUMMYFUNCTION("""COMPUTED_VALUE"""),"On-time reward applied") -> On-time reward applied | M54: =IFERROR(__xludf.DUMMYFUNCTION("""COMPUTED_VALUE"""),"Success") -> Success
A55: =IFERROR(__xludf.DUMMYFUNCTION("""COMPUTED_VALUE"""),46175.35034722222) -> 46175.35 | B55: =IFERROR(__xludf.DUMMYFUNCTION("""COMPUTED_VALUE"""),46175.0) -> 46175 | C55: =IFERROR(__xludf.DUMMYFUNCTION("""COMPUTED_VALUE"""),"dc04eef4") -> dc04eef4 | D55: =IFERROR(__xludf.DUMMYFUNCTION("""COMPUTED_VALUE"""),"Joshua Jung") -> Joshua Jung | E55: =IFERROR(__xludf.DUMMYFUNCTION("""COMPUTED_VALUE"""),10.0) -> 10 | F55: =IFERROR(__xludf.DUMMYFUNCTION("""COMPUTED_VALUE"""),"HS202") -> HS202 | G55: =IFERROR(__xludf.DUMMYFUNCTION("""COMPUTED_VALUE"""),"Homeroom") -> Homeroom | H55: =IFERROR(__xludf.DUMMYFUNCTION("""COMPUTED_VALUE"""),"Present") -> Present | I55: =IFERROR(__xludf.DUMMYFUNCTION("""COMPUTED_VALUE"""),0.3503472222222222) -> 0.35034722 | J55: =IFERROR(__xludf.DUMMYFUNCTION("""COMPUTED_VALUE"""),2.0) -> 2 | K55: =IFERROR(__xludf.DUMMYFUNCTION("""COMPUTED_VALUE"""),10.0) -> 10 | L55: =IFERROR(__xludf.DUMMYFUNCTION("""COMPUTED_VALUE"""),"On-time reward applied") -> On-time reward applied | M55: =IFERROR(__xludf.DUMMYFUNCTION("""COMPUTED_VALUE"""),"Success") -> Success
A56: =IFERROR(__xludf.DUMMYFUNCTION("""COMPUTED_VALUE"""),46175.35125) -> 46175.351 | B56: =IFERROR(__xludf.DUMMYFUNCTION("""COMPUTED_VALUE"""),46175.0) -> 46175 | C56: =IFERROR(__xludf.DUMMYFUNCTION("""COMPUTED_VALUE"""),"ba912211") -> ba912211 | D56: =IFERROR(__xludf.DUMMYFUNCTION("""COMPUTED_VALUE"""),"Daisy Dou") -> Daisy Dou | E56: =IFERROR(__xludf.DUMMYFUNCTION("""COMPUTED_VALUE"""),10.0) -> 10 | F56: =IFERROR(__xludf.DUMMYFUNCTION("""COMPUTED_VALUE"""),"HS202") -> HS202 | G56: =IFERROR(__xludf.DUMMYFUNCTION("""COMPUTED_VALUE"""),"Homeroom") -> Homeroom | H56: =IFERROR(__xludf.DUMMYFUNCTION("""COMPUTED_VALUE"""),"Present") -> Present | I56: =IFERROR(__xludf.DUMMYFUNCTION("""COMPUTED_VALUE"""),0.35125) -> 0.35125 | J56: =IFERROR(__xludf.DUMMYFUNCTION("""COMPUTED_VALUE"""),2.0) -> 2 | K56: =IFERROR(__xludf.DUMMYFUNCTION("""COMPUTED_VALUE"""),10.0) -> 10 | L56: =IFERROR(__xludf.DUMMYFUNCTION("""COMPUTED_VALUE"""),"On-time reward applied") -> On-time reward applied | M56: =IFERROR(__xludf.DUMMYFUNCTION("""COMPUTED_VALUE"""),"Success") -> Success
A57: =IFERROR(__xludf.DUMMYFUNCTION("""COMPUTED_VALUE"""),46175.352476851855) -> 46175.352 | B57: =IFERROR(__xludf.DUMMYFUNCTION("""COMPUTED_VALUE"""),46175.0) -> 46175 | C57: =IFERROR(__xludf.DUMMYFUNCTION("""COMPUTED_VALUE"""),"babde4c4") -> babde4c4 | D57: =IFERROR(__xludf.DUMMYFUNCTION("""COMPUTED_VALUE"""),"Ashley Guk") -> Ashley Guk | E57: =IFERROR(__xludf.DUMMYFUNCTION("""COMPUTED_VALUE"""),10.0) -> 10 | F57: =IFERROR(__xludf.DUMMYFUNCTION("""COMPUTED_VALUE"""),"HS202") -> HS202 | G57: =IFERROR(__xludf.DUMMYFUNCTION("""COMPUTED_VALUE"""),"Homeroom") -> Homeroom | H57: =IFERROR(__xludf.DUMMYFUNCTION("""COMPUTED_VALUE"""),"Present") -> Present | I57: =IFERROR(__xludf.DUMMYFUNCTION("""COMPUTED_VALUE"""),0.35247685185185185) -> 0.35247685 | J57: =IFERROR(__xludf.DUMMYFUNCTION("""COMPUTED_VALUE"""),2.0) -> 2 | K57: =IFERROR(__xludf.DUMMYFUNCTION("""COMPUTED_VALUE"""),10.0) -> 10 | L57: =IFERROR(__xludf.DUMMYFUNCTION("""COMPUTED_VALUE"""),"On-time reward applied") -> On-time reward applied | M57: =IFERROR(__xludf.DUMMYFUNCTION("""COMPUTED_VALUE"""),"Success") -> Success
A58: =IFERROR(__xludf.DUMMYFUNCTION("""COMPUTED_VALUE"""),46175.35579861111) -> 46175.356 | B58: =IFERROR(__xludf.DUMMYFUNCTION("""COMPUTED_VALUE"""),46175.0) -> 46175 | C58: =IFERROR(__xludf.DUMMYFUNCTION("""COMPUTED_VALUE"""),"9a5f2811") -> 9a5f2811 | D58: =IFERROR(__xludf.DUMMYFUNCTION("""COMPUTED_VALUE"""),"Junyoung Yoo") -> Junyoung Yoo | E58: =IFERROR(__xludf.DUMMYFUNCTION("""COMPUTED_VALUE"""),10.0) -> 10 | F58: =IFERROR(__xludf.DUMMYFUNCTION("""COMPUTED_VALUE"""),"HS202") -> HS202 | G58: =IFERROR(__xludf.DUMMYFUNCTION("""COMPUTED_VALUE"""),"Homeroom") -> Homeroom | H58: =IFERROR(__xludf.DUMMYFUNCTION("""COMPUTED_VALUE"""),"Present") -> Present | I58: =IFERROR(__xludf.DUMMYFUNCTION("""COMPUTED_VALUE"""),0.3557986111111111) -> 0.35579861 | J58: =IFERROR(__xludf.DUMMYFUNCTION("""COMPUTED_VALUE"""),1.0) -> 1 | K58: =IFERROR(__xludf.DUMMYFUNCTION("""COMPUTED_VALUE"""),10.0) -> 10 | L58: =IFERROR(__xludf.DUMMYFUNCTION("""COMPUTED_VALUE"""),"On-time reward applied") -> On-time reward applied | M58: =IFERROR(__xludf.DUMMYFUNCTION("""COMPUTED_VALUE"""),"Success") -> Success
A59: =IFERROR(__xludf.DUMMYFUNCTION("""COMPUTED_VALUE"""),46175.35594907407) -> 46175.356 | B59: =IFERROR(__xludf.DUMMYFUNCTION("""COMPUTED_VALUE"""),46175.0) -> 46175 | C59: =IFERROR(__xludf.DUMMYFUNCTION("""COMPUTED_VALUE"""),"1e3e1410") -> 1e3e1410 | D59: =IFERROR(__xludf.DUMMYFUNCTION("""COMPUTED_VALUE"""),"Junjae Park") -> Junjae Park | E59: =IFERROR(__xludf.DUMMYFUNCTION("""COMPUTED_VALUE"""),10.0) -> 10 | F59: =IFERROR(__xludf.DUMMYFUNCTION("""COMPUTED_VALUE"""),"HS202") -> HS202 | G59: =IFERROR(__xludf.DUMMYFUNCTION("""COMPUTED_VALUE"""),"Homeroom") -> Homeroom | H59: =IFERROR(__xludf.DUMMYFUNCTION("""COMPUTED_VALUE"""),"Present") -> Present | I59: =IFERROR(__xludf.DUMMYFUNCTION("""COMPUTED_VALUE"""),0.35594907407407406) -> 0.35594907 | J59: =IFERROR(__xludf.DUMMYFUNCTION("""COMPUTED_VALUE"""),1.0) -> 1 | K59: =IFERROR(__xludf.DUMMYFUNCTION("""COMPUTED_VALUE"""),10.0) -> 10 | L59: =IFERROR(__xludf.DUMMYFUNCTION("""COMPUTED_VALUE"""),"On-time reward applied") -> On-time reward applied | M59: =IFERROR(__xludf.DUMMYFUNCTION("""COMPUTED_VALUE"""),"Success") -> Success
A60: =IFERROR(__xludf.DUMMYFUNCTION("""COMPUTED_VALUE"""),46175.35625) -> 46175.356 | B60: =IFERROR(__xludf.DUMMYFUNCTION("""COMPUTED_VALUE"""),46175.0) -> 46175 | C60: =IFERROR(__xludf.DUMMYFUNCTION("""COMPUTED_VALUE"""),"ba353911") -> ba353911 | D60: =IFERROR(__xludf.DUMMYFUNCTION("""COMPUTED_VALUE"""),"Dayeon Kang") -> Dayeon Kang | E60: =IFERROR(__xludf.DUMMYFUNCTION("""COMPUTED_VALUE"""),10.0) -> 10 | F60: =IFERROR(__xludf.DUMMYFUNCTION("""COMPUTED_VALUE"""),"HS202") -> HS202 | G60: =IFERROR(__xludf.DUMMYFUNCTION("""COMPUTED_VALUE"""),"Homeroom") -> Homeroom | H60: =IFERROR(__xludf.DUMMYFUNCTION("""COMPUTED_VALUE"""),"Present") -> Present | I60: =IFERROR(__xludf.DUMMYFUNCTION("""COMPUTED_VALUE"""),0.35625) -> 0.35625 | J60: =IFERROR(__xludf.DUMMYFUNCTION("""COMPUTED_VALUE"""),2.0) -> 2 | K60: =IFERROR(__xludf.DUMMYFUNCTION("""COMPUTED_VALUE"""),10.0) -> 10 | L60: =IFERROR(__xludf.DUMMYFUNCTION("""COMPUTED_VALUE"""),"On-time reward applied") -> On-time reward applied | M60: =IFERROR(__xludf.DUMMYFUNCTION("""COMPUTED_VALUE"""),"Success") -> Success
A61: =IFERROR(__xludf.DUMMYFUNCTION("""COMPUTED_VALUE"""),46175.3575462963) -> 46175.358 | B61: =IFERROR(__xludf.DUMMYFUNCTION("""COMPUTED_VALUE"""),46175.0) -> 46175 | C61: =IFERROR(__xludf.DUMMYFUNCTION("""COMPUTED_VALUE"""),"5a032611") -> 5a032611 | D61: =IFERROR(__xludf.DUMMYFUNCTION("""COMPUTED_VALUE"""),"Harold Dou") -> Harold Dou | E61: =IFERROR(__xludf.DUMMYFUNCTION("""COMPUTED_VALUE"""),10.0) -> 10 | F61: =IFERROR(__xludf.DUMMYFUNCTION("""COMPUTED_VALUE"""),"HS202") -> HS202 | G61: =IFERROR(__xludf.DUMMYFUNCTION("""COMPUTED_VALUE"""),"Homeroom") -> Homeroom | H61: =IFERROR(__xludf.DUMMYFUNCTION("""COMPUTED_VALUE"""),"Present") -> Present | I61: =IFERROR(__xludf.DUMMYFUNCTION("""COMPUTED_VALUE"""),0.3575462962962963) -> 0.3575463 | J61: =IFERROR(__xludf.DUMMYFUNCTION("""COMPUTED_VALUE"""),1.0) -> 1 | K61: =IFERROR(__xludf.DUMMYFUNCTION("""COMPUTED_VALUE"""),10.0) -> 10 | L61: =IFERROR(__xludf.DUMMYFUNCTION("""COMPUTED_VALUE"""),"On-time reward applied") -> On-time reward applied | M61: =IFERROR(__xludf.DUMMYFUNCTION("""COMPUTED_VALUE"""),"Success") -> Success
A62: =IFERROR(__xludf.DUMMYFUNCTION("""COMPUTED_VALUE"""),46175.35768518518) -> 46175.358 | B62: =IFERROR(__xludf.DUMMYFUNCTION("""COMPUTED_VALUE"""),46175.0) -> 46175 | C62: =IFERROR(__xludf.DUMMYFUNCTION("""COMPUTED_VALUE"""),"7c4e261e") -> 7c4e261e | D62: =IFERROR(__xludf.DUMMYFUNCTION("""COMPUTED_VALUE"""),"Suha Lee") -> Suha Lee | E62: =IFERROR(__xludf.DUMMYFUNCTION("""COMPUTED_VALUE"""),10.0) -> 10 | F62: =IFERROR(__xludf.DUMMYFUNCTION("""COMPUTED_VALUE"""),"HS202") -> HS202 | G62: =IFERROR(__xludf.DUMMYFUNCTION("""COMPUTED_VALUE"""),"Homeroom") -> Homeroom | H62: =IFERROR(__xludf.DUMMYFUNCTION("""COMPUTED_VALUE"""),"Present") -> Present | I62: =IFERROR(__xludf.DUMMYFUNCTION("""COMPUTED_VALUE"""),0.35768518518518516) -> 0.35768519 | J62: =IFERROR(__xludf.DUMMYFUNCTION("""COMPUTED_VALUE"""),2.0) -> 2 | K62: =IFERROR(__xludf.DUMMYFUNCTION("""COMPUTED_VALUE"""),10.0) -> 10 | L62: =IFERROR(__xludf.DUMMYFUNCTION("""COMPUTED_VALUE"""),"On-time reward applied") -> On-time reward applied | M62: =IFERROR(__xludf.DUMMYFUNCTION("""COMPUTED_VALUE"""),"Success") -> Success
A63: =IFERROR(__xludf.DUMMYFUNCTION("""COMPUTED_VALUE"""),46175.37440972222) -> 46175.374 | B63: =IFERROR(__xludf.DUMMYFUNCTION("""COMPUTED_VALUE"""),46175.0) -> 46175 | C63: =IFERROR(__xludf.DUMMYFUNCTION("""COMPUTED_VALUE"""),"ba0fc5c4") -> ba0fc5c4 | D63: =IFERROR(__xludf.DUMMYFUNCTION("""COMPUTED_VALUE"""),"Junwoo Kang") -> Junwoo Kang | E63: =IFERROR(__xludf.DUMMYFUNCTION("""COMPUTED_VALUE"""),10.0) -> 10 | F63: =IFERROR(__xludf.DUMMYFUNCTION("""COMPUTED_VALUE"""),"HS202") -> HS202 | G63: =IFERROR(__xludf.DUMMYFUNCTION("""COMPUTED_VALUE"""),"Homeroom") -> Homeroom | H63: =IFERROR(__xludf.DUMMYFUNCTION("""COMPUTED_VALUE"""),"Late") -> Late | I63: =IFERROR(__xludf.DUMMYFUNCTION("""COMPUTED_VALUE"""),0.37440972222222224) -> 0.37440972 | J63: =IFERROR(__xludf.DUMMYFUNCTION("""COMPUTED_VALUE"""),0.0) -> 0 | K63: =IFERROR(__xludf.DUMMYFUNCTION("""COMPUTED_VALUE"""),0.0) -> 0 | L63: =IFERROR(__xludf.DUMMYFUNCTION("""COMPUTED_VALUE"""),"Late penalty not applied: insufficient balance") -> Late penalty not applied: insufficient balance | M63: =IFERROR(__xludf.DUMMYFUNCTION("""COMPUTED_VALUE"""),"Success") -> Success
